Workbook
Name DataIVA: #REF!
Name RangoNombre2: R_CLIENTES!$A:$A
Name RegiPeri: #REF!
Name RangoNombre1: R_CLIENTES!$1:$1000
Name ListPeri: #REF!
Name R_CLIENTES: R_CLIENTES!$1:$1000
Name DataBanc: #REF!
Name DataVend: #REF!

Sheet Modelo Cotización
G2: Nro de Cotización:
G3: 82
D9: Sucursales: Marco Gallo Vergara 536 B, Dpto 411 Torre D | AE9: =G3 -> 82
D10: Casa Matriz: Huerfanos, 1055 Oficina 503
D11: Giro: Servicios de Seguridad y Cerrajería
D12: eMail: ventas@polygonos.cl
D13: Fono: 9-81334980 | AD13: ="Fecha de Cotización: " & TEXT(IFERROR(VLOOKUP($AE$9, R_COTIZACIONES!$A$6:$B1000, 2, FALSE), ""), "dd-mm-yyyy") -> Fecha de Cotización: 04-03-2026
D14: Vendedor: Maximo Hudson / maximo.hudson.blanco@gmail.com
D16: Nombre Cliente: | L16: =IFERROR(VLOOKUP($AE$9, R_COTIZACIONES!$A$6:$G1000, 5, FALSE), "Sin contacto") -> Diego Palma
D17: R.U.T.: | G17: =IFERROR(VLOOKUP($AE$9, R_COTIZACIONES!$A:$C, 3, FALSE), "") -> 65.066.845-6
D18: Razon Social: | K18: =IFERROR(VLOOKUP($AE$9, R_COTIZACIONES!$A:$E, 4, FALSE), "No encontrado") -> Condominio Ossandon
D19: Dirección: | I19: =IFERROR(VLOOKUP(VLOOKUP($AE$9, R_COTIZACIONES!$A$6:$C1000, 3, FALSE), R_CLIENTES!$A$3:$C1000, 3, FALSE), "Dirección no encontrada") -> Av Ossandón 60
D20: Comuna: | I20: =IFERROR(VLOOKUP(VLOOKUP($AE$9, R_COTIZACIONES!$A$6:$C1000, 3, FALSE), R_CLIENTES!$A$3:$D1000, 4, FALSE), "") -> Coquimbo | S20: Telefono: | W20: {=IFERROR(VLOOKUP(TRIM($AE$9), TRIM(R_COTIZACIONES!$A:$G), 7, FALSE), "No encontrado")} -> 9 9969 8228
D21: Correo: | H21: =IFERROR(VLOOKUP(VLOOKUP($AE$9, R_COTIZACIONES!$A$6:$C1000, 3, FALSE), R_CLIENTES!$A$3:$I1000, 9, FALSE), "Correo no registrado") -> admossandon@gmail.com
D23: Código | I23: Descripción | AB23: Cantidad | AG23: Valor Uni | AM23: % Desc. | AQ23: Sub Total
A24: 1 | B24: =CONCATENATE($AE$9,"a",A24) -> 82a1 | D24: =IFERROR(__xludf.DUMMYFUNCTION("IFERROR(FILTER('Detalle Cotización'!H:H, 'Detalle Cotización'!B:B = $AE$9), """")"),"S18") -> S18 | I24: =IFERROR(__xludf.DUMMYFUNCTION("IFERROR(FILTER('Detalle Cotización'!I:I, 'Detalle Cotización'!B:B = $AE$9), """")"),"Servicio CCTV e Infraestrcutura para exteriores y 2 cámaras en poste.") -> Servicio CCTV e Infraestrcutura para exteriores y 2 cámaras en poste. | AD24: =IFERROR(__xludf.DUMMYFUNCTION("IFERROR(FILTER('Detalle Cotización'!J4:J1000, 'Detalle Cotización'!B4:B1000 = $AE$9), """")"),1.0) -> 1 | AG24: =IFERROR(__xludf.DUMMYFUNCTION("IFERROR(FILTER('Detalle Cotización'!K:K, 'Detalle Cotización'!B:B = $AE$9), """")"),3640000.0) -> 3640000 | AM24: =IFERROR(__xludf.DUMMYFUNCTION("IFERROR(FILTER('Detalle Cotización'!L4:L1000, 'Detalle Cotización'!B4:B1000 = $AE$9), """")"),0.0) -> 0 | AQ24: =IFERROR(__xludf.DUMMYFUNCTION("IFERROR(FILTER('Detalle Cotización'!M4:M1000, 'Detalle Cotización'!B4:B1000 = $AE$9), """")"),3640000.0) -> 3640000
A25: 2 | B25: =CONCATENATE($AE$9,"a",A25) -> 82a2
A26: 3 | B26: =CONCATENATE($AE$9,"a",A26) -> 82a3
A27: 4 | B27: =CONCATENATE($AE$9,"a",A27) -> 82a4
A28: 5 | B28: =CONCATENATE($AE$9,"a",A28) -> 82a5
A29: 6 | B29: =CONCATENATE($AE$9,"a",A29) -> 82a6
A30: 7 | B30: =CONCATENATE($AE$9,"a",A30) -> 82a7
A31: 8 | B31: =CONCATENATE($AE$9,"a",A31) -> 82a8
A32: 9 | B32: =CONCATENATE($AE$9,"a",A32) -> 82a9
A33: 10 | B33: =CONCATENATE($AE$9,"a",A33) -> 82a10
A34: 11 | B34: =CONCATENATE($AE$9,"a",A34) -> 82a11
A35: 12 | B35: =CONCATENATE($AE$9,"a",A35) -> 82a12
A36: 13 | B36: =CONCATENATE($AE$9,"a",A36) -> 82a13
... A38: 15 | B38: =CONCATENATE($AE$9,"a",A38) -> 82a15
D40: Comentarios: | AL40: Total Neto | AM40: =SUM(AQ24:AV38) -> 3640000
D41: =IFERROR(VLOOKUP($AE$9, R_COTIZACIONES!$A$4:$Q1000, 14, FALSE), "") -> Valor CCTV cámaras exteriores (2) e infraestructura base CCTV IP.
AL42: Total | AM42: =SUM(AM40:AP41) -> 3640000
D45: Forma de Pago:
D46: =IFERROR(VLOOKUP($AE$9, R_COTIZACIONES!$A$4:$Q1000, 9, FALSE), "") -> 50 anticipo y 50 al finalizar
D49: Terminos y Condiciones:
D50: 1-. El trabajo de ejecuta posterior a la aceptación de la cotización y coordinación de fecha de instalación y entrega.
D51: 2-. No refiere stock ni fecha de instalación.
D52: 3-. Cotización válida por 15 días.
D54: Pagos en transferencia, efectivo o cheque a nombre de:
D56: ='Base de datos'!C3 -> Polygonos SPA RUT: 77.180.437-3 Banco Santander Cta. Cte. 99128755 Correo: maximo.hudson.blanco@gmail.com
D58: Aceptación del cliente (Nombre, Rut y firma del cliente):
D60: x

Sheet Base de datos
A2: Aplicar IVA | B2: Vendedor | C2: Datos Bancarios
A3: Si | B3: Maximo Hudson | C3: Polygonos SPA RUT: 77.180.437-3 Banco Santander Cta. Cte. 99128755 Correo: maximo.hudson.blanco@gmail.com | F3: Costos CCTV (Proveedores)
A4: no | B4: Maximo Hudson | C4: Maximo Hudson 26074100-4 Banco Santander Cta. Cte.: 75 36164 5 Correo: maximo.hudson.blanco@gmail.com | E4: Cod | F4: Producto | G4: Modelo | H4: Proveedor | I4: Link publicado | J4: Valor publicado | K4: Neto | L4: IVA | M4: Margen | N4: Precio Venta | O4: Cant | P4: Total | Q4: Utilidad
E5: N32 | F5: NVR | G5: NVR4232-4KS3 | H5: Smart Secure | I5: Link | J5: 190324 | K5: =J5/1.19 -> 159936.13 | L5: =J5-K5 -> 30387.866 | M5: =J5*0.6 -> 114194.4 | N5: =J5+M5 -> 304518.4 | O5: 1 | P5: =N5 -> 304518.4 | Q5: =P5/1.6 -> 190324
A6: Periodo | E6: N32-E | F6: NVR | G6: NVR4232-4KS3 | H6: IAI Tech | I6: Link | J6: 182000 | K6: =J6/1.19 -> 152941.18 | L6: =J6-K6 -> 29058.824 | M6: =J6*0.6 -> 109200 | N6: =J6+M6 -> 291200 | O6: 1 | P6: =N6 -> 291200 | Q6: =P6/1.6 -> 182000
A7: Hoy | B7: =TODAY() -> 46088 | C7: =TODAY() -> 46088 | E7: H4TB | F7: HDD 4 TB | G7: ST4000VX015 | H7: Smart Secure | I7: Link | J7: 135096 | K7: =J7/1.19 -> 113526.05 | L7: =J7-K7 -> 21569.95 | M7: =J7*0.6 -> 81057.6 | N7: =J7+M7 -> 216153.6 | O7: 2 | P7: =N7*O7 -> 432307.2 | Q7: =P7/1.6 -> 270192
A8: Enero | B8: 45658 | C8: 45688 | E8: H6TB | F8: HDD 6 TB | G8: WD60EFFX | H8: IAI Tech | I8: Link | J8: 219990 | K8: =J8/1.19 -> 184865.55 | L8: =J8-K8 -> 35124.454 | M8: =J8*0.6 -> 131994 | N8: =J8+M8 -> 351984 | O8: 1 | P8: =N8*O8 -> 351984 | Q8: =P8/1.6 -> 219990
A9: Febrero | B9: 45689 | C9: 45716 | E9: UPS15 | F9: UPS 1500 VA | G9: DH-PFM350-900-A | H9: Smart Secure | I9: Link | J9: 84238 | K9: =J9/1.19 -> 70788.235 | L9: =J9-K9 -> 13449.765 | M9: =J9*0.6 -> 50542.8 | N9: =J9+M9 -> 134780.8 | O9: 2 | P9: =N9*O9 -> 269561.6 | Q9: =P9/1.6 -> 168476
A10: Marzo | B10: 45717 | C10: 45747 | E10: UPS15 | F10: UPS 1500 VA | G10: MR-UF1500 | H10: IAI Tech | I10: Link | J10: 116991 | K10: =J10/1.19 -> 98311.765 | L10: =J10-K10 -> 18679.235 | M10: =J10*0.6 -> 70194.6 | N10: =J10+M10 -> 187185.6 | O10: 2 | P10: =N10*O10 -> 374371.2 | Q10: =P10/1.6 -> 233982
A11: Abril | B11: 45748 | C11: 45777 | E11: SW24 | F11: Switch 24 | G11: DH-CS4228-24GT-240 | H11: IAI Tech | I11: Link | J11: 349550 | K11: =J11/1.19 -> 293739.5 | L11: =J11-K11 -> 55810.504 | M11: =J11*0.6 -> 209730 | N11: =J11+M11 -> 559280 | O11: 1 | P11: =N11*O11 -> 559280 | Q11: =P11/1.6 -> 349550
A12: Mayo | B12: 45778 | C12: 45808 | E12: SW24 | F12: Switch 24 | G12: DH-CS4228-24GT-240 | H12: Smart Secure | I12: Link | J12: 240211 | K12: =J12/1.19 -> 201857.98 | L12: =J12-K12 -> 38353.017 | M12: =J12*0.6 -> 144126.6 | N12: =J12+M12 -> 384337.6 | O12: 1 | P12: =N12*O12 -> 384337.6 | Q12: =P12/1.6 -> 240211
A13: Junio | B13: 45809 | C13: 45838 | E13: SW8 | F13: Switch 8 | G13: DH-PFS3010-8ET-65 | H13: Smart Secure | I13: Link | J13: 63603 | K13: =J13/1.19 -> 53447.899 | L13: =J13-K13 -> 10155.101 | M13: =J13*0.6 -> 38161.8 | N13: =J13+M13 -> 101764.8 | O13: 2 | P13: =N13*O13 -> 203529.6 | Q13: =P13/1.6 -> 127206
A14: Julio | B14: 45839 | C14: 45869 | E14: SW8 | F14: Switch 8 | G14: POE208-100MB | H14: IAI Tech | I14: Link | J14: 36400 | K14: =J14/1.19 -> 30588.235 | L14: =J14-K14 -> 5811.7647 | M14: =J14*0.6 -> 21840 | N14: =J14+M14 -> 58240 | O14: 2 | P14: =N14*O14 -> 116480 | Q14: =P14/1.6 -> 72800
A15: Agosto | B15: 45870 | C15: 45900 | E15: SW4 | F15: Switch 4 | G15: DH-PFS3006-4ET-36 | H15: Smart Secure | I15: Link | J15: 35079 | K15: =J15/1.19 -> 29478.151 | L15: =J15-K15 -> 5600.8487 | M15: =J15*0.6 -> 21047.4 | N15: =J15+M15 -> 56126.4 | O15: 3 | P15: =N15*O15 -> 168379.2 | Q15: =P15/1.6 -> 105237
A16: Septiembre | B16: 45901 | C16: 45930 | E16: SW4 | F16: Switch 4 | G16: POE204-100MB | H16: IAI Tech | I16: Link | J16: 23600 | K16: =J16/1.19 -> 19831.933 | L16: =J16-K16 -> 3768.0672 | M16: =J16*0.6 -> 14160 | N16: =J16+M16 -> 37760 | O16: 3 | P16: =N16*O16 -> 113280 | Q16: =P16/1.6 -> 70800
A17: Octubre | B17: 45931 | C17: 45961 | E17: RC20 | F17: Router Inalambrico | G17: Archer C20 | H17: Smart Secure | I17: Link | J17: 25368 | K17: =J17/1.19 -> 21317.647 | L17: =J17-K17 -> 4050.3529 | M17: =J17*0.6 -> 15220.8 | N17: =J17+M17 -> 40588.8 | O17: 1 | P17: =N17*O17 -> 40588.8 | Q17: =P17/1.6 -> 25368
A18: Noviembre | B18: 45962 | C18: 45991 | E18: RC21 | F18: Router Inalambrico | G18: RG-EW1200G PRO | H18: IAI Tech | I18: Link | J18: 41500 | K18: =J18/1.19 -> 34873.95 | L18: =J18-K18 -> 6626.0504 | M18: =J18*0.6 -> 24900 | N18: =J18+M18 -> 66400 | O18: 1 | P18: =N18*O18 -> 66400 | Q18: =P18/1.6 -> 41500
A19: Diciembre | B19: 45992 | C19: 46022 | E19: UBIM5 | F19: Antenas | G19: Loco M5 (par) | H19: Clickbox | I19: Link | J19: 155990 | K19: =J19/1.19 -> 131084.03 | L19: =J19-K19 -> 24905.966 | M19: =J19*0.6 -> 93594 | N19: =J19+M19 -> 249584 | O19: 4 | P19: =N19*O19 -> 998336 | Q19: =P19/1.6 -> 623960
E20: CPE51 | F20: Antenas | G20: WI-CPE511H-KIT | H20: ANTENASCHILE | I20: Link | J20: 119990 | K20: =J20/1.19 -> 100831.93 | L20: =J20-K20 -> 19158.067 | M20: =J20*0.6 -> 71994 | N20: =J20+M20 -> 191984 | O20: 4 | P20: =N20*O20 -> 767936 | Q20: =P20/1.6 -> 479960
A21: 2024 | E21: 1230T1 | F21: Camara Domo | G21: DH-IPC-HDW1230T1-0280B | H21: Smart Secure | I21: Link | J21: 44061 | K21: =J21/1.19 -> 37026.05 | L21: =J21-K21 -> 7034.9496 | M21: =J21*0.6 -> 26436.6 | N21: =J21+M21 -> 70497.6 | O21: 18 | P21: =N21*O21 -> 1268956.8 | Q21: =P21/1.6 -> 793098
A22: Enero | B22: 45292 | C22: 45322 | E22: 1430T1 | F22: Camara Domo | G22: DH-IPC-HDW1431T1P-A-0280B-S6 | H22: IAI Tech | I22: Link | J22: 52191 | K22: =J22/1.19 -> 43857.983 | L22: =J22-K22 -> 8333.0168 | M22: =J22*0.6 -> 31314.6 | N22: =J22+M22 -> 83505.6 | O22: 18 | P22: =N22*O22 -> 1503100.8 | Q22: =P22/1.6 -> 939438
A23: Febrero | B23: 45323 | C23: 45350 | E23: 1239S1 | F23: Cámara Bullet | G23: DH-IPC-HFW1239S1-LED-0280B | H23: Smart Secure | I23: Link | J23: 43940 | K23: =J23/1.19 -> 36924.37 | L23: =J23-K23 -> 7015.6303 | M23: =J23*0.6 -> 26364 | N23: =J23+M23 -> 70304 | O23: 12 | P23: =N23*O23 -> 843648 | Q23: =P23/1.4 -> 602605.71
A24: Marzo | B24: 45352 | C24: 45382 | E24: 2249S | F24: Cámara Bullet | G24: DH-IPC-HFW2249S-S-IL | H24: IAI Tech | I24: Link | J24: 66591 | K24: =J24/1.19 -> 55958.824 | L24: =J24-K24 -> 10632.176 | M24: =J24*0.4 -> 26636.4 | N24: =J24+M24 -> 93227.4 | O24: 12 | P24: =N24*O24 -> 1118728.8 | Q24: =P24/1.4 -> 799092
A25: Abril | B25: 45383 | C25: 45412 | E25: 304020 | F25: Gabinete exteriores | G25: Gabinete Mural-304020 | H25: IAI Tech | I25: Link | J25: 37990 | K25: =J25/1.19 -> 31924.37 | L25: =J25-K25 -> 6065.6303 | M25: =J25*0.6 -> 22794 | N25: =J25+M25 -> 60784 | O25: 4 | P25: =N25*O25 -> 243136 | Q25: =P25/1.6 -> 151960
A26: Mayo | B26: 45413 | C26: 45443 | E26: 604550 | F26: Rack Gabinete interior | G26: Gabinete Rack 6U Dahua 600x450x501 | H26: Smart Secure | I26: Link | J26: 94070 | K26: =J26/1.19 -> 79050.42 | L26: =J26-K26 -> 15019.58 | M26: =J26*0.6 -> 56442 | N26: =J26+M26 -> 150512 | O26: 1 | P26: =N26*O26 -> 150512 | Q26: =P26/1.6 -> 94070
A27: Junio | B27: 45444 | C27: 45473 | E27: 534020 | F27: Rack Gabinete interior | G27: Gabinete Rack 4U Dahua 530X400X200 | H27: Smart Secure | I27: Link | J27: 60933 | K27: =J27/1.19 -> 51204.202 | L27: =J27-K27 -> 9728.7983 | M27: =J27*0.6 -> 36559.8 | N27: =J27+M27 -> 97492.8 | O27: 1 | P27: =N27*O27 -> 97492.8 | Q27: =P27/1.6 -> 60933
A28: Julio | B28: 45474 | C28: 45504 | E28: 534060 | F28: Rack Gabinete interior | G28: Gabinete Rack 12U Dahua 530x400x600 | H28: IAI Tech | I28: Link | J28: 102150 | K28: =J28/1.19 -> 85840.336 | L28: =J28-K28 -> 16309.664 | M28: =J28*0.6 -> 61290 | N28: =J28+M28 -> 163440 | O28: 1 | P28: =N28*O28 -> 163440 | Q28: =P28/1.6 -> 102150
A29: Agosto | B29: 45505 | C29: 45535 | E29: PATCH24 | F29: Patch panel | G29: Patch panel 24 puertos Cat 6 | H29: IAI Tech | I29: Link | J29: 15500 | K29: =J29/1.19 -> 13025.21 | L29: =J29-K29 -> 2474.7899 | M29: =J29*0.6 -> 9300 | N29: =J29+M29 -> 24800 | O29: 1 | P29: =N29*O29 -> 24800 | Q29: =P29/1.6 -> 15500
A30: Septiembre | B30: 45536 | C30: 45565 | E30: PATCH24 | F30: Patch panel | G30: Patch panel 24 puertos Cat 6 | H30: Clickbox | I30: Link | J30: 36295 | K30: =J30/1.19 -> 30500 | L30: =J30-K30 -> 5795 | M30: =J30*0.6 -> 21777 | N30: =J30+M30 -> 58072 | O30: 1 | P30: =N30*O30 -> 58072 | Q30: =P30/1.6 -> 36295
A31: Octubre | B31: 45566 | C31: 45596 | E31: PATCH972 | F31: Patch cord | G31: DH-PFM972-6U-2-S | H31: Smart Secure | I31: Link | J31: 2306 | K31: =J31/1.19 -> 1937.8151 | L31: =J31-K31 -> 368.18487 | M31: =J31*0.6 -> 1383.6 | N31: =J31+M31 -> 3689.6 | O31: 30 | P31: =N31*O31 -> 110688 | Q31: =P31/1.6 -> 69180
A32: Noviembre | B32: 45597 | C32: 45626 | E32: CAT6305 | F32: Caja de cable Cat 6 305 | G32: DH-PFM923I-6UN-C | H32: Smart Secure | I32: Link | J32: 135581 | K32: =J32/1.19 -> 113933.61 | L32: =J32-K32 -> 21647.387 | M32: =J32*0.6 -> 81348.6 | N32: =J32+M32 -> 216929.6 | O32: 4 | P32: =N32*O32 -> 867718.4 | Q32: =P32/1.6 -> 542324
A33: Diciembre | B33: 45627 | C33: 45657 | E33: CAT6100 | F33: Caja de cable Cat 6 100 | G33: DH-PFM920I-6UN-C-100 | H33: Smart Secure | I33: Link | J33: 47824 | K33: =J33/1.19 -> 40188.235 | L33: =J33-K33 -> 7635.7647 | M33: =J33*0.6 -> 28694.4 | N33: =J33+M33 -> 76518.4 | O33: 2 | P33: =N33*O33 -> 153036.8 | Q33: =P33/1.6 -> 95648
E34: CAN10050 | F34: Canaletas troncal 100x50 | G34: CANAL100X50 | H34: Moreto clima | I34: Link | J34: 7965 | K34: =J34/1.19 -> 6693.2773 | L34: =J34-K34 -> 1271.7227 | M34: =J34*0.6 -> 4779 | N34: =J34+M34 -> 12744 | O34: 20 | P34: =N34*O34 -> 254880 | Q34: =P34/1.6 -> 159300
A35: Forma de pago | B35: Estado | E35: CAE100100 | F35: Caja estanca 100x100 | G35: Cono 10010070 | H35: IAI Tech | I35: Link | J35: 2450 | K35: =J35/1.19 -> 2058.8235 | L35: =J35-K35 -> 391.17647 | M35: =J35*0.6 -> 1470 | N35: =J35+M35 -> 3920 | O35: 30 | P35: =N35*O35 -> 117600 | Q35: =P35/1.6 -> 73500
A36: Contado | B36: Aprobado
A37: 50 anticipo y 50 al finalizar | B37: Pendiente | F37: Costos Motores y Accesorios (Proveedores)
A38: 0 a 30 días | B38: Rechazado | E38: Cod | F38: Categoría | G38: Modelo | H38: Proveedor | I38: Link publicado | J38: Valor publicado | K38: Neto | L38: IVA | M38: Margen | N38: Precio Venta | O38: Cant | P38: Total | Q38: Utilidad
A39: Al finalizar | E39: D10S | F39: Motor Corredera | G39: D10 Standard | H39: RW | I39: N/A | J39: 639018 | K39: =J39/1.19 -> 536989.92 | L39: =J39-K39 -> 102028.08 | M39: =J39*0.6 -> 383410.8 | N39: =J39+M39 -> 1022428.8 | O39: 1 | P39: =N39 -> 1022428.8 | Q39: =P39/1.6 -> 639018
A40: 33% inicial 33% a 30 días y 33% a 60 días | K40: =J40/1.19 -> 0 | L40: =J40-K40 -> 0 | M40: =J40*0.6 -> 0 | N40: =J40+M40 -> 0 | P40: =N40 -> 0 | Q40: =P40/1.6 -> 0
E41: D10S | F41: Motor Corredera | G41: D10 Standard | H41: APACOM | I41: N/A | J41: 640208 | K41: =J41/1.19 -> 537989.92 | L41: =J41-K41 -> 102218.08 | M41: =J41*0.6 -> 384124.8 | N41: =J41+M41 -> 1024332.8 | O41: 1 | P41: =N41 -> 1024332.8 | Q41: =P41/1.6 -> 640208
A42: Nombre de proveedor | E42: D10SKIT | F42: Motor Corredera | G42: D10 Standard Kit 1(6 crem y 2 controles) | H42: RW | I42: N/A | J42: 700000 | K42: =J42/1.19 -> 588235.29 | L42: =J42-K42 -> 111764.71 | M42: =J42*0.6 -> 420000 | N42: =J42+M42 -> 1120000 | O42: 1 | P42: =N42*O42 -> 1120000 | Q42: =P42/1.6 -> 700000
A43: Smartsecure | E43: D10SKIT | F43: Motor Corredera | G43: D10 Standard Kit 1(6 crem y 2 controles) | H43: APACOM | I43: N/A | J43: 688926 | K43: =J43/1.19 -> 578929.41 | L43: =J43-K43 -> 109996.59 | M43: =J43*0.6 -> 413355.6 | N43: =J43+M43 -> 1102281.6 | O43: 1 | P43: =N43*O43 -> 1102281.6 | Q43: =P43/1.6 -> 688926
A44: IAI Tech | E44: D10T | F44: Motor Corredera | G44: D10 Turbo | H44: RW | I44: N/A | J44: 705628 | K44: =J44/1.19 -> 592964.71 | L44: =J44-K44 -> 112663.29 | M44: =J44*0.6 -> 423376.8 | N44: =J44+M44 -> 1129004.8 | O44: 1 | P44: =N44*O44 -> 1129004.8 | Q44: =P44/1.6 -> 705628
A45: Clickbox | E45: D10TKIT | F45: Motor Corredera | G45: D10 Turbo (6 crem y 2 controles) | H45: APACOM | I45: N/A | J45: 750806 | K45: =J45/1.19 -> 630929.41 | L45: =J45-K45 -> 119876.59 | M45: =J45*0.6 -> 450483.6 | N45: =J45+M45 -> 1201289.6 | O45: 1 | P45: =N45*O45 -> 1201289.6 | Q45: =P45/1.6 -> 750806
A46: ANTENASCHILE | E46: D10TKIT | F46: Motor Corredera | G46: D10 Turbo (6 crem y 2 controles) | H46: RW | I46: N/A | J46: 754377 | K46: =J46/1.19 -> 633930.25 | L46: =J46-K46 -> 120446.75 | M46: =J46*0.6 -> 452626.2 | N46: =J46+M46 -> 1207003.2 | O46: 1 | P46: =N46*O46 -> 1207003.2 | Q46: =P46/1.6 -> 754377
A47: Moreto Clima | E47: D10TKIT 2 | F47: Motor Corredera | G47: D10 (6 crem, 2 controles 1 par de Photosmart Fotoceldas Inalámbricas) | H47: APACOM | I47: N/A | J47: 813577 | K47: =J47/1.19 -> 683678.15 | L47: =J47-K47 -> 129898.85 | M47: =J47*0.5 -> 406788.5 | N47: =J47+M47 -> 1220365.5 | P47: =N47*O47 -> 0 | Q47: =P47/1.6 -> 0
A48: RW | E48: D6KIT | F48: Motor Corredera | G48: D6 (6 crem y 2 controles) | H48: APACOM | I48: N/A | J48: 519945 | K48: =J48/1.19 -> 436928.57 | L48: =J48-K48 -> 83016.429 | M48: =J48*0.6 -> 311967 | N48: =J48+M48 -> 831912 | O48: 1 | P48: =N48*O48 -> 831912 | Q48: =P48/1.6 -> 519945
A49: APACOM | E49: D6KIT 2 | F49: Motor Corredera | G49: D6 (6 crem y 2 controles) | H49: RW | I49: N/A | J49: 518780 | K49: =J49/1.19 -> 435949.58 | L49: =J49-K49 -> 82830.42 | M49: =J49*0.6 -> 311268 | N49: =J49+M49 -> 830048 | O49: 1 | P49: =N49*O49 -> 830048 | Q49: =P49/1.6 -> 518780
A50: PRODALAM | E50: D6KIT 3 | F50: Motor Corredera | G50: D6 (6 crem, 2 controles 1 par de Photosmart Fotoceldas Inalámbricas) | H50: APACOM | I50: N/A | J50: 578280 | K50: =J50/1.19 -> 485949.58 | L50: =J50-K50 -> 92330.42 | M50: =J50*0.6 -> 346968 | N50: =J50+M50 -> 925248 | P50: =N50*O50 -> 0 | Q50: =P50/1.6 -> 0
A51: ACENOR | E51: CRM1MT | F51: Cremalleras | G51: Cremallera Mt 1 mt | H51: APACOM | I51: N/A | J51: 7723 | K51: =J51/1.19 -> 6489.916 | L51: =J51-K51 -> 1233.084 | M51: =J51*0.6 -> 4633.8 | N51: =J51+M51 -> 12356.8 | O51: 1 | P51: =N51*O51 -> 12356.8 | Q51: =P51/1.6 -> 7723
A52: Particular | E52: CRM1MT | F52: Cremalleras | G52: Cremallera Mt 1 mt | H52: RW | I52: N/A | J52: 7723 | K52: =J52/1.19 -> 6489.916 | L52: =J52-K52 -> 1233.084 | M52: =J52*0.6 -> 4633.8 | N52: =J52+M52 -> 12356.8 | O52: 1 | P52: =N52*O52 -> 12356.8 | Q52: =P52/1.6 -> 7723
A53: PowerInverter | E53: CREM1N | F53: Cremalleras | G53: Cremallera Nylon 1 mt | H53: APACOM | I53: N/A | J53: 8318 | K53: =J53/1.19 -> 6989.916 | L53: =J53-K53 -> 1328.084 | M53: =J53*0.6 -> 4990.8 | N53: =J53+M53 -> 13308.8 | O53: 1 | P53: =N53*O53 -> 13308.8 | Q53: =P53/1.6 -> 8318
A54: Otro | E54: CREM1N | F54: Cremalleras | G54: Cremallera Nylon 1 mt | H54: RW | J54: 8318 | K54: =J54/1.19 -> 6989.916 | L54: =J54-K54 -> 1328.084 | M54: =J54*0.6 -> 4990.8 | N54: =J54+M54 -> 13308.8 | O54: 1 | P54: =N54*O54 -> 13308.8 | Q54: =P54/1.6 -> 8318
A55: SODIMAC | E55: PHSMRT | F55: Fotocelda | G55: Photon Smart (par) | H55: APACOM | I55: N/A | J55: 59488 | K55: =J55/1.19 -> 49989.916 | L55: =J55-K55 -> 9498.084 | M55: =J55*0.6 -> 35692.8 | N55: =J55+M55 -> 95180.8 | O55: 1 | P55: =N55*O55 -> 95180.8 | Q55: =P55/1.6 -> 59488
E56: PHSMRT | F56: Fotocelda | G56: Photon Smart (par) | H56: RW | I56: N/A | J56: 59488 | K56: =J56/1.19 -> 49989.916 | L56: =J56-K56 -> 9498.084 | M56: =J56*0.6 -> 35692.8 | N56: =J56+M56 -> 95180.8 | O56: 1 | P56: =N56*O56 -> 95180.8 | Q56: =P56/1.6 -> 59488
E57: NOVA2 | F57: Controles | G57: Control NOVA 2CH | H57: APACOM | I57: N/A | J57: 8913 | K57: =J57/1.19 -> 7489.916 | L57: =J57-K57 -> 1423.084 | M57: =J57*0.9 -> 8021.7 | N57: =J57+M57 -> 16934.7 | O57: 1 | P57: =N57*O57 -> 16934.7 | Q57: =P57/1.6 -> 10584.188
E58: NOVA2 | F58: Controles | G58: Control NOVA 2CH | H58: RW | I58: N/A | J58: 8913 | K58: =J58/1.19 -> 7489.916 | L58: =J58-K58 -> 1423.084 | M58: =J58*0.6 -> 5347.8 | N58: =J58+M58 -> 14260.8 | O58: 1 | P58: =N58*O58 -> 14260.8 | Q58: =P58/1.6 -> 8913
E59: WP17 | F59: Sistema Apertura | G59: Controlador Wifi WP17 | H59: RW | I59: N/A | J59: 80920 | K59: =J59/1.19 -> 68000 | L59: =J59-K59 -> 12920 | M59: =J59*200% -> 161840 | N59: =J59+M59 -> 242760 | O59: 1 | P59: =N59*O59 -> 242760 | Q59: =P59/1.6 -> 151725
E60: BALNC1224 | F60: Baliza | G60: Baliza NICE 12-38V | H60: APACOM | I60: N/A | J60: 32118 | K60: =J60/1.19 -> 26989.916 | L60: =J60-K60 -> 5128.084 | M60: =J60*0.6 -> 19270.8 | N60: =J60+M60 -> 51388.8 | O60: 1 | P60: =N60*O60 -> 51388.8 | Q60: =P60/1.6 -> 32118
E61: BALNC1225 | F61: Baliza | G61: Baliza NICE 12-38V | H61: RW | I61: N/A | J61: 56680 | K61: =J61/1.19 -> 47630.252 | L61: =J61-K61 -> 9049.7479 | M61: =J61*0.6 -> 34008 | N61: =J61+M61 -> 90688 | O61: 1 | P61: =N61*O61 -> 90688 | Q61: =P61/1.6 -> 56680
E62: KITG4060 | F62: Juego de guías | G62: Set de Guias 40x60 | H62: PRODALAM | I62: N/A | J62: 16699 | K62: =J62/1.19 -> 14032.773 | L62: =J62-K62 -> 2666.2269 | M62: =J62*0.6 -> 10019.4 | N62: =J62+M62 -> 26718.4 | O62: 1 | P62: =N62*O62 -> 26718.4 | Q62: =P62/1.6 -> 16699
E63: GN4060 | F63: Guias | G63: Guias Nylon 40x60 | H63: PRODALAM | I63: N/A | J63: 5788 | K63: =J63/1.19 -> 4863.8655 | L63: =J63-K63 -> 924.13445 | M63: =J63*1.1 -> 6366.8 | N63: =J63+M63 -> 12154.8 | O63: 1 | P63: =N63*O63 -> 12154.8 | Q63: =P63/1.6 -> 7596.75
E64: GN4060 | F64: Guias | G64: Guias Nylon 40x60 | H64: ACENOR | I64: N/A | J64: 4111 | K64: =J64/1.19 -> 3454.6218 | L64: =J64-K64 -> 656.37815 | M64: =J64*1.1 -> 4522.1 | N64: =J64+M64 -> 8633.1 | O64: 1 | P64: =N64*O64 -> 8633.1 | Q64: =P64/1.6 -> 5395.6875
E65: GN40120 | F65: Guias | G65: Guias Nylon 40x120 | H65: ACENOR | I65: N/A | J65: 9217 | K65: =J65/1.19 -> 7745.3782 | L65: =J65-K65 -> 1471.6218 | M65: =J65*1.1 -> 10138.7 | N65: =J65+M65 -> 19355.7 | O65: 1 | P65: =N65*O65 -> 19355.7 | Q65: =P65/1.6 -> 12097.312
E66: FERRV | F66: Ferretería | G66: Ferreterías varias | H66: Otro | I66: N/A | J66: 50000 | K66: =J66/1.19 -> 42016.807 | L66: =J66-K66 -> 7983.1933 | M66: =J66*1.1 -> 55000 | N66: =J66+M66 -> 105000 | O66: 1 | P66: =N66*O66 -> 105000 | Q66: =P66/1.6 -> 65625
E67: R100 | F67: Ruedas | G67: Ruedas c/ Pasador 100 mm | H67: PRODALAM | I67: N/A | J67: 12245 | K67: =J67/1.19 -> 10289.916 | L67: =J67-K67 -> 1955.084 | M67: =J67*1.1 -> 13469.5 | N67: =J67+M67 -> 25714.5 | O67: 1 | P67: =N67*O67 -> 25714.5 | Q67: =P67/1.6 -> 16071.562
E68: R100 | F68: Ruedas | G68: Ruedas c/ Pasador 100 mm | H68: ACENOR | I68: N/A | J68: 19987 | K68: =J68/1.19 -> 16795.798 | L68: =J68-K68 -> 3191.2017 | M68: =J68*1.1 -> 21985.7 | N68: =J68+M68 -> 41972.7 | O68: 1 | P68: =N68*O68 -> 41972.7 | Q68: =P68/1.6 -> 26232.938
F70: Costos Chapas, retenedores y accesorios (Proveedores)
E71: Cod | F71: Categoría | G71: Modelo | H71: Proveedor | I71: Link publicado | J71: Valor publicado | K71: Neto | L71: IVA | M71: Margen | N71: Precio Venta | O71: Cant | P71: Total | Q71: Utilidad
E72: 28OA | F72: Retenedor 280 KGs | G72: Dahua DHI-ASF280A-V1 | H72: Smart Secure | I72: Link | J72: 25163 | K72: =J72/1.19 -> 21145.378 | L72: =J72-K72 -> 4017.6218 | M72: =J72*1.9 -> 47809.7 | N72: =J72+M72 -> 72972.7 | O72: 1 | P72: =N72 -> 72972.7 | Q72: =P72/1.6 -> 45607.938
E73: 280HS | F73: Retenedor 280 KGs | G73: ZK Teco CM-280HS | H73: Smart Secure | I73: Link | J73: 29738 | K73: =J73/1.19 -> 24989.916 | L73: =J73-K73 -> 4748.084 | M73: =J73*1.6 -> 47580.8 | N73: =J73+M73 -> 77318.8 | P73: =N73 -> 77318.8 | Q73: =P73/1.6 -> 48324.25
E74: CM180H | F74: Retenedor 180 KGs | G74: ZK Teco CM-180H Retenedor electromagnético para puertas batientes | H74: Smart Secure | I74: Link | J74: 20548 | K74: =J74/1.19 -> 17267.227 | L74: =J74-K74 -> 3280.7731 | M74: =J74*1.9 -> 39041.2 | N74: =J74+M74 -> 59589.2 | O74: 1 | P74: =N74 -> 59589.2 | Q74: =P74/1.6 -> 37243.25
E75: TRGPLAS | F75: Pulsador Garita | G75: Pulsador de Salida Mecánico Plástico | H75: Otro | I75: Link | J75: 2960 | K75: =J75/1.19 -> 2487.395 | L75: =J75-K75 -> 472.60504 | M75: =J75*3 -> 8880 | N75: =J75+M75 -> 11840 | O75: 1 | P75: =N75*O75 -> 11840 | Q75: =P75/1.6 -> 7400
E76: SOPRET01 | F76: Soporte retenedor | G76: Soporte retenedor tipo L | H76: Smart Secure | I76: Link | J76: 8254 | K76: =J76/1.19 -> 6936.1345 | L76: =J76-K76 -> 1317.8655 | M76: =J76*2 -> 16508 | N76: =J76+M76 -> 24762 | O76: 1 | P76: =N76*O76 -> 24762 | Q76: =P76/1.6 -> 15476.25
E77: ASI1201E | F77: Control de acceso | G77: Control Acceso DHI-ASI1201E | H77: Smart Secure | I77: Link | J77: 57369 | K77: =J77/1.19 -> 48209.244 | L77: =J77-K77 -> 9159.7563 | M77: =J77*1.5 -> 86053.5 | N77: =J77+M77 -> 143422.5 | O77: 1 | P77: =N77*O77 -> 143422.5 | Q77: =P77/1.6 -> 89639.062
E78: ASI1201E-D | F78: Control de acceso | G78: Control Acceso ASI1201E-D | H78: Smart Secure | I78: Link | J78: 48698 | K78: =J78/1.19 -> 40922.689 | L78: =J78-K78 -> 7775.3109 | M78: =J78*1.5 -> 73047 | N78: =J78+M78 -> 121745 | O78: 1 | P78: =N78*O78 -> 121745 | Q78: =P78/1.6 -> 76090.625
E79: PLC12V | F79: Controladora 2 puertas | G79: Placa controladora 12V | H79: PowerInverter | I79: Link | J79: 60000 | K79: =J79/1.19 -> 50420.168 | L79: =J79-K79 -> 9579.8319 | M79: =J79*1.5 -> 90000 | N79: =J79+M79 -> 150000 | O79: 1 | P79: =N79*O79 -> 150000 | Q79: =P79/1.6 -> 93750
E80: S802MAX | F80: Cerradura Digital | G80: Cerradura digital App TUYA, teclado, huella y tarjeta c Cámara | H80: Claudio Quezada | I80: N/A | J80: 120000 | M80: =J80*1.5 -> 180000 | N80: =M80 -> 180000 | O80: 1 | P80: =N80*O80 -> 180000 | Q80: =M80-J80 -> 60000
E81: 958MAX | F81: Cerradura Digital | G81: Cerradura digital, App TUYA, teclado, huella y tarjeta c Reconocimiento facial | H81: Claudio Quezada | I81: N/A | J81: 170000 | M81: =J81*1.4 -> 238000 | N81: =M81 -> 238000 | O81: 1 | P81: =N81*O81 -> 238000 | Q81: =M81-J81 -> 68000
E82: S811 | F82: Cerradura Digital | G82: Cerradura digital básica, App TUYA, teclado, huella y tarjeta | H82: Claudio Quezada | I82: N/A | J82: 110000 | M82: =J82*1.5 -> 165000 | N82: =M82 -> 165000 | O82: 1 | P82: =N82*O82 -> 165000 | Q82: =M82-J82 -> 55000
E83: ASSABLOY | F83: Chapa exteriores | G83: Cerradura Eléctrica Poli Estándar 3010 Color Gris | H83: SODIMAC | I83: Link | J83: 56430 | K83: =J83/1.19 -> 47420.168 | L83: =J83-K83 -> 9009.8319 | M83: =J83*0.8 -> 45144 | N83: =J83+M83 -> 101574 | O83: 1 | P83: =N83*O83 -> 101574 | Q83: =P83/1.6 -> 63483.75
F85: Servicio (Instaladores)
E86: Cod | F86: Categoría | G86: Modelo | H86: Proveedor | I86: Link publicado | J86: Valor publicado | K86: Neto | L86: IVA | M86: Margen | N86: Precio Venta | O86: Cant | P86: Total | Q86: Utilidad
E87: S01 | F87: Servicio | G87: Instalación de motor (Solo) | H87: Particular | I87: N/A | J87: 100000 | K87: =J87/1.19 -> 84033.613 | L87: =J87-K87 -> 15966.387 | M87: =J87*0.6 -> 60000 | N87: =J87+M87 -> 160000 | O87: 1 | P87: =N87*O87 -> 160000 | Q87: =P87 -> 160000
E88: S01CIP | F88: Servicio | G88: Servicio de recuperación IP de cámara asociada a NVR | H88: Particular | I88: N/A | J88: 58012 | K88: =J88/1.19 -> 48749.58 | L88: =J88-K88 -> 9262.4202 | M88: =J88*0 -> 0 | N88: =J88+M88 -> 58012 | O88: 1 | P88: =N88*O88 -> 58012 | Q88: =P88 -> 58012
E89: S02GATOR | F89: Servicio | G89: Servicio de recuperación de dispositivo Protegus 2 | H89: Particular | I89: N/A | J89: 47600 | K89: =J89/1.19 -> 40000 | L89: =J89-K89 -> 7600 | M89: =J89*0 -> 0 | N89: =J89+M89 -> 47600 | O89: 1 | P89: =N89*O89 -> 47600 | Q89: =P89 -> 47600
E90: S02 | F90: Servicio | G90: Instalación de motor (Kit) | H90: Particular | I90: N/A | J90: 200000 | K90: =J90/1.19 -> 168067.23 | L90: =J90-K90 -> 31932.773 | M90: =J90*0.9 -> 180000 | N90: =J90+M90 -> 380000 | O90: 1 | P90: =N90*O90 -> 380000 | Q90: =P90 -> 380000
E91: S03 | F91: Servicio | G91: Instalación de ruedas (Unidad) | H91: Particular | I91: N/A | J91: 25000 | K91: =J91/1.19 -> 21008.403 | L91: =J91-K91 -> 3991.5966 | M91: =J91*0.9 -> 22500 | N91: =J91+M91 -> 47500 | O91: 1 | P91: =N91*O91 -> 47500 | Q91: =P91 -> 47500
E92: S04 | F92: Servicio | G92: Instalación de guias | H92: Particular | I92: N/A | J92: 25000 | K92: =J92/1.19 -> 21008.403 | L92: =J92-K92 -> 3991.5966 | M92: =J92*0.9 -> 22500 | N92: =J92+M92 -> 47500 | O92: 1 | P92: =N92*O92 -> 47500 | Q92: =P92 -> 47500
E93: S05 | F93: Servicio | G93: Instalación Retenedor | H93: Particular | I93: N/A | J93: 45000 | K93: =J93/1.19 -> 37815.126 | L93: =J93-K93 -> 7184.874 | M93: =J93*0.9 -> 40500 | N93: =J93+M93 -> 85500 | O93: 1 | P93: =N93*O93 -> 85500 | Q93: =P93 -> 85500
E94: S06 | F94: Servicio | G94: Instalación Protegus y config | H94: Particular | I94: N/A | J94: 20000 | K94: =J94/1.19 -> 16806.723 | L94: =J94-K94 -> 3193.2773 | M94: =J94 -> 20000 | N94: =J94+M94 -> 40000 | O94: 1 | P94: =N94*O94 -> 40000 | Q94: =P94 -> 40000
E95: S07 | F95: Servicio | G95: Mantención programada | H95: Particular | I95: N/A | J95: 100000 | K95: =J95/1.19 -> 84033.613 | L95: =J95-K95 -> 15966.387 | M95: =J95*100% -> 100000 | N95: =J95+M95 -> 200000 | O95: 1 | P95: =N95*O95 -> 200000 | Q95: =P95 -> 200000
E96: S08 | F96: Servicio | G96: Instalación de chapa Exteriores | H96: Particular | I96: N/A | J96: 50000 | K96: =J96/1.19 -> 42016.807 | L96: =J96-K96 -> 7983.1933 | M96: =J96*100% -> 50000 | N96: =J96+M96 -> 100000 | O96: 1 | P96: =N96*O96 -> 100000 | Q96: =P96 -> 100000
E97: S08I | F97: Servicio | G97: Servicio de instalación y configuración de chapas digitales | H97: Particular | I97: N/A | J97: 70000 | M97: =J97*0.4 -> 28000 | N97: =J97+M97 -> 98000 | O97: 1 | P97: =N97*O97 -> 98000 | Q97: =J97-M97 -> 42000
E98: S09 | F98: Servicio | G98: Servicio de recuperación post colisión Motor Centurion | H98: Particular | I98: N/A | J98: 238000 | K98: =J98/1.19 -> 200000 | L98: =J98-K98 -> 38000 | M98: =K98*0.5 -> 100000 | N98: =J98+M98 -> 338000 | O98: 1 | P98: =N98*O98 -> 338000 | Q98: =P98 -> 338000
E99: S09F | F99: Servicio | G99: Servicio de recuperación estructural | H99: Particular | I99: N/A | K99: =J99/1.19 -> 0 | L99: =J99-K99 -> 0 | M99: =K99*0.5 -> 0 | N99: =J99+M99 -> 0 | P99: =N99*O99 -> 0 | Q99: =P99 -> 0
E100: S10 | F100: Servicio | G100: Servicio de instalación digitador de acceso | H100: Particular | I100: N/A | J100: 119000 | K100: =J100/1.19 -> 100000 | L100: =J100-K100 -> 19000 | M100: =K100*0.1 -> 10000 | N100: =J100+M100 -> 129000 | O100: 1 | P100: =N100*O100 -> 129000 | Q100: =P100 -> 129000
E101: S11 | F101: Servicio | G101: Fabricación de perfil 100x100 c/ pintura y polines | H101: Particular | I101: N/A | J101: 120000 | K101: =J101/1.19 -> 100840.34 | L101: =J101-K101 -> 19159.664 | M101: =K101*1.5 -> 151260.5 | N101: =J101+M101 -> 271260.5 | O101: 1 | P101: =N101*O101 -> 271260.5 | Q101: =P101 -> 271260.5
E102: S13 | F102: Proyecto | G102: Servicio de mantenimiento CCTV central. | H102: Particular | I102: N/A | J102: 200000 | K102: =J102/1.19 -> 168067.23 | L102: =J102-K102 -> 31932.773 | M102: =K102*1.5 -> 252100.84 | N102: =J102+M102 -> 452100.84 | P102: =N102*O102 -> 0 | Q102: =P102 -> 0
E103: S14 | F103: Proyecto | G103: Servicio de mantenimiento y renovacion/acondicionamiento de central CCTV Fase I | H103: Particular | I103: N/A | J103: 680000 | K103: =J103/1.19 -> 571428.57 | L103: =J103-K103 -> 108571.43 | M103: =K103*1.5 -> 857142.86 | N103: =J103+M103 -> 1537142.9 | P103: =N103*O103 -> 0 | Q103: =P103 -> 0
...

Sheet R_CLIENTES
A1: RUT | B1: RAZÓN SOCIAL | C1: DIRECCION | D1: COMUNA | E1: CIUDAD | F1: REGIÓN | G1: CONTACTO | H1: TELÉFONO | I1: MAIL | J1: Columna 1 | K1: Columna 2 | L1: Columna 3 | M1: Columna 4 | N1: Columna 5 | O1: Columna 6 | P1: Columna 7 | Q1: Columna 8 | R1: Columna 9 | S1: Columna 10 | T1: Columna 11 | U1: Columna 12 | V1: Columna 13 | W1: Columna 14 | X1: Columna 15 | Y1: Columna 16 | Z1: Columna 17
A2: 53320939-4 | B2: Condominio Paseo Peñuelas | C2: AV. PACIFICO 5208 | D2: La Serena | E2: La Serena | F2: Coquimbo | G2: Adm Victor Figueroa | H2: 9-59823214 | I2: Pendiente correo
A3: 53334332-5 | B3: Condominio Mirador Los Clarines | C3: Av Los Clarines 1575 | D3: Coquimbo | E3: Coquimbo | F3: Coquimbo | G3: Emerson Castillo | H3: 9-5982-3214 | I3: condominiomiradordelosclarines@gmail.com
A4: 65198585-4 | B4: Condominio Vicenza II | C4: Av. Marco Gallo Vergara 536 | D4: La Serena | E4: La Serena | F4: Coquimbo | G4: Mauricio Araya | H4: 9-97269955 | I4: mauricio@mypspa.cl
A5: 53333086-k | B5: Condominio Colinas del Milagro | C5: Enrique Lynch 4332 | D5: La Serena | E5: La Serena | F5: Coquimbo | G5: Mauricio Araya | H5: 9-97269955 | I5: mauricio@mypspa.cl
A6: 76733113-4 | B6: RW SPA | C6: Arzobispo Larrain Gandarillas 87 | D6: Providencia | E6: Santiago | F6: Santiago | G6: Leonardo Arriaga | H6: SIN TELEFONO | I6: -
A7: 65216508-7 | B7: Condominio Mirador El Milagro | C7: Av. Las Palmeras 7000 | D7: La Serena | E7: La Serena | F7: Coquimbo | G7: Camila Godoy | H7: 9-44637185 | I7: condominiomiradorelmilagro@gmail.com
A8: 76470822-9 | B8: Sociedad Educacional Shalom SpA | C8: Avda. El Rosario 3870 | D8: Coquimbo | E8: Coquimbo | F8: Coquimbo | G8: Jorge Adm | H8: 999847687 | I8: contacto@amazinggraceco.cl
A9: 65203446-2 | B9: Condominio Altos del Parque | C9: G. Mistral 3605 E-1 Altos del Pque | D9: La Serena | E9: La Serena | F9: Coquimbo | G9: Maria Antoniera del Pino | H9: 9-84398698 | I9: -
A10: 50.000.001-0 | B10: Condominio Lomas de San Joaquin | C10: Av Gabriela Mistral 3670 | D10: La Serena | E10: La Serena | F10: Coquimbo | G10: Paola Robles | H10: 9-95802922 | I10: -
A11: 56047780-5 | B11: Comunidad Edificio Florencia | C11: Av Puertas del mar 347 | D11: La Serena | E11: La Serena | F11: Coquimbo | G11: Guillermo Negrete | H11: 9-93590543 | I11: -
A12: 53322672-8 | B12: CONDOMINIO V.I.V.E LA FLORIDA ORIENTE | C12: Av El Litre 2162, La Florida | D12: La Serena | E12: La Serena | F12: Coquimbo | G12: Paola Robles | H12: 9-95802922 | I12: -
A13: 53.332.075-9 | B13: Condominio Jardin Central | C13: Blanco garces 154 | D13: Estacion Central | E13: Santiago | F13: Metropolitana | G13: Vanessa Guerra | H13: 9 49856345 | I13: administracion@jardincentro.cl
A14: 50.000.000-0 | B14: Edificio Puerta Centro | C14: Morande 857 | D14: Santiago Centro | E14: Santiago | F14: Metropolitana | G14: César | H14: 9 98402129 | I14: Epuertacentro@gmail.com
A15: 53.322.860-7 | B15: Condominio Los Tamarindos I | C15: Av Islón 1301 | D15: La Serena | E15: La Serena | F15: Coquimbo | G15: Norman Rojas | H15: 9 49856345 | I15: -
A16: 65.095.336-2 | B16: Condominio Neo Spazio | C16: Av Central 5000 | D16: Coquimbo | E16: La Serena | F16: Coquimbo | G16: Guillermo Negrete | H16: 9-93590543 | I16: condominioneospazio@gmail.com
A17: 76.324.502-0 | B17: CitoApp SpA | C17: Providencia 1650 oficina 1603 | D17: Providencia | E17: Santiago | F17: Metropolitana | G17: Rodrigo Mansilla | H17: 9 6699 9835 | I17: contacto@citoapp.cl
A18: 76.324.502- 0 | B18: Cond Artes 1 | C18: Av Alberto Carvajal 4235 | D18: La Serena | E18: La Serena | F18: Coquimbo | G18: Carlos Hinojosa | H18: 9 7806 9280
A19: 76.179.872-3 | B19: Sociedad Educacional Basaldiaz S.A | C19: Cruz del Molino #386 Puertas del Mar La Serena | D19: La Serena | E19: La Serena | F19: Coquimbo | G19: Jonatan Mena | H19: 949911870 | I19: adquisiciones@amazinggracels.cl
A20: 53332414-2 | B20: Portal del Valle II | C20: Calle Raul Bitran 3501 | D20: La Serena | E20: La Serena | F20: Coquimbo | G20: Mauricio Araya | H20: 9-97269955 | I20: mauricio@mypspa.cl
A21: 76256791-1 | B21: Condominio Verona | C21: Monaco 493 | D21: La Serena | E21: La Serena | F21: Coquimbo | G21: Guillermo Negrete | H21: 9-93590543
A22: 76866075-1 | B22: Paseo San Carlos VII | C22: Waldo alcalde 1180 | D22: Coquimbo | E22: Coquimbo | F22: Coquimbo | G22: Claudio García | H22: 9-84398698
A23: 65.229.898-2 | B23: Distrito Verde I | C23: Emilio Apey 405 | D23: La Serena | E23: La Serena | F23: Coquimbo | G23: Maria Antonieta del Pino | H23: 9-84398698 | I23: madelpinoarcos@gmail.com
A24: 65.244.656- 6 | B24: Distrito Verde II | C24: Emilio Apey 409 | D24: La Serena | E24: La Serena | F24: Coquimbo | G24: Maria Antonieta del Pino | H24: 9-84398698 | I24: madelpinoarcos@gmail.com
A25: 79866075-1 | B25: Cond Doña Anita | C25: Av del mar 3320 | D25: La Serena | E25: La Serena | F25: Coquimbo | G25: Noema Reyes | H25: 9 7731 14628
A26: 53332351-0 | B26: Cond Aires de La Florida 4 | C26: Los Arándonos 5506 | D26: La Serena | E26: La Serena | F26: Coquimbo | G26: Camila Godoy | H26: 9-7684 0230
A27: 90000000-1 | B27: Condominio Gabriela Mistral | C27: Av Libertadores | D27: La Serena | E27: La Serena | F27: Coquimbo | G27: Mauricio Araya | H27: 9-97269955 | I27: mauricio@mypspa.cl
A28: 90000002-1 | B28: Condominio Golf III | C28: Enrique Abbott 380 | D28: La Serena | E28: La Serena | F28: Coquimbo | G28: Oscar Castro | H28: 9 9450 8233
A29: 90000003-1 | B29: Juan Fernando Mancilla | C29: Enrique Abbott 390 | D29: La Serena | E29: La Serena | F29: Coquimbo | G29: Juan Fernando Mancilla | H29: 999680974 | I29: jperez@gmail.com
A30: 65242132-6 | B30: Condominio Alto Bellavista | C30: Av Las Palmeras 740 | D30: La Serena | E30: La Serena | F30: Coquimbo | G30: Maria Antoniera del Pino | H30: 9-84398698 | I30: madelpinoarcos@gmail.com
A31: 65106948-3 | B31: Condominio Capri | C31: Av Puertas del mar 425 | D31: La Serena | E31: La Serena | F31: Coquimbo | G31: Bernardita Orellana | H31: 9-93193675 | I31: adm.condominiocapri@gmail.com
A32: 76785900-7 | B32: Espacio Norte La Serena | C32: El Rodillo Parcela 125 Vegas Norte La Serena | D32: La Serena | E32: La Serena | F32: Coquimbo | G32: Juan Retamal | H32: 9-985690424 | I32: contacto@espacioserenanorte.cl
A33: 53318313-1 | B33: Condominio Parque Libertad | C33: Juan Lorenzo Solis Castro 520 | D33: La Serena | E33: La Serena | F33: Coquimbo | G33: Wilson Vargas | H33: 9-61183960 | I33: admparquelibertad@gmail.com
A34: 65094027-K | B34: Cond Marina Horizonte | C34: Av Los Pescadores 5301 | D34: Coquimbo | E34: Coquimbo | F34: Coquimbo | G34: Rodrigo Mancilla | H34: 9-6699 9835 | I34: rodrigomancilla@gmail.com
A35: 76866075-2 | B35: Condominio Pacífico | C35: Av Pacífico 3100 | D35: La Serena | E35: La Serena | F35: Coquimbo | G35: Gabriel Mollano | H35: 9-95906289
A36: 53.312.705-3 | B36: Condominio Palermo | C36: Av Roberto Flores 0175 | D36: La Serena | E36: La Serena | F36: Coquimbo | G36: Elvis Díaz | H36: 9-39074968 | I36: elvisdiazdiaz.adm@gmail.com
A37: 65.049.582-9 | B37: Espacio Urbano | C37: Av Francisco de Aguirre 075 | D37: La Serena | E37: La Serena | F37: Coquimbo | G37: Gypsy Adm | H37: 9 6287 8932 | I37: N/A
A38: 65.066.845-6 | B38: Condominio Ossandon | C38: Av Ossandón 60 | D38: Coquimbo | E38: Coquimbo | F38: Coquimbo | G38: Diego Palma | H38: 9 9969 8228 | I38: admossandon@gmail.com
A39: 65.110.744-K | B39: Condominio Bahia Horizonte | C39: Darío Salas 1111 | D39: Coquimbo | E39: Coquimbo | F39: Coquimbo | G39: Diego Palma | H39: 9 9969 8228 | I39: Cbh.adm.2025@gmail.com
A40: 53.330.222-K | B40: Condominio Jardines del Pacífico | C40: Av Pacifico 510 | D40: La Serena | E40: La Serena | F40: Coquimbo | G40: Sergio Cortez | H40: 9 5148 2432 | I40: condominiojardinesdelpacifico@gmail.com

Sheet R_COTIZACIONES
A3: ID_COT | B3: FECHA | C3: RUT_CLIENTE | D3: RAZÓN SOCIAL | E3: CONTACTO | F3: APLICA IVA | G3: TELEFÓNO | H3: VENDEDOR | I3: FORMA DE PAGO | J3: VALOR NETO | K3: IVA | L3: TOTAL | M3: DESCRIPCIÓN | N3: COMENTARIOS | O3: ESTADO | P3: DOCUMENTO | Q3: NRO DOCUMENTO | R3: Columna 7 | S3: Columna 8 | T3: Columna 9 | U3: Columna 10 | V3: Columna 11 | W3: Columna 12 | X3: Columna 13 | Y3: Columna 14 | Z3: Columna 15 | AA3: Columna 16
A4: 1 | B4: 45568 | C4: 53334332-5 | D4: {=IFERROR( INDEX(R_CLIENTES!B:B, MATCH(C4, R_CLIENTES!A:A, 0) ), "" )} -> Condominio Mirador Los Clarines | E4: {=IFERROR( INDEX(R_CLIENTES!G:G, MATCH(C4, R_CLIENTES!A:A, 0) ), "" )} -> Emerson Castillo | F4: Si | G4: {=IFERROR( INDEX(R_CLIENTES!H:H, MATCH(C4, R_CLIENTES!A:A, 0) ), "" )} -> 9-5982-3214 | H4: Maximo Hudson | I4: Al finalizar | J4: 200000 | K4: =IF(J4="","",IF(F4="SI",J4*0.19,0)) -> 38000 | L4: =IF(J4="","",J4+K4) -> 238000 | M4: Servicio de mantención Programada 2024 | O4: Aprobado
A5: 2 | B5: 45568 | C5: 53333086-k | D5: {=IFERROR( INDEX(R_CLIENTES!B:B, MATCH(C5, R_CLIENTES!A:A, 0) ), "" )} -> Condominio Colinas del Milagro | E5: {=IFERROR( INDEX(R_CLIENTES!G:G, MATCH(C5, R_CLIENTES!A:A, 0) ), "" )} -> Mauricio Araya | F5: Si | G5: {=IFERROR( INDEX(R_CLIENTES!H:H, MATCH(C5, R_CLIENTES!A:A, 0) ), "" )} -> 9-97269955 | H5: Maximo Hudson | I5: Al finalizar | J5: 200000 | K5: =IF(J5="","",IF(F5="SI",J5*0.19,0)) -> 38000 | L5: =IF(J5="","",J5+K5) -> 238000 | M5: Servicio de mantención Programada 2024 | O5: Aprobado
A6: 3 | B6: 45568 | C6: 56047780-5 | D6: {=IFERROR( INDEX(R_CLIENTES!B:B, MATCH(C6, R_CLIENTES!A:A, 0) ), "" )} -> Comunidad Edificio Florencia | E6: {=IFERROR( INDEX(R_CLIENTES!G:G, MATCH(C6, R_CLIENTES!A:A, 0) ), "" )} -> Guillermo Negrete | F6: Si | G6: {=IFERROR( INDEX(R_CLIENTES!H:H, MATCH(C6, R_CLIENTES!A:A, 0) ), "" )} -> 9-93590543 | H6: Maximo Hudson | I6: Al finalizar | J6: 220000 | K6: =IF(J6="","",IF(F6="SI",J6*0.19,0)) -> 41800 | L6: =IF(J6="","",J6+K6) -> 261800 | M6: Dispositivo GATOR para activación de portón remoto para apertura con aplicativo Protegus | N6: Dispositivo GATOR para activación de portón remoto para apertura con aplicativo Protegus (hasta 500 usuarios). | O6: Aprobado
A7: 4 | B7: 45568 | C7: 53322672-8 | D7: {=IFERROR( INDEX(R_CLIENTES!B:B, MATCH(C7, R_CLIENTES!A:A, 0) ), "" )} -> CONDOMINIO V.I.V.E LA FLORIDA ORIENTE | E7: {=IFERROR( INDEX(R_CLIENTES!G:G, MATCH(C7, R_CLIENTES!A:A, 0) ), "" )} -> Paola Robles | F7: Si | G7: {=IFERROR( INDEX(R_CLIENTES!H:H, MATCH(C7, R_CLIENTES!A:A, 0) ), "" )} -> 9-95802922 | H7: Maximo Hudson | I7: Al finalizar | J7: 300000 | K7: =IF(J7="","",IF(F7="SI",J7*0.19,0)) -> 57000 | L7: =IF(J7="","",J7+K7) -> 357000 | M7: Cambio Ruedas 24mm (par) | N7: Instalación de Rueda 100x100 doble rodamiento, cambio de las 2 ruedas pre existentes y una rueda entremedia 100x100 para redistribución de la carga total del portón. | O7: Rechazado
A8: 5 | B8: 45568 | C8: 50.000.001-0 | D8: {=IFERROR( INDEX(R_CLIENTES!B:B, MATCH(C8, R_CLIENTES!A:A, 0) ), "" )} -> Condominio Lomas de San Joaquin | E8: {=IFERROR( INDEX(R_CLIENTES!G:G, MATCH(C8, R_CLIENTES!A:A, 0) ), "" )} -> Paola Robles | F8: Si | G8: {=IFERROR( INDEX(R_CLIENTES!H:H, MATCH(C8, R_CLIENTES!A:A, 0) ), "" )} -> 9-95802922 | H8: Maximo Hudson | I8: 0 a 30 días | J8: 1400000 | K8: =IF(J8="","",IF(F8="SI",J8*0.19,0)) -> 266000 | L8: =IF(J8="","",J8+K8) -> 1666000 | M8: Kit D10 Smart con 6mts Cremallera M, CR y Baliza | N8: Kit incluye: Placa metálica de montaje, 6 cremalleras metálicas, 2 baterías de 12V/7amp (24V) de respaldo, 1 Control Transmisor NOVA, 1 Baliza 24V y 1 par de Fotocelda Centurion Smart | O8: Rechazado
A9: 6 | B9: 45574 | C9: 56047780-5 | D9: {=IFERROR( INDEX(R_CLIENTES!B:B, MATCH(C9, R_CLIENTES!A:A, 0) ), "" )} -> Comunidad Edificio Florencia | E9: {=IFERROR( INDEX(R_CLIENTES!G:G, MATCH(C9, R_CLIENTES!A:A, 0) ), "" )} -> Guillermo Negrete | F9: Si | G9: {=IFERROR( INDEX(R_CLIENTES!H:H, MATCH(C9, R_CLIENTES!A:A, 0) ), "" )} -> 9-93590543 | H9: Maximo Hudson | I9: 50 anticipo y 50 al finalizar | J9: 230000 | K9: =IF(J9="","",IF(F9="SI",J9*0.19,0)) -> 43700 | L9: =IF(J9="","",J9+K9) -> 273700 | M9: Servicio Mantención | N9: Cambio de Guías + reparación riel + reparación topes | O9: Rechazado
A10: 7 | B10: 45576 | C10: 53.322.860-7 | D10: {=IFERROR( INDEX(R_CLIENTES!B:B, MATCH(C10, R_CLIENTES!A:A, 0) ), "" )} -> Condominio Los Tamarindos I | E10: {=IFERROR( INDEX(R_CLIENTES!G:G, MATCH(C10, R_CLIENTES!A:A, 0) ), "" )} -> Norman Rojas | F10: no | G10: {=IFERROR( INDEX(R_CLIENTES!H:H, MATCH(C10, R_CLIENTES!A:A, 0) ), "" )} -> 9 49856345 | H10: Maximo Hudson | I10: 0 a 30 días | J10: 1500000 | K10: =IF(J10="","",IF(F10="SI",J10*0.19,0)) -> 0 | L10: =IF(J10="","",J10+K10) -> 1500000 | M10: Kit D10 Smart con 6mts Cremallera M, CR, Baliza y fotocelda Smart | N10: Kit incluye: Placa metálica de montaje, 6 cremalleras metálicas, 2 baterías de 12V/7amp (24V) de respaldo, 1 Control Transmisor NOVA, 1 Baliza 24V y 1 par de Fotocelda Centurion Smart | O10: Rechazado
A11: 8 | B11: 45576 | C11: 53.322.860-7 | D11: {=IFERROR( INDEX(R_CLIENTES!B:B, MATCH(C11, R_CLIENTES!A:A, 0) ), "" )} -> Condominio Los Tamarindos I | E11: {=IFERROR( INDEX(R_CLIENTES!G:G, MATCH(C11, R_CLIENTES!A:A, 0) ), "" )} -> Norman Rojas | F11: no | G11: {=IFERROR( INDEX(R_CLIENTES!H:H, MATCH(C11, R_CLIENTES!A:A, 0) ), "" )} -> 9 49856345 | H11: Maximo Hudson | I11: 50 anticipo y 50 al finalizar | J11: 220000 | K11: =IF(J11="","",IF(F11="SI",J11*0.19,0)) -> 0 | L11: =IF(J11="","",J11+K11) -> 220000 | M11: Dispositivo GATOR para activación de portón remoto para apertura con aplicativo Protegus | N11: Sistema para apertura remota mediante aplicativo protegus 2 | O11: Rechazado
A12: 9 | B12: 45580 | C12: 53.332.075-9 | D12: {=IFERROR( INDEX(R_CLIENTES!B:B, MATCH(C12, R_CLIENTES!A:A, 0) ), "" )} -> Condominio Jardin Central | E12: {=IFERROR( INDEX(R_CLIENTES!G:G, MATCH(C12, R_CLIENTES!A:A, 0) ), "" )} -> Vanessa Guerra | F12: no | G12: {=IFERROR( INDEX(R_CLIENTES!H:H, MATCH(C12, R_CLIENTES!A:A, 0) ), "" )} -> 9 49856345 | H12: Maximo Hudson | I12: Al finalizar | J12: 170000 | K12: =IF(J12="","",IF(F12="SI",J12*0.19,0)) -> 0 | L12: =IF(J12="","",J12+K12) -> 170000 | M12: Servicio Mantención | N12: Servicio incluye suministro, aceite de motor FAAC, Bisagras y accesorios. | O12: Rechazado
A13: 10 | B13: 45580 | C13: 50.000.000-0 | D13: {=IFERROR( INDEX(R_CLIENTES!B:B, MATCH(C13, R_CLIENTES!A:A, 0) ), "" )} -> Edificio Puerta Centro | E13: {=IFERROR( INDEX(R_CLIENTES!G:G, MATCH(C13, R_CLIENTES!A:A, 0) ), "" )} -> César | F13: no | G13: {=IFERROR( INDEX(R_CLIENTES!H:H, MATCH(C13, R_CLIENTES!A:A, 0) ), "" )} -> 9 98402129 | H13: Maximo Hudson | I13: Al finalizar | J13: 170000 | K13: =IF(J13="","",IF(F13="SI",J13*0.19,0)) -> 0 | L13: =IF(J13="","",J13+K13) -> 170000 | M13: Servicio Mantención | N13: Servicio incluye suministro, aceite de motor FAAC, Bisagras y accesorios. Modificación de portón incluye Quicios y perfil 100x50, incluye servicio de aplicación de pintura. | O13: Rechazado
A14: 11 | B14: 45580 | C14: 65.095.336-2 | D14: {=IFERROR( INDEX(R_CLIENTES!B:B, MATCH(C14, R_CLIENTES!A:A, 0) ), "" )} -> Condominio Neo Spazio | E14: {=IFERROR( INDEX(R_CLIENTES!G:G, MATCH(C14, R_CLIENTES!A:A, 0) ), "" )} -> Guillermo Negrete | F14: Si | G14: {=IFERROR( INDEX(R_CLIENTES!H:H, MATCH(C14, R_CLIENTES!A:A, 0) ), "" )} -> 9-93590543 | H14: Maximo Hudson | I14: 50 anticipo y 50 al finalizar | J14: 1250000 | K14: =IF(J14="","",IF(F14="SI",J14*0.19,0)) -> 237500 | L14: =IF(J14="","",J14+K14) -> 1487500 | M14: Central Citofonía Bticino | N14: Kit de citofono Btcino con expansor y fuente de alimentación con Instalacíon. | O14: Rechazado
A15: 12 | B15: 45509 | C15: 65216508-7 | D15: {=IFERROR( INDEX(R_CLIENTES!B:B, MATCH(C15, R_CLIENTES!A:A, 0) ), "" )} -> Condominio Mirador El Milagro | E15: {=IFERROR( INDEX(R_CLIENTES!G:G, MATCH(C15, R_CLIENTES!A:A, 0) ), "" )} -> Camila Godoy | F15: Si | G15: {=IFERROR( INDEX(R_CLIENTES!H:H, MATCH(C15, R_CLIENTES!A:A, 0) ), "" )} -> 9-44637185 | H15: Maximo Hudson | I15: 0 a 30 días | J15: 1435990 | K15: =IF(J15="","",IF(F15="SI",J15*0.19,0)) -> 272838.1 | L15: =IF(J15="","",J15+K15) -> 1708828.1 | M15: D10 STD Smart + 6mts cremallera + 1 Control 2b + 2 Bateria 12v + Baliza 24V + Fotocelda Smart Ina + con Inst Motor + Servicios Tecnico post venta | N15: Servicio incluye motor, instalación, accesorios y 2 controles. | O15: Aprobado
A16: 13 | B16: 45366 | C16: 53333086-k | D16: {=IFERROR( INDEX(R_CLIENTES!B:B, MATCH(C16, R_CLIENTES!A:A, 0) ), "" )} -> Condominio Colinas del Milagro | E16: {=IFERROR( INDEX(R_CLIENTES!G:G, MATCH(C16, R_CLIENTES!A:A, 0) ), "" )} -> Mauricio Araya | F16: Si | G16: {=IFERROR( INDEX(R_CLIENTES!H:H, MATCH(C16, R_CLIENTES!A:A, 0) ), "" )} -> 9-97269955 | H16: Maximo Hudson | I16: 0 a 30 días | J16: 1340000 | K16: =IF(J16="","",IF(F16="SI",J16*0.19,0)) -> 254600 | L16: =IF(J16="","",J16+K16) -> 1594600 | M16: Kit D10 T Smart + Fotocelda Smart + Inst Motor | N16: Servicio incluye motor, instalación, accesorios y 2 controles. | O16: Aprobado
A17: 14 | B17: 45586 | C17: 53333086-k | D17: {=IFERROR( INDEX(R_CLIENTES!B:B, MATCH(C17, R_CLIENTES!A:A, 0) ), "" )} -> Condominio Colinas del Milagro | E17: {=IFERROR( INDEX(R_CLIENTES!G:G, MATCH(C17, R_CLIENTES!A:A, 0) ), "" )} -> Mauricio Araya | F17: Si | G17: {=IFERROR( INDEX(R_CLIENTES!H:H, MATCH(C17, R_CLIENTES!A:A, 0) ), "" )} -> 9-97269955 | H17: Maximo Hudson | I17: 0 a 30 días | J17: 370000 | K17: =IF(J17="","",IF(F17="SI",J17*0.19,0)) -> 70300 | L17: =IF(J17="","",J17+K17) -> 440300 | M17: Instalación de chapa eléctrica Poli para exteriores. | N17: Servicio incluye chapa electromagnetica, cableado y garantía | O17: Aprobado
... A21: 18 | B21: 45615 | C21: 76.179.872-3 | D21: {=IFERROR( INDEX(R_CLIENTES!B:B, MATCH(C21, R_CLIENTES!A:A, 0) ), "" )} -> Sociedad Educacional Basaldiaz S.A | E21: {=IFERROR( INDEX(R_CLIENTES!G:G, MATCH(C21, R_CLIENTES!A:A, 0) ), "" )} -> Jonatan Mena | F21: Si | G21: {=IFERROR( INDEX(R_CLIENTES!H:H, MATCH(C21, R_CLIENTES!A:A, 0) ), "" )} -> 949911870 | H21: Maximo Hudson | I21: 50 anticipo y 50 al finalizar | J21: 1300000 | K21: =IF(J21="","",IF(F21="SI",J21*0.19,0)) -> 247000 | L21: =IF(J21="","",J21+K21) -> 1547000 | M21: Instalación de motor Centurion D10 con 6 cremalleras, baliza, fotoceldas, sistema WIFI de apertura remota, mano de obra y configuración. | N21: Servicio incluye motor, instalación, accesorios y 2 controles. | O21: Rechazado
A22: 19 | B22: 45622 | C22: 53332414-2 | D22: {=IFERROR( INDEX(R_CLIENTES!B:B, MATCH(C22, R_CLIENTES!A:A, 0) ), "" )} -> Portal del Valle II | E22: {=IFERROR( INDEX(R_CLIENTES!G:G, MATCH(C22, R_CLIENTES!A:A, 0) ), "" )} -> Mauricio Araya | F22: Si | G22: {=IFERROR( INDEX(R_CLIENTES!H:H, MATCH(C22, R_CLIENTES!A:A, 0) ), "" )} -> 9-97269955 | H22: Maximo Hudson | I22: 50 anticipo y 50 al finalizar | J22: 1645813 | K22: =IF(J22="","",IF(F22="SI",J22*0.19,0)) -> 312704.47 | L22: =IF(J22="","",J22+K22) -> 1958517.5 | M22: Instalación de motor Centurion D10Turbo con 6 cremalleras, baliza, fotoceldas, cambio de ruedas, Polines de Guías, mano de obra y configuración. | O22: Aprobado
A23: 20 | B23: 45699 | C23: 56047780-5 | D23: {=IFERROR( INDEX(R_CLIENTES!B:B, MATCH(C23, R_CLIENTES!A:A, 0) ), "" )} -> Comunidad Edificio Florencia | E23: {=IFERROR( INDEX(R_CLIENTES!G:G, MATCH(C23, R_CLIENTES!A:A, 0) ), "" )} -> Guillermo Negrete | F23: no | G23: {=IFERROR( INDEX(R_CLIENTES!H:H, MATCH(C23, R_CLIENTES!A:A, 0) ), "" )} -> 9-93590543 | H23: Maximo Hudson | I23: Al finalizar | J23: 140000 | K23: =IF(J23="","",IF(F23="SI",J23*0.19,0)) -> 0 | L23: =IF(J23="","",J23+K23) -> 140000 | M23: Reparación sensores Centurion D10 | O23: Aprobado
A24: 21 | B24: 45699 | C24: 65198585-4 | D24: {=IFERROR( INDEX(R_CLIENTES!B:B, MATCH(C24, R_CLIENTES!A:A, 0) ), "" )} -> Condominio Vicenza II | E24: {=IFERROR( INDEX(R_CLIENTES!G:G, MATCH(C24, R_CLIENTES!A:A, 0) ), "" )} -> Mauricio Araya | F24: Si | G24: {=IFERROR( INDEX(R_CLIENTES!H:H, MATCH(C24, R_CLIENTES!A:A, 0) ), "" )} -> 9-97269955 | H24: Maximo Hudson | I24: Al finalizar | J24: 670000 | K24: =IF(J24="","",IF(F24="SI",J24*0.19,0)) -> 127300 | L24: =IF(J24="","",J24+K24) -> 797300 | M24: Cambio de ruedas, Guías, cambio de cremalleras, enderezamiento de portón, y preparación para instalar motor | N24: Servicio sin equipo, solo materiales y accesorios | O24: Aprobado
A25: 22 | B25: 45699 | C25: 65198585-4 | D25: {=IFERROR( INDEX(R_CLIENTES!B:B, MATCH(C25, R_CLIENTES!A:A, 0) ), "" )} -> Condominio Vicenza II | E25: {=IFERROR( INDEX(R_CLIENTES!G:G, MATCH(C25, R_CLIENTES!A:A, 0) ), "" )} -> Mauricio Araya | F25: Si | G25: {=IFERROR( INDEX(R_CLIENTES!H:H, MATCH(C25, R_CLIENTES!A:A, 0) ), "" )} -> 9-97269955 | H25: Maximo Hudson | I25: Al finalizar | J25: 1000000 | K25: =IF(J25="","",IF(F25="SI",J25*0.19,0)) -> 190000 | L25: =IF(J25="","",J25+K25) -> 1190000 | M25: Centurion D10 Turbo Smart incluye instalación de 6 mts de cremallera y 2 controles remoto | N25: Motor D10 Turbo incluye cremalleras, controles y mano de obra | O25: Aprobado
A26: 23 | B26: 45699 | C26: 65198585-4 | D26: {=IFERROR( INDEX(R_CLIENTES!B:B, MATCH(C26, R_CLIENTES!A:A, 0) ), "" )} -> Condominio Vicenza II | E26: {=IFERROR( INDEX(R_CLIENTES!G:G, MATCH(C26, R_CLIENTES!A:A, 0) ), "" )} -> Mauricio Araya | F26: Si | G26: {=IFERROR( INDEX(R_CLIENTES!H:H, MATCH(C26, R_CLIENTES!A:A, 0) ), "" )} -> 9-97269955 | H26: Maximo Hudson | I26: Al finalizar | J26: 200000 | K26: =IF(J26="","",IF(F26="SI",J26*0.19,0)) -> 38000 | L26: =IF(J26="","",J26+K26) -> 238000 | M26: Reparación Portón por colisión | O26: Aprobado
A27: 24 | B27: 45856 | C27: 76866075-1 | D27: {=IFERROR( INDEX(R_CLIENTES!B:B, MATCH(C27, R_CLIENTES!A:A, 0) ), "" )} -> Paseo San Carlos VII | E27: {=IFERROR( INDEX(R_CLIENTES!G:G, MATCH(C27, R_CLIENTES!A:A, 0) ), "" )} -> Claudio García | F27: Si | G27: {=IFERROR( INDEX(R_CLIENTES!H:H, MATCH(C27, R_CLIENTES!A:A, 0) ), "" )} -> 9-84398698 | H27: Maximo Hudson | I27: Al finalizar | J27: 1600000 | K27: =IF(J27="","",IF(F27="SI",J27*0.19,0)) -> 304000 | L27: =IF(J27="","",J27+K27) -> 1904000 | M27: Instalación de motor Centurion D10Turbo con 6 cremalleras, baliza, fotoceldas, cambio de ruedas, Polines de Guías, mano de obra y configuración. | N27: Motor D10 Turbo incluye cremalleras, controles y mano de obra | O27: Aprobado
A28: 25 | B28: 45860 | C28: 65203446-2 | D28: {=IFERROR( INDEX(R_CLIENTES!B:B, MATCH(C28, R_CLIENTES!A:A, 0) ), "" )} -> Condominio Altos del Parque | E28: {=IFERROR( INDEX(R_CLIENTES!G:G, MATCH(C28, R_CLIENTES!A:A, 0) ), "" )} -> Maria Antoniera del Pino | F28: Si | G28: {=IFERROR( INDEX(R_CLIENTES!H:H, MATCH(C28, R_CLIENTES!A:A, 0) ), "" )} -> 9-84398698 | H28: Maximo Hudson | I28: Al finalizar | J28: 1310833 | K28: =IF(J28="","",IF(F28="SI",J28*0.19,0)) -> 249058.27 | L28: =IF(J28="","",J28+K28) -> 1559891.3 | M28: Instalación de motor Centurion D10Turbo con 6 cremalleras, baliza, fotoceldas, cambio de ruedas, Polines de Guías, mano de obra y configuración. | N28: Motor D10 Turbo incluye cremalleras, controles y mano de obra | O28: Aprobado
A29: 26 | B29: 45888 | C29: 65.229.898-2 | D29: {=IFERROR( INDEX(R_CLIENTES!B:B, MATCH(C29, R_CLIENTES!A:A, 0) ), "" )} -> Distrito Verde I | E29: {=IFERROR( INDEX(R_CLIENTES!G:G, MATCH(C29, R_CLIENTES!A:A, 0) ), "" )} -> Maria Antonieta del Pino | F29: Si | G29: {=IFERROR( INDEX(R_CLIENTES!H:H, MATCH(C29, R_CLIENTES!A:A, 0) ), "" )} -> 9-84398698 | H29: Maximo Hudson | I29: Al finalizar | J29: 545000 | K29: =IF(J29="","",IF(F29="SI",J29*0.19,0)) -> 103550 | L29: =IF(J29="","",J29+K29) -> 648550 | M29: Recuperación automatización portón Distrito verde 1 (incluye foto celdas internas inalambricas) | N29: Dtto Verde 1 Reparación por concepto defectos de instalacion de cremalleras, instalación perfil en medio de recorrido , puesta en marcha y configuración de equipo | O29: Aprobado
A30: 27 | B30: 45888 | C30: 65.244.656- 6 | D30: {=IFERROR( INDEX(R_CLIENTES!B:B, MATCH(C30, R_CLIENTES!A:A, 0) ), "" )} -> Distrito Verde II | E30: {=IFERROR( INDEX(R_CLIENTES!G:G, MATCH(C30, R_CLIENTES!A:A, 0) ), "" )} -> Maria Antonieta del Pino | F30: Si | G30: {=IFERROR( INDEX(R_CLIENTES!H:H, MATCH(C30, R_CLIENTES!A:A, 0) ), "" )} -> 9-84398698 | H30: Maximo Hudson | I30: Al finalizar | J30: 840000 | K30: =IF(J30="","",IF(F30="SI",J30*0.19,0)) -> 159600 | L30: =IF(J30="","",J30+K30) -> 999600 | M30: Recuperación automatización portón Distrito verde 1 (incluye foto celdas internas inalambricas) | N30: Dtto Verde 2 Reparación por concepto defectos de instalacion de cremalleras, instalación perfil en medio de recorrido , puesta en marcha y configuración de equipo | O30: Aprobado
A31: 28 | B31: 45911 | C31: 79866075-1 | D31: {=IFERROR( INDEX(R_CLIENTES!B:B, MATCH(C31, R_CLIENTES!A:A, 0) ), "" )} -> Cond Doña Anita | E31: {=IFERROR( INDEX(R_CLIENTES!G:G, MATCH(C31, R_CLIENTES!A:A, 0) ), "" )} -> Noema Reyes | F31: no | G31: {=IFERROR( INDEX(R_CLIENTES!H:H, MATCH(C31, R_CLIENTES!A:A, 0) ), "" )} -> 9 7731 14628 | H31: Maximo Hudson | I31: 50 anticipo y 50 al finalizar | J31: 3950000 | K31: =IF(J31="","",IF(F31="SI",J31*0.19,0)) -> 0 | L31: =IF(J31="","",J31+K31) -> 3950000 | M31: Reconfiguración e instalación de moptor D10 Turbo | N31: Mano de obra de reconfiguracion motor batiente a corredizo, trabajos de obra civil e instalación de motor D10 Turbo con kit de instalacion. | O31: Rechazado
A32: 29 | B32: 45916 | C32: 53320939-4 | D32: {=IFERROR( INDEX(R_CLIENTES!B:B, MATCH(C32, R_CLIENTES!A:A, 0) ), "" )} -> Condominio Paseo Peñuelas | E32: {=IFERROR( INDEX(R_CLIENTES!G:G, MATCH(C32, R_CLIENTES!A:A, 0) ), "" )} -> Adm Victor Figueroa | F32: Si | G32: {=IFERROR( INDEX(R_CLIENTES!H:H, MATCH(C32, R_CLIENTES!A:A, 0) ), "" )} -> 9-59823214 | H32: Maximo Hudson | I32: Al finalizar | J32: 1180000 | K32: =IF(J32="","",IF(F32="SI",J32*0.19,0)) -> 224200 | L32: =IF(J32="","",J32+K32) -> 1404200 | M32: D10 STD Smart + 6mts cremallera + 2 Control 2b + 2 Bateria 12v + Fotocelda Smart Ina Serial: ZAXZ200031C2 | N32: Serial Motor: ZAXZ200031C2 | O32: Aprobado
A33: 29 | B33: 45916 | C33: 53320939-4 | D33: {=IFERROR( INDEX(R_CLIENTES!B:B, MATCH(C33, R_CLIENTES!A:A, 0) ), "" )} -> Condominio Paseo Peñuelas | E33: {=IFERROR( INDEX(R_CLIENTES!G:G, MATCH(C33, R_CLIENTES!A:A, 0) ), "" )} -> Adm Victor Figueroa | F33: no | G33: {=IFERROR( INDEX(R_CLIENTES!H:H, MATCH(C33, R_CLIENTES!A:A, 0) ), "" )} -> 9-59823214 | H33: Maximo Hudson | I33: Al finalizar | J33: 370000 | K33: =IF(J33="","",IF(F33="SI",J33*0.19,0)) -> 0 | L33: =IF(J33="","",J33+K33) -> 370000 | M33: Con Inst Motor + Servicios Tecnico post vent | N33: Solo servicio y mano de obra | O33: Aprobado
A34: 30 | B34: 45916 | C34: 53320939-4 | D34: {=IFERROR( INDEX(R_CLIENTES!B:B, MATCH(C34, R_CLIENTES!A:A, 0) ), "" )} -> Condominio Paseo Peñuelas | E34: {=IFERROR( INDEX(R_CLIENTES!G:G, MATCH(C34, R_CLIENTES!A:A, 0) ), "" )} -> Adm Victor Figueroa | F34: no | G34: {=IFERROR( INDEX(R_CLIENTES!H:H, MATCH(C34, R_CLIENTES!A:A, 0) ), "" )} -> 9-59823214 | H34: Maximo Hudson | I34: Al finalizar | J34: 200000 | K34: =IF(J34="","",IF(F34="SI",J34*0.19,0)) -> 0 | L34: =IF(J34="","",J34+K34) -> 200000 | M34: Manteción programada 2025 | N34: Mantención programada 2025 | O34: Aprobado
A35: 31 | B35: 45883 | C35: 65216508-7 | D35: {=IFERROR( INDEX(R_CLIENTES!B:B, MATCH(C35, R_CLIENTES!A:A, 0) ), "" )} -> Condominio Mirador El Milagro | E35: {=IFERROR( INDEX(R_CLIENTES!G:G, MATCH(C35, R_CLIENTES!A:A, 0) ), "" )} -> Camila Godoy | F35: Si | G35: {=IFERROR( INDEX(R_CLIENTES!H:H, MATCH(C35, R_CLIENTES!A:A, 0) ), "" )} -> 9-44637185 | H35: Maximo Hudson | I35: Al finalizar | J35: 200000 | K35: =IF(J35="","",IF(F35="SI",J35*0.19,0)) -> 38000 | L35: =IF(J35="","",J35+K35) -> 238000 | M35: Manteción programada 2025 | N35: Mantención programada 2025 | O35: Aprobado
A36: 32 | B36: 45938 | C36: 65216508-7 | D36: {=IFERROR( INDEX(R_CLIENTES!B:B, MATCH(C36, R_CLIENTES!A:A, 0) ), "" )} -> Condominio Mirador El Milagro | E36: {=IFERROR( INDEX(R_CLIENTES!G:G, MATCH(C36, R_CLIENTES!A:A, 0) ), "" )} -> Camila Godoy | F36: no | G36: {=IFERROR( INDEX(R_CLIENTES!H:H, MATCH(C36, R_CLIENTES!A:A, 0) ), "" )} -> 9-44637185 | H36: Maximo Hudson | I36: Al finalizar | J36: 153000 | K36: =IF(J36="","",IF(F36="SI",J36*0.19,0)) -> 0 | L36: =IF(J36="","",J36+K36) -> 153000 | M36: Controles Centurion | N36: 9 controles NOVA 2CH | O36: Aprobado
A37: 33 | B37: 45883 | C37: 53333086-k | D37: {=IFERROR( INDEX(R_CLIENTES!B:B, MATCH(C37, R_CLIENTES!A:A, 0) ), "" )} -> Condominio Colinas del Milagro | E37: {=IFERROR( INDEX(R_CLIENTES!G:G, MATCH(C37, R_CLIENTES!A:A, 0) ), "" )} -> Mauricio Araya | F37: Si | G37: {=IFERROR( INDEX(R_CLIENTES!H:H, MATCH(C37, R_CLIENTES!A:A, 0) ), "" )} -> 9-97269955 | H37: Maximo Hudson | I37: Al finalizar | J37: 200000 | K37: =IF(J37="","",IF(F37="SI",J37*0.19,0)) -> 38000 | L37: =IF(J37="","",J37+K37) -> 238000 | M37: Manteción programada 2025 | N37: Manteción programada 2025 | O37: Aprobado
A38: 34 | B38: 45883 | C38: 65198585-4 | D38: {=IFERROR( INDEX(R_CLIENTES!B:B, MATCH(C38, R_CLIENTES!A:A, 0) ), "" )} -> Condominio Vicenza II | E38: {=IFERROR( INDEX(R_CLIENTES!G:G, MATCH(C38, R_CLIENTES!A:A, 0) ), "" )} -> Mauricio Araya | F38: Si | G38: {=IFERROR( INDEX(R_CLIENTES!H:H, MATCH(C38, R_CLIENTES!A:A, 0) ), "" )} -> 9-97269955 | H38: Maximo Hudson | I38: Al finalizar | J38: 200000 | K38: =IF(J38="","",IF(F38="SI",J38*0.19,0)) -> 38000 | L38: =IF(J38="","",J38+K38) -> 238000 | M38: Manteción programada 2025 | N38: Manteción programada 2025 | O38: Aprobado
... A40: 36 | B40: 45938 | C40: 53332414-2 | D40: {=IFERROR( INDEX(R_CLIENTES!B:B, MATCH(C40, R_CLIENTES!A:A, 0) ), "" )} -> Portal del Valle II | E40: {=IFERROR( INDEX(R_CLIENTES!G:G, MATCH(C40, R_CLIENTES!A:A, 0) ), "" )} -> Mauricio Araya | F40: Si | G40: {=IFERROR( INDEX(R_CLIENTES!H:H, MATCH(C40, R_CLIENTES!A:A, 0) ), "" )} -> 9-97269955 | H40: Maximo Hudson | I40: Al finalizar | J40: 290000 | K40: =IF(J40="","",IF(F40="SI",J40*0.19,0)) -> 55100 | L40: =IF(J40="","",J40+K40) -> 345100 | M40: Servicio de perfil de apoyo 100x100 con 3ra rueda de aguante para estabilizacion de paño | N40: Estabilizacion y separación de paño portón de pared vecinal. | O40: Aprobado
A41: 37 | B41: 45950 | C41: 90000000-1 | D41: {=IFERROR( INDEX(R_CLIENTES!B:B, MATCH(C41, R_CLIENTES!A:A, 0) ), "" )} -> Condominio Gabriela Mistral | E41: {=IFERROR( INDEX(R_CLIENTES!G:G, MATCH(C41, R_CLIENTES!A:A, 0) ), "" )} -> Mauricio Araya | F41: no | G41: {=IFERROR( INDEX(R_CLIENTES!H:H, MATCH(C41, R_CLIENTES!A:A, 0) ), "" )} -> 9-97269955 | H41: Maximo Hudson | I41: Al finalizar | J41: 250000 | K41: =IF(J41="","",IF(F41="SI",J41*0.19,0)) -> 0 | L41: =IF(J41="","",J41+K41) -> 250000 | M41: Chapa ODIS Model 783 Instalada | O41: Aprobado
A42: 38 | B42: 45950 | C42: 53332351-0 | D42: {=IFERROR( INDEX(R_CLIENTES!B:B, MATCH(C42, R_CLIENTES!A:A, 0) ), "" )} -> Cond Aires de La Florida 4 | E42: {=IFERROR( INDEX(R_CLIENTES!G:G, MATCH(C42, R_CLIENTES!A:A, 0) ), "" )} -> Camila Godoy | F42: Si | G42: {=IFERROR( INDEX(R_CLIENTES!H:H, MATCH(C42, R_CLIENTES!A:A, 0) ), "" )} -> 9-7684 0230 | H42: Maximo Hudson | I42: 50 anticipo y 50 al finalizar | J42: 2000000 | K42: =IF(J42="","",IF(F42="SI",J42*0.19,0)) -> 380000 | L42: =IF(J42="","",J42+K42) -> 2380000 | M42: Kit D10 Smart con 6mts Cremallera M, CR, Baliza y fotocelda Smart | N42: Instalación de motor Centurion D10 Turbo, cambio de ruedas, cambio de guías y acondicionamiento de base de motor. | O42: Pendiente
A43: 39 | B43: 45972 | C43: 56047780-5 | D43: {=IFERROR( INDEX(R_CLIENTES!B:B, MATCH(C43, R_CLIENTES!A:A, 0) ), "" )} -> Comunidad Edificio Florencia | E43: {=IFERROR( INDEX(R_CLIENTES!G:G, MATCH(C43, R_CLIENTES!A:A, 0) ), "" )} -> Guillermo Negrete | F43: no | G43: {=IFERROR( INDEX(R_CLIENTES!H:H, MATCH(C43, R_CLIENTES!A:A, 0) ), "" )} -> 9-93590543 | H43: Maximo Hudson | I43: Al finalizar | J43: 430000 | K43: =IF(J43="","",IF(F43="SI",J43*0.19,0)) -> 0 | L43: =IF(J43="","",J43+K43) -> 430000 | M43: Recuperación de 8 cámaras IP y recuperación señal Protegus 2 | N43: Recuperación de 8 cámaras IP y recuperación señal Protegus 2 | O43: Aprobado
A44: 40 | B44: 45975 | C44: 90000002-1 | D44: {=IFERROR( INDEX(R_CLIENTES!B:B, MATCH(C44, R_CLIENTES!A:A, 0) ), "" )} -> Condominio Golf III | E44: {=IFERROR( INDEX(R_CLIENTES!G:G, MATCH(C44, R_CLIENTES!A:A, 0) ), "" )} -> Oscar Castro | F44: Si | G44: {=IFERROR( INDEX(R_CLIENTES!H:H, MATCH(C44, R_CLIENTES!A:A, 0) ), "" )} -> 9 9450 8233 | H44: Maximo Hudson | I44: 50 anticipo y 50 al finalizar | J44: 8250000 | K44: =IF(J44="","",IF(F44="SI",J44*0.19,0)) -> 1567500 | L44: =IF(J44="","",J44+K44) -> 9817500 | M44: Servicio de venta e instalación 17 cámaras IP en la perfiferia del Condominio con alcance de antenas inalámbricas. | N44: Servicio de instalación y puesta en marcha de circuito CCTV IP implementando antenas inalámbricas. | O44: Pendiente
A45: 41 | B45: 45979 | C45: 76470822-9 | D45: {=IFERROR( INDEX(R_CLIENTES!B:B, MATCH(C45, R_CLIENTES!A:A, 0) ), "" )} -> Sociedad Educacional Shalom SpA | E45: {=IFERROR( INDEX(R_CLIENTES!G:G, MATCH(C45, R_CLIENTES!A:A, 0) ), "" )} -> Jorge Adm | F45: Si | G45: {=IFERROR( INDEX(R_CLIENTES!H:H, MATCH(C45, R_CLIENTES!A:A, 0) ), "" )} -> 999847687 | H45: Maximo Hudson | I45: Al finalizar | J45: 200000 | K45: =IF(J45="","",IF(F45="SI",J45*0.19,0)) -> 38000 | L45: =IF(J45="","",J45+K45) -> 238000 | M45: Servicio de mantención Programada 2025 | N45: Servicio de mantención Programada 2025 | O45: Pendiente
A46: 42 | B46: 45979 | C46: 65216508-7 | D46: {=IFERROR( INDEX(R_CLIENTES!B:B, MATCH(C46, R_CLIENTES!A:A, 0) ), "" )} -> Condominio Mirador El Milagro | E46: {=IFERROR( INDEX(R_CLIENTES!G:G, MATCH(C46, R_CLIENTES!A:A, 0) ), "" )} -> Camila Godoy | F46: no | G46: {=IFERROR( INDEX(R_CLIENTES!H:H, MATCH(C46, R_CLIENTES!A:A, 0) ), "" )} -> 9-44637185 | H46: Maximo Hudson | I46: Al finalizar | J46: 136000 | K46: =IF(J46="","",IF(F46="SI",J46*0.19,0)) -> 0 | L46: =IF(J46="","",J46+K46) -> 136000 | M46: Venta de 8 controles NOVA 2CH | N46: Venta de 8 controles NOVA 2CH | O46: Aprobado
A47: 43 | B47: 45979 | C47: 56047780-5 | D47: {=IFERROR( INDEX(R_CLIENTES!B:B, MATCH(C47, R_CLIENTES!A:A, 0) ), "" )} -> Comunidad Edificio Florencia | E47: {=IFERROR( INDEX(R_CLIENTES!G:G, MATCH(C47, R_CLIENTES!A:A, 0) ), "" )} -> Guillermo Negrete | F47: no | G47: {=IFERROR( INDEX(R_CLIENTES!H:H, MATCH(C47, R_CLIENTES!A:A, 0) ), "" )} -> 9-93590543 | H47: Maximo Hudson | I47: Al finalizar | J47: 180000 | K47: =IF(J47="","",IF(F47="SI",J47*0.19,0)) -> 0 | L47: =IF(J47="","",J47+K47) -> 180000 | M47: Recuperación cámaras Torre 3, y configuración TCP/IP para visualizar CCTV por dispisitivos remotos | N47: Recuperación cámaras Torre 3, y configuración TCP/IP para visualizar CCTV por dispisitivos remotos | O47: Aprobado
A48: 44 | B48: 45980 | C48: 90000003-1 | D48: {=IFERROR( INDEX(R_CLIENTES!B:B, MATCH(C48, R_CLIENTES!A:A, 0) ), "" )} -> Juan Fernando Mancilla | E48: {=IFERROR( INDEX(R_CLIENTES!G:G, MATCH(C48, R_CLIENTES!A:A, 0) ), "" )} -> Juan Fernando Mancilla | F48: no | G48: {=IFERROR( INDEX(R_CLIENTES!H:H, MATCH(C48, R_CLIENTES!A:A, 0) ), "" )} -> 999680974 | H48: Maximo Hudson | I48: Al finalizar | J48: 240000 | K48: =IF(J48="","",IF(F48="SI",J48*0.19,0)) -> 0 | L48: =IF(J48="","",J48+K48) -> 240000 | M48: Instalación de chapa S821MAX | N48: Instalación de chapa S821MAX | O48: Aprobado
A49: 45 | B49: 45986 | C49: 56047780-5 | D49: {=IFERROR( INDEX(R_CLIENTES!B:B, MATCH(C49, R_CLIENTES!A:A, 0) ), "" )} -> Comunidad Edificio Florencia | E49: {=IFERROR( INDEX(R_CLIENTES!G:G, MATCH(C49, R_CLIENTES!A:A, 0) ), "" )} -> Guillermo Negrete | F49: no | G49: {=IFERROR( INDEX(R_CLIENTES!H:H, MATCH(C49, R_CLIENTES!A:A, 0) ), "" )} -> 9-93590543 | H49: Maximo Hudson | I49: Al finalizar | J49: 1130000 | K49: =IF(J49="","",IF(F49="SI",J49*0.19,0)) -> 0 | L49: =IF(J49="","",J49+K49) -> 1130000 | M49: Motor D10 Turbo c Instalación | N49: Motor D10 Turbo | O49: Aprobado
A50: 46 | B50: 45987 | C50: 65242132-6 | D50: {=IFERROR( INDEX(R_CLIENTES!B:B, MATCH(C50, R_CLIENTES!A:A, 0) ), "" )} -> Condominio Alto Bellavista | E50: {=IFERROR( INDEX(R_CLIENTES!G:G, MATCH(C50, R_CLIENTES!A:A, 0) ), "" )} -> Maria Antoniera del Pino | F50: Si | G50: {=IFERROR( INDEX(R_CLIENTES!H:H, MATCH(C50, R_CLIENTES!A:A, 0) ), "" )} -> 9-84398698 | H50: Maximo Hudson | I50: Al finalizar | J50: 750000 | K50: =IF(J50="","",IF(F50="SI",J50*0.19,0)) -> 142500 | L50: =IF(J50="","",J50+K50) -> 892500 | M50: Servicio de recuperación , rectificación y mantención de motor D10 Turbo y estructura general. | N50: Servicio de recuperación , rectificación y mantención de motor D10 Turbo y estructura general. | O50: Pendiente
A51: 47 | B51: 45992 | C51: 53320939-4 | D51: {=IFERROR( INDEX(R_CLIENTES!B:B, MATCH(C51, R_CLIENTES!A:A, 0) ), "" )} -> Condominio Paseo Peñuelas | E51: {=IFERROR( INDEX(R_CLIENTES!G:G, MATCH(C51, R_CLIENTES!A:A, 0) ), "" )} -> Adm Victor Figueroa | F51: no | G51: {=IFERROR( INDEX(R_CLIENTES!H:H, MATCH(C51, R_CLIENTES!A:A, 0) ), "" )} -> 9-59823214 | H51: Maximo Hudson | I51: 50 anticipo y 50 al finalizar | J51: 3304000 | K51: =IF(J51="","",IF(F51="SI",J51*0.19,0)) -> 0 | L51: =IF(J51="","",J51+K51) -> 3304000 | M51: Valor CCTV equipos principales e instalación de cámaras en periferia de garita; | N51: Presupuesto c/ Levantamiento donde se detallan las correcciones y materiales. | O51: Pendiente
A52: 48 | B52: 45992 | C52: 53320939-4 | D52: {=IFERROR( INDEX(R_CLIENTES!B:B, MATCH(C52, R_CLIENTES!A:A, 0) ), "" )} -> Condominio Paseo Peñuelas | E52: {=IFERROR( INDEX(R_CLIENTES!G:G, MATCH(C52, R_CLIENTES!A:A, 0) ), "" )} -> Adm Victor Figueroa | F52: no | G52: {=IFERROR( INDEX(R_CLIENTES!H:H, MATCH(C52, R_CLIENTES!A:A, 0) ), "" )} -> 9-59823214 | H52: Maximo Hudson | I52: 0 a 30 días | J52: 4825000 | K52: =IF(J52="","",IF(F52="SI",J52*0.19,0)) -> 0 | L52: =IF(J52="","",J52+K52) -> 4825000 | M52: Valor CCTV Estacionamiento y estaciones inalámbricas. | N52: Presupuesto c/ Levantamiento donde se detallan las correcciones y materiales. | O52: Pendiente
A53: 49 | B53: 45992 | C53: 53320939-4 | D53: {=IFERROR( INDEX(R_CLIENTES!B:B, MATCH(C53, R_CLIENTES!A:A, 0) ), "" )} -> Condominio Paseo Peñuelas | E53: {=IFERROR( INDEX(R_CLIENTES!G:G, MATCH(C53, R_CLIENTES!A:A, 0) ), "" )} -> Adm Victor Figueroa | F53: no | G53: {=IFERROR( INDEX(R_CLIENTES!H:H, MATCH(C53, R_CLIENTES!A:A, 0) ), "" )} -> 9-59823214 | H53: Maximo Hudson | I53: 33% inicial 33% a 30 días y 33% a 60 días | J53: 10871000 | K53: =IF(J53="","",IF(F53="SI",J53*0.19,0)) -> 0 | L53: =IF(J53="","",J53+K53) -> 10871000 | M53: Valor CCTV Áreas comunes, pasillos y accesos peatonales. | N53: Presupuesto c/ Levantamiento donde se detallan las correcciones y materiales. | O53: Pendiente
... A61: 57 | B61: 46017 | C61: 65198585-4 | D61: {=IFERROR( INDEX(R_CLIENTES!B:B, MATCH(C61, R_CLIENTES!A:A, 0) ), "" )} -> Condominio Vicenza II | E61: {=IFERROR( INDEX(R_CLIENTES!G:G, MATCH(C61, R_CLIENTES!A:A, 0) ), "" )} -> Mauricio Araya | F61: Si | G61: {=IFERROR( INDEX(R_CLIENTES!H:H, MATCH(C61, R_CLIENTES!A:A, 0) ), "" )} -> 9-97269955 | H61: Maximo Hudson | I61: Al finalizar | J61: 110000 | K61: =IF(J61="","",IF(F61="SI",J61*0.19,0)) -> 20900 | L61: =IF(J61="","",J61+K61) -> 130900 | M61: Renovación de retenedor electromagnético Torre B (Incluye Mano de obra) | N61: Renovación de retenedor electromagnético Torre B (Incluye Mano de obra) | O61: Pendiente
A62: 58 | B62: 46017 | C62: 53332414-2 | D62: {=IFERROR( INDEX(R_CLIENTES!B:B, MATCH(C62, R_CLIENTES!A:A, 0) ), "" )} -> Portal del Valle II | E62: {=IFERROR( INDEX(R_CLIENTES!G:G, MATCH(C62, R_CLIENTES!A:A, 0) ), "" )} -> Mauricio Araya | F62: Si | G62: {=IFERROR( INDEX(R_CLIENTES!H:H, MATCH(C62, R_CLIENTES!A:A, 0) ), "" )} -> 9-97269955 | H62: Maximo Hudson | I62: Al finalizar | J62: 200000 | K62: =IF(J62="","",IF(F62="SI",J62*0.19,0)) -> 38000 | L62: =IF(J62="","",J62+K62) -> 238000 | M62: Recuperación de portón chocado (incluye reparación, renovación de partes de dañadas y configuración)
A63: 59 | B63: 46386 | C63: 65198585-4 | D63: {=IFERROR( INDEX(R_CLIENTES!B:B, MATCH(C63, R_CLIENTES!A:A, 0) ), "" )} -> Condominio Vicenza II | E63: {=IFERROR( INDEX(R_CLIENTES!G:G, MATCH(C63, R_CLIENTES!A:A, 0) ), "" )} -> Mauricio Araya | F63: Si | G63: {=IFERROR( INDEX(R_CLIENTES!H:H, MATCH(C63, R_CLIENTES!A:A, 0) ), "" )} -> 9-97269955 | H63: Maximo Hudson | I63: Al finalizar | J63: 250000 | K63: =IF(J63="","",IF(F63="SI",J63*0.19,0)) -> 47500 | L63: =IF(J63="","",J63+K63) -> 297500 | M63: Servicio de mantención CCTV | N63: Servicio de mantención CCTV | O63: Pendiente
A64: 60 | B64: 46030 | C64: 65198585-4 | D64: {=IFERROR( INDEX(R_CLIENTES!B:B, MATCH(C64, R_CLIENTES!A:A, 0) ), "" )} -> Condominio Vicenza II | E64: {=IFERROR( INDEX(R_CLIENTES!G:G, MATCH(C64, R_CLIENTES!A:A, 0) ), "" )} -> Mauricio Araya | F64: Si | G64: {=IFERROR( INDEX(R_CLIENTES!H:H, MATCH(C64, R_CLIENTES!A:A, 0) ), "" )} -> 9-97269955 | H64: Maximo Hudson | I64: Al finalizar | J64: 325000 | K64: =IF(J64="","",IF(F64="SI",J64*0.19,0)) -> 61750 | L64: =IF(J64="","",J64+K64) -> 386750 | M64: Servicio de cambio de retenedor magnético (Incluye cambio de suministro) y cambio de digitador Torre B) | N64: Servicio de cambio de retenedor magnético (Incluye cambio de suministro) y cambio de digitador Torre B) | O64: Pendiente
A65: 61 | B65: 46030 | C65: 65198585-4 | D65: {=IFERROR( INDEX(R_CLIENTES!B:B, MATCH(C65, R_CLIENTES!A:A, 0) ), "" )} -> Condominio Vicenza II | E65: {=IFERROR( INDEX(R_CLIENTES!G:G, MATCH(C65, R_CLIENTES!A:A, 0) ), "" )} -> Mauricio Araya | F65: no | G65: {=IFERROR( INDEX(R_CLIENTES!H:H, MATCH(C65, R_CLIENTES!A:A, 0) ), "" )} -> 9-97269955 | H65: Maximo Hudson | I65: Al finalizar | J65: 325000 | K65: =IF(J65="","",IF(F65="SI",J65*0.19,0)) -> 0 | L65: =IF(J65="","",J65+K65) -> 325000 | M65: Servicio de cambio de retenedor magnético (Incluye cambio de suministro) y cambio de digitador Torre B) | N65: Servicio de cambio de retenedor magnético (Incluye cambio de suministro) y cambio de digitador Torre B) | O65: Pendiente
A66: 62 | B66: 46037 | C66: 65.229.898-2 | D66: {=IFERROR( INDEX(R_CLIENTES!B:B, MATCH(C66, R_CLIENTES!A:A, 0) ), "" )} -> Distrito Verde I | E66: {=IFERROR( INDEX(R_CLIENTES!G:G, MATCH(C66, R_CLIENTES!A:A, 0) ), "" )} -> Maria Antonieta del Pino | F66: Si | G66: {=IFERROR( INDEX(R_CLIENTES!H:H, MATCH(C66, R_CLIENTES!A:A, 0) ), "" )} -> 9-84398698 | H66: Maximo Hudson | I66: Al finalizar | J66: 200000 | K66: =IF(J66="","",IF(F66="SI",J66*0.19,0)) -> 38000 | L66: =IF(J66="","",J66+K66) -> 238000 | M66: Manteción programada 2026 (Se adjunta check list de mantención a cotización) | N66: Manteción programada 2026 (Se adjunta check list de mantención a cotización) | O66: Pendiente
A67: 63 | B67: 46041 | C67: 53.312.705-3 | D67: {=IFERROR( INDEX(R_CLIENTES!B:B, MATCH(C67, R_CLIENTES!A:A, 0) ), "" )} -> Condominio Palermo | E67: {=IFERROR( INDEX(R_CLIENTES!G:G, MATCH(C67, R_CLIENTES!A:A, 0) ), "" )} -> Elvis Díaz | F67: Si | G67: {=IFERROR( INDEX(R_CLIENTES!H:H, MATCH(C67, R_CLIENTES!A:A, 0) ), "" )} -> 9-39074968 | H67: Maximo Hudson | I67: 50 anticipo y 50 al finalizar | J67: 1558000 | K67: =IF(J67="","",IF(F67="SI",J67*0.19,0)) -> 296020 | L67: =IF(J67="","",J67+K67) -> 1854020 | M67: Instalación de motor Centurion D10 Standard (26 mts x min) con 6 cremalleras, baliza, fotoceldas, cambio de ruedas (100x100 ) mano de obra y configuración. | N67: Instalación de motor Centurion D10 Standard (26 mts x min) con 6 cremalleras, baliza, fotoceldas, cambio de ruedas (100x100 ) mano de obra y configuración. | O67: Pendiente
A68: 64 | B68: 46041 | C68: 53.312.705-3 | D68: {=IFERROR( INDEX(R_CLIENTES!B:B, MATCH(C68, R_CLIENTES!A:A, 0) ), "" )} -> Condominio Palermo | E68: {=IFERROR( INDEX(R_CLIENTES!G:G, MATCH(C68, R_CLIENTES!A:A, 0) ), "" )} -> Elvis Díaz | F68: Si | G68: {=IFERROR( INDEX(R_CLIENTES!H:H, MATCH(C68, R_CLIENTES!A:A, 0) ), "" )} -> 9-39074968 | H68: Maximo Hudson | I68: 50 anticipo y 50 al finalizar | J68: 1700000 | K68: =IF(J68="","",IF(F68="SI",J68*0.19,0)) -> 323000 | L68: =IF(J68="","",J68+K68) -> 2023000 | M68: Instalación de motor Centurion D10 Turbo (45 mts x min) con 6 cremalleras, baliza, fotoceldas, cambio de ruedas (100x100 ) mano de obra y configuración. | N68: Instalación de motor Centurion D10 Turbo (45 mts x min) con 6 cremalleras, baliza, fotoceldas, cambio de ruedas (100x100 ) mano de obra y configuración. | O68: Pendiente
A69: 65 | B69: 46048 | C69: 65.095.336-2 | D69: {=IFERROR( INDEX(R_CLIENTES!B:B, MATCH(C69, R_CLIENTES!A:A, 0) ), "" )} -> Condominio Neo Spazio | E69: {=IFERROR( INDEX(R_CLIENTES!G:G, MATCH(C69, R_CLIENTES!A:A, 0) ), "" )} -> Guillermo Negrete | F69: no | G69: {=IFERROR( INDEX(R_CLIENTES!H:H, MATCH(C69, R_CLIENTES!A:A, 0) ), "" )} -> 9-93590543 | H69: Maximo Hudson | I69: 50 anticipo y 50 al finalizar | J69: 360000 | K69: =IF(J69="","",IF(F69="SI",J69*0.19,0)) -> 0 | L69: =IF(J69="","",J69+K69) -> 360000 | M69: Re instalación de cremalleras, desengrase de rodamiento, recorridos, piñón de motor (Incluye cremalleras) Configuración y puesta en marcha. | N69: Re instalación de cremalleras, desengrase de rodamiento, recorridos, piñón de motor (Incluye cremalleras) Configuración y puesta en marcha motor Nice Drive1000. | O69: Aprobado
A70: 66 | B70: 46048 | C70: 56047780-5 | D70: {=IFERROR( INDEX(R_CLIENTES!B:B, MATCH(C70, R_CLIENTES!A:A, 0) ), "" )} -> Comunidad Edificio Florencia | E70: {=IFERROR( INDEX(R_CLIENTES!G:G, MATCH(C70, R_CLIENTES!A:A, 0) ), "" )} -> Guillermo Negrete | F70: no | G70: {=IFERROR( INDEX(R_CLIENTES!H:H, MATCH(C70, R_CLIENTES!A:A, 0) ), "" )} -> 9-93590543 | H70: Maximo Hudson | I70: Al finalizar | J70: 170000 | K70: =IF(J70="","",IF(F70="SI",J70*0.19,0)) -> 0 | L70: =IF(J70="","",J70+K70) -> 170000 | M70: 10 Controles NOVA Centurion | N70: 10 Controles NOVA Centurion | O70: Aprobado
A71: 67 | B71: 46056 | C71: 65.049.582-9 | D71: {=IFERROR( INDEX(R_CLIENTES!B:B, MATCH(C71, R_CLIENTES!A:A, 0) ), "" )} -> Espacio Urbano | E71: {=IFERROR( INDEX(R_CLIENTES!G:G, MATCH(C71, R_CLIENTES!A:A, 0) ), "" )} -> Gypsy Adm | F71: Si | G71: {=IFERROR( INDEX(R_CLIENTES!H:H, MATCH(C71, R_CLIENTES!A:A, 0) ), "" )} -> 9 6287 8932 | H71: Maximo Hudson | I71: 50 anticipo y 50 al finalizar | J71: 1000000 | K71: =IF(J71="","",IF(F71="SI",J71*0.19,0)) -> 190000 | L71: =IF(J71="","",J71+K71) -> 1190000 | M71: Kit Centurion D6 para portón de 200 Kgs , 200 mil ciclos de vida útiles, cremalleras, y baliza se incluyen en el servicio. | N71: Kit Centurion D6 para portón de 200 Kgs , 200 mil ciclos de vida útiles, cremalleras, Y fotoceldas se incluyen en el servicio. | O71: Pendiente
A72: 68 | B72: 46056 | C72: 76866075-1 | D72: {=IFERROR( INDEX(R_CLIENTES!B:B, MATCH(C72, R_CLIENTES!A:A, 0) ), "" )} -> Paseo San Carlos VII | E72: {=IFERROR( INDEX(R_CLIENTES!G:G, MATCH(C72, R_CLIENTES!A:A, 0) ), "" )} -> Claudio García | F72: Si | G72: {=IFERROR( INDEX(R_CLIENTES!H:H, MATCH(C72, R_CLIENTES!A:A, 0) ), "" )} -> 9-84398698 | H72: Maximo Hudson | I72: Al finalizar | J72: 130000 | K72: =IF(J72="","",IF(F72="SI",J72*0.19,0)) -> 24700 | L72: =IF(J72="","",J72+K72) -> 154700 | M72: Cambio de ruedas 100x100 (2) | N72: Cambio de ruedas 100x100 (2) | O72: Pendiente
A73: 69 | B73: 46062 | C73: 65.066.845-6 | D73: {=IFERROR( INDEX(R_CLIENTES!B:B, MATCH(C73, R_CLIENTES!A:A, 0) ), "" )} -> Condominio Ossandon | E73: {=IFERROR( INDEX(R_CLIENTES!G:G, MATCH(C73, R_CLIENTES!A:A, 0) ), "" )} -> Diego Palma | F73: Si | G73: {=IFERROR( INDEX(R_CLIENTES!H:H, MATCH(C73, R_CLIENTES!A:A, 0) ), "" )} -> 9 9969 8228 | H73: Maximo Hudson | I73: 50 anticipo y 50 al finalizar | J73: 440000 | K73: =IF(J73="","",IF(F73="SI",J73*0.19,0)) -> 83600 | L73: =IF(J73="","",J73+K73) -> 523600 | M73: Instalación de sistema de apertura Wifi para motor Centurion. para cada motor (2), incluye capacitación de uso para administración y enrolamientos al sistema, NECESARIO contar con Wifi para enlazar dispositivo a la red del condominio. | N73: Instalación de sistema de apertura Wifi para motor Centurion. para cada motor (2), incluye capacitación de uso para administración y enrolamientos al sistema, NECESARIO contar con Wifi para enlazar dispositivo a la red del condominio. | O73: Pendiente
A74: 70 | B74: 46062 | C74: 65.066.845-6 | D74: {=IFERROR( INDEX(R_CLIENTES!B:B, MATCH(C74, R_CLIENTES!A:A, 0) ), "" )} -> Condominio Ossandon | E74: {=IFERROR( INDEX(R_CLIENTES!G:G, MATCH(C74, R_CLIENTES!A:A, 0) ), "" )} -> Diego Palma | F74: Si | G74: {=IFERROR( INDEX(R_CLIENTES!H:H, MATCH(C74, R_CLIENTES!A:A, 0) ), "" )} -> 9 9969 8228 | H74: Maximo Hudson | I74: Al finalizar | J74: 300000 | K74: =IF(J74="","",IF(F74="SI",J74*0.19,0)) -> 57000 | L74: =IF(J74="","",J74+K74) -> 357000 | M74: Manteción programada 2026 (Se adjunta check list de mantención a cotización) 2 portones del condominio. | N74: Manteción programada 2026 (Se adjunta check list de mantención a cotización) 2 portones del condominio. | O74: Pendiente
... A91: 87 | B91: 46085 | C91: 65.066.845-6 | D91: {=IFERROR( INDEX(R_CLIENTES!B:B, MATCH(C91, R_CLIENTES!A:A, 0) ), "" )} -> Condominio Ossandon | E91: {=IFERROR( INDEX(R_CLIENTES!G:G, MATCH(C91, R_CLIENTES!A:A, 0) ), "" )} -> Diego Palma | F91: Si | G91: {=IFERROR( INDEX(R_CLIENTES!H:H, MATCH(C91, R_CLIENTES!A:A, 0) ), "" )} -> 9 9969 8228 | H91: Maximo Hudson | I91: 0 a 30 días | J91: 1595000 | K91: =IF(J91="","",IF(F91="SI",J91*0.19,0)) -> 303050 | L91: =IF(J91="","",J91+K91) -> 1898050 | M91: Nodo 4 (8) Piso del 5 al 2 | N91: Instalación CCTV de cámaras pisos 5 al 2 (8 cámaras) | O91: Pendiente
D92: {=IFERROR( INDEX(R_CLIENTES!B:B, MATCH(C92, R_CLIENTES!A:A, 0) ), "" )} | E92: {=IFERROR( INDEX(R_CLIENTES!G:G, MATCH(C92, R_CLIENTES!A:A, 0) ), "" )} | G92: {=IFERROR( INDEX(R_CLIENTES!H:H, MATCH(C92, R_CLIENTES!A:A, 0) ), "" )} | K92: =IF(J92="","",IF(F92="SI",J92*0.19,0)) | L92: =IF(J92="","",J92+K92)
D93: {=IFERROR( INDEX(R_CLIENTES!B:B, MATCH(C93, R_CLIENTES!A:A, 0) ), "" )} | E93: {=IFERROR( INDEX(R_CLIENTES!G:G, MATCH(C93, R_CLIENTES!A:A, 0) ), "" )} | G93: {=IFERROR( INDEX(R_CLIENTES!H:H, MATCH(C93, R_CLIENTES!A:A, 0) ), "" )} | K93: =IF(J93="","",IF(F93="SI",J93*0.19,0)) | L93: =IF(J93="","",J93+K93)
D94: {=IFERROR( INDEX(R_CLIENTES!B:B, MATCH(C94, R_CLIENTES!A:A, 0) ), "" )} | E94: {=IFERROR( INDEX(R_CLIENTES!G:G, MATCH(C94, R_CLIENTES!A:A, 0) ), "" )} | G94: {=IFERROR( INDEX(R_CLIENTES!H:H, MATCH(C94, R_CLIENTES!A:A, 0) ), "" )} | K94: =IF(J94="","",IF(F94="SI",J94*0.19,0)) | L94: =IF(J94="","",J94+K94)
D95: {=IFERROR( INDEX(R_CLIENTES!B:B, MATCH(C95, R_CLIENTES!A:A, 0) ), "" )} | E95: {=IFERROR( INDEX(R_CLIENTES!G:G, MATCH(C95, R_CLIENTES!A:A, 0) ), "" )} | G95: {=IFERROR( INDEX(R_CLIENTES!H:H, MATCH(C95, R_CLIENTES!A:A, 0) ), "" )} | K95: =IF(J95="","",IF(F95="SI",J95*0.19,0)) | L95: =IF(J95="","",J95+K95)
D96: {=IFERROR( INDEX(R_CLIENTES!B:B, MATCH(C96, R_CLIENTES!A:A, 0) ), "" )} | E96: {=IFERROR( INDEX(R_CLIENTES!G:G, MATCH(C96, R_CLIENTES!A:A, 0) ), "" )} | G96: {=IFERROR( INDEX(R_CLIENTES!H:H, MATCH(C96, R_CLIENTES!A:A, 0) ), "" )} | K96: =IF(J96="","",IF(F96="SI",J96*0.19,0)) | L96: =IF(J96="","",J96+K96)
D97: {=IFERROR( INDEX(R_CLIENTES!B:B, MATCH(C97, R_CLIENTES!A:A, 0) ), "" )} | E97: {=IFERROR( INDEX(R_CLIENTES!G:G, MATCH(C97, R_CLIENTES!A:A, 0) ), "" )} | G97: {=IFERROR( INDEX(R_CLIENTES!H:H, MATCH(C97, R_CLIENTES!A:A, 0) ), "" )} | K97: =IF(J97="","",IF(F97="SI",J97*0.19,0)) | L97: =IF(J97="","",J97+K97)
D98: {=IFERROR( INDEX(R_CLIENTES!B:B, MATCH(C98, R_CLIENTES!A:A, 0) ), "" )} | E98: {=IFERROR( INDEX(R_CLIENTES!G:G, MATCH(C98, R_CLIENTES!A:A, 0) ), "" )} | G98: {=IFERROR( INDEX(R_CLIENTES!H:H, MATCH(C98, R_CLIENTES!A:A, 0) ), "" )} | K98: =IF(J98="","",IF(F98="SI",J98*0.19,0)) | L98: =IF(J98="","",J98+K98)
D99: {=IFERROR( INDEX(R_CLIENTES!B:B, MATCH(C99, R_CLIENTES!A:A, 0) ), "" )} | E99: {=IFERROR( INDEX(R_CLIENTES!G:G, MATCH(C99, R_CLIENTES!A:A, 0) ), "" )} | G99: {=IFERROR( INDEX(R_CLIENTES!H:H, MATCH(C99, R_CLIENTES!A:A, 0) ), "" )} | K99: =IF(J99="","",IF(F99="SI",J99*0.19,0)) | L99: =IF(J99="","",J99+K99)
D100: {=IFERROR( INDEX(R_CLIENTES!B:B, MATCH(C100, R_CLIENTES!A:A, 0) ), "" )} | E100: {=IFERROR( INDEX(R_CLIENTES!G:G, MATCH(C100, R_CLIENTES!A:A, 0) ), "" )} | G100: {=IFERROR( INDEX(R_CLIENTES!H:H, MATCH(C100, R_CLIENTES!A:A, 0) ), "" )} | K100: =IF(J100="","",IF(F100="SI",J100*0.19,0)) | L100: =IF(J100="","",J100+K100)
D101: {=IFERROR( INDEX(R_CLIENTES!B:B, MATCH(C101, R_CLIENTES!A:A, 0) ), "" )} | E101: {=IFERROR( INDEX(R_CLIENTES!G:G, MATCH(C101, R_CLIENTES!A:A, 0) ), "" )} | G101: {=IFERROR( INDEX(R_CLIENTES!H:H, MATCH(C101, R_CLIENTES!A:A, 0) ), "" )} | K101: =IF(J101="","",IF(F101="SI",J101*0.19,0)) | L101: =IF(J101="","",J101+K101)
D102: {=IFERROR( INDEX(R_CLIENTES!B:B, MATCH(C102, R_CLIENTES!A:A, 0) ), "" )} | E102: {=IFERROR( INDEX(R_CLIENTES!G:G, MATCH(C102, R_CLIENTES!A:A, 0) ), "" )} | G102: {=IFERROR( INDEX(R_CLIENTES!H:H, MATCH(C102, R_CLIENTES!A:A, 0) ), "" )} | K102: =IF(J102="","",IF(F102="SI",J102*0.19,0)) | L102: =IF(J102="","",J102+K102)
D103: {=IFERROR( INDEX(R_CLIENTES!B:B, MATCH(C103, R_CLIENTES!A:A, 0) ), "" )} | E103: {=IFERROR( INDEX(R_CLIENTES!G:G, MATCH(C103, R_CLIENTES!A:A, 0) ), "" )} | G103: {=IFERROR( INDEX(R_CLIENTES!H:H, MATCH(C103, R_CLIENTES!A:A, 0) ), "" )} | K103: =IF(J103="","",IF(F103="SI",J103*0.19,0)) | L103: =IF(J103="","",J103+K103)
... D321: {=IFERROR( INDEX(R_CLIENTES!B:B, MATCH(C321, R_CLIENTES!A:A, 0) ), "" )} | E321: {=IFERROR( INDEX(R_CLIENTES!G:G, MATCH(C321, R_CLIENTES!A:A, 0) ), "" )} | G321: {=IFERROR( INDEX(R_CLIENTES!H:H, MATCH(C321, R_CLIENTES!A:A, 0) ), "" )} | K321: =IF(J321="","",IF(F321="SI",J321*0.19,0)) | L321: =IF(J321="","",J321+K321)
D322: {=IFERROR( INDEX(R_CLIENTES!B:B, MATCH(C322, R_CLIENTES!A:A, 0) ), "" )} | E322: {=IFERROR( INDEX(R_CLIENTES!G:G, MATCH(C322, R_CLIENTES!A:A, 0) ), "" )} | K322: =IF(J322="","",IF(F322="SI",J322*0.19,0)) | L322: =IF(J322="","",J322+K322)
D323: {=IFERROR( INDEX(R_CLIENTES!B:B, MATCH(C323, R_CLIENTES!A:A, 0) ), "" )} | K323: =IF(J323="","",IF(F323="SI",J323*0.19,0)) | L323: =IF(J323="","",J323+K323)
D324: {=IFERROR( INDEX(R_CLIENTES!B:B, MATCH(C324, R_CLIENTES!A:A, 0) ), "" )} | K324: =IF(J324="","",IF(F324="SI",J324*0.19,0)) | L324: =IF(J324="","",J324+K324)
D325: {=IFERROR( INDEX(R_CLIENTES!B:B, MATCH(C325, R_CLIENTES!A:A, 0) ), "" )} | K325: =IF(J325="","",IF(F325="SI",J325*0.19,0)) | L325: =IF(J325="","",J325+K325)
D326: {=IFERROR( INDEX(R_CLIENTES!B:B, MATCH(C326, R_CLIENTES!A:A, 0) ), "" )} | K326: =IF(J326="","",IF(F326="SI",J326*0.19,0)) | L326: =IF(J326="","",J326+K326)
D327: {=IFERROR( INDEX(R_CLIENTES!B:B, MATCH(C327, R_CLIENTES!A:A, 0) ), "" )} | K327: =IF(J327="","",IF(F327="SI",J327*0.19,0)) | L327: =IF(J327="","",J327+K327)
D328: {=IFERROR( INDEX(R_CLIENTES!B:B, MATCH(C328, R_CLIENTES!A:A, 0) ), "" )} | K328: =IF(J328="","",IF(F328="SI",J328*0.19,0)) | L328: =IF(J328="","",J328+K328)
D329: {=IFERROR( INDEX(R_CLIENTES!B:B, MATCH(C329, R_CLIENTES!A:A, 0) ), "" )} | K329: =IF(J329="","",IF(F329="SI",J329*0.19,0)) | L329: =IF(J329="","",J329+K329)
D330: {=IFERROR( INDEX(R_CLIENTES!B:B, MATCH(C330, R_CLIENTES!A:A, 0) ), "" )} | K330: =IF(J330="","",IF(F330="SI",J330*0.19,0)) | L330: =IF(J330="","",J330+K330)
D331: {=IFERROR( INDEX(R_CLIENTES!B:B, MATCH(C331, R_CLIENTES!A:A, 0) ), "" )} | K331: =IF(J331="","",IF(F331="SI",J331*0.19,0)) | L331: =IF(J331="","",J331+K331)
D332: {=IFERROR( INDEX(R_CLIENTES!B:B, MATCH(C332, R_CLIENTES!A:A, 0) ), "" )} | K332: =IF(J332="","",IF(F332="SI",J332*0.19,0)) | L332: =IF(J332="","",J332+K332)
D333: {=IFERROR( INDEX(R_CLIENTES!B:B, MATCH(C333, R_CLIENTES!A:A, 0) ), "" )} | K333: =IF(J333="","",IF(F333="SI",J333*0.19,0)) | L333: =IF(J333="","",J333+K333)
D334: {=IFERROR( INDEX(R_CLIENTES!B:B, MATCH(C334, R_CLIENTES!A:A, 0) ), "" )} | K334: =IF(J334="","",IF(F334="SI",J334*0.19,0)) | L334: =IF(J334="","",J334+K334)
... D439: {=IFERROR( INDEX(R_CLIENTES!B:B, MATCH(C439, R_CLIENTES!A:A, 0) ), "" )} | K439: =IF(J439="","",IF(F439="SI",J439*0.19,0)) | L439: =IF(J439="","",J439+K439)
K440: =IF(J440="","",IF(F440="SI",J440*0.19,0)) | L440: =IF(J440="","",J440+K440)
K441: =IF(J441="","",IF(F441="SI",J441*0.19,0)) | L441: =IF(J441="","",J441+K441)
K442: =IF(J442="","",IF(F442="SI",J442*0.19,0)) | L442: =IF(J442="","",J442+K442)
K443: =IF(J443="","",IF(F443="SI",J443*0.19,0)) | L443: =IF(J443="","",J443+K443)
K444: =IF(J444="","",IF(F444="SI",J444*0.19,0)) | L444: =IF(J444="","",J444+K444)
K445: =IF(J445="","",IF(F445="SI",J445*0.19,0)) | L445: =IF(J445="","",J445+K445)
K446: =IF(J446="","",IF(F446="SI",J446*0.19,0)) | L446: =IF(J446="","",J446+K446)
K447: =IF(J447="","",IF(F447="SI",J447*0.19,0)) | L447: =IF(J447="","",J447+K447)
K448: =IF(J448="","",IF(F448="SI",J448*0.19,0)) | L448: =IF(J448="","",J448+K448)
K449: =IF(J449="","",IF(F449="SI",J449*0.19,0)) | L449: =IF(J449="","",J449+K449)
K450: =IF(J450="","",IF(F450="SI",J450*0.19,0)) | L450: =IF(J450="","",J450+K450)
...

Sheet Detalle Cotización
A1: Detalle de cotizaciones
A3: Columna 1 | B3: Nro Cot | C3: Nro de fila | D3: Cliente | E3: RUT | F3: IVA | G3: Proveedor | H3: Cod | I3: Producto / Servicio | J3: Cant | K3: Valor unitario | L3: Descuento | M3: Sub- Total unitario | N3: VALOR IVA | O3: Total Uni | P3: Total acumulado | Q3: Margen Unitario | R3: Margen acumulado | S3: Columna 2
A4: =B4&"-"&C4 -> 1-1 | B4: =IF(R_COTIZACIONES!A4="","",R_COTIZACIONES!A4) -> 1 | C4: =IF(B4="","",COUNTIF($B$4:B4,B4)) -> 1 | D4: {=IF(B4="","",IFERROR( INDEX(R_COTIZACIONES!D:D,MATCH(B4,R_COTIZACIONES!A:A,0)), ""))} -> Condominio Mirador Los Clarines | E4: {=IF(B4="","",IFERROR( INDEX(R_COTIZACIONES!C:C,MATCH(B4,R_COTIZACIONES!A:A,0)), ""))} -> 53334332-5 | F4: Si | G4: Particular | H4: S07 | I4: =IF(H4="","",VLOOKUP(H4,'Base de datos'!$E:$G,3,FALSE)) -> Mantención programada | J4: 1 | K4: =IF(H4="","",VLOOKUP(H4,'Base de datos'!E:N,10,FALSE)) -> 200000 | L4: 0 | M4: =IF(K4="","",J4*K4*(1-IFERROR(L4,0))) -> 200000 | N4: =IF(M4="","",IF(F4="SI",M4*0.19,0)) -> 38000 | O4: =IF(K4="","",M4+N4) -> 238000 | P4: =IF(K4="","",SUMIF($B:$B,B4,$O:$O)) -> 238000 | Q4: =IF(H4="","",VLOOKUP(H4,'Base de datos'!E:M,9,FALSE)) -> 100000 | R4: =IF(Q4="","",SUMIF($B:$B,B4,$Q:$Q)) -> 100000
A5: =B5&"-"&C5 -> 2-1 | B5: 2 | C5: =IF(B5="","",COUNTIF($B$4:B5,B5)) -> 1 | D5: {=IF(B5="","",IFERROR( INDEX(R_COTIZACIONES!D:D,MATCH(B5,R_COTIZACIONES!A:A,0)), ""))} -> Condominio Colinas del Milagro | E5: {=IF(B5="","",IFERROR( INDEX(R_COTIZACIONES!C:C,MATCH(B5,R_COTIZACIONES!A:A,0)), ""))} -> 53333086-k | F5: Si | G5: Particular | H5: S07 | I5: =IF(H5="","",VLOOKUP(H5,'Base de datos'!$E:$G,3,FALSE)) -> Mantención programada | J5: 1 | K5: =IF(H5="","",VLOOKUP(H5,'Base de datos'!E:N,10,FALSE)) -> 200000 | L5: 0 | M5: =IF(K5="","",J5*K5*(1-IFERROR(L5,0))) -> 200000 | N5: =IF(M5="","",IF(F5="SI",M5*0.19,0)) -> 38000 | O5: =IF(K5="","",M5+N5) -> 238000 | P5: =IF(K5="","",SUMIF($B:$B,B5,$O:$O)) -> 238000 | Q5: =IF(H5="","",VLOOKUP(H5,'Base de datos'!E:M,9,FALSE)) -> 100000 | R5: =IF(Q5="","",SUMIF($B:$B,B5,$Q:$Q)) -> 100000
A6: =B6&"-"&C6 -> 3-1 | B6: 3 | C6: =IF(B6="","",COUNTIF($B$4:B6,B6)) -> 1 | D6: {=IF(B6="","",IFERROR( INDEX(R_COTIZACIONES!D:D,MATCH(B6,R_COTIZACIONES!A:A,0)), ""))} -> Comunidad Edificio Florencia | E6: {=IF(B6="","",IFERROR( INDEX(R_COTIZACIONES!C:C,MATCH(B6,R_COTIZACIONES!A:A,0)), ""))} -> 56047780-5 | F6: Si | G6: RW | H6: WP17 | I6: =IF(H6="","",VLOOKUP(H6,'Base de datos'!$E:$G,3,FALSE)) -> Controlador Wifi WP17 | J6: 1 | K6: 220000 | L6: 0 | M6: =IF(K6="","",J6*K6*(1-IFERROR(L6,0))) -> 220000 | N6: =IF(M6="","",IF(F6="SI",M6*0.19,0)) -> 41800 | O6: =IF(K6="","",M6+N6) -> 261800 | P6: =IF(K6="","",SUMIF($B:$B,B6,$O:$O)) -> 261800 | Q6: =IF(H6="","",VLOOKUP(H6,'Base de datos'!E:M,9,FALSE)) -> 161840 | R6: =IF(Q6="","",SUMIF($B:$B,B6,$Q:$Q)) -> 161840
A7: =B7&"-"&C7 -> 4-1 | B7: 4 | C7: =IF(B7="","",COUNTIF($B$4:B7,B7)) -> 1 | D7: {=IF(B7="","",IFERROR( INDEX(R_COTIZACIONES!D:D,MATCH(B7,R_COTIZACIONES!A:A,0)), ""))} -> CONDOMINIO V.I.V.E LA FLORIDA ORIENTE | E7: {=IF(B7="","",IFERROR( INDEX(R_COTIZACIONES!C:C,MATCH(B7,R_COTIZACIONES!A:A,0)), ""))} -> 53322672-8 | F7: Si | G7: Particular | H7: S03 | I7: =IF(H7="","",VLOOKUP(H7,'Base de datos'!$E:$G,3,FALSE)) -> Instalación de ruedas (Unidad) | J7: 1 | K7: 200000 | L7: 0 | M7: =IF(K7="","",J7*K7*(1-IFERROR(L7,0))) -> 200000 | N7: =IF(M7="","",IF(F7="SI",M7*0.19,0)) -> 38000 | O7: =IF(K7="","",M7+N7) -> 238000 | P7: =IF(K7="","",SUMIF($B:$B,B7,$O:$O)) -> 357000 | Q7: =IF(H7="","",VLOOKUP(H7,'Base de datos'!E:M,9,FALSE)) -> 22500 | R7: =IF(Q7="","",SUMIF($B:$B,B7,$Q:$Q)) -> 45000
A8: =B8&"-"&C8 -> 4-2 | B8: 4 | C8: =IF(B8="","",COUNTIF($B$4:B8,B8)) -> 2 | D8: {=IF(B8="","",IFERROR( INDEX(R_COTIZACIONES!D:D,MATCH(B8,R_COTIZACIONES!A:A,0)), ""))} -> CONDOMINIO V.I.V.E LA FLORIDA ORIENTE | E8: {=IF(B8="","",IFERROR( INDEX(R_COTIZACIONES!C:C,MATCH(B8,R_COTIZACIONES!A:A,0)), ""))} -> 53322672-8 | F8: Si | G8: Particular | H8: S03 | I8: =IF(H8="","",VLOOKUP(H8,'Base de datos'!$E:$G,3,FALSE)) -> Instalación de ruedas (Unidad) | J8: 1 | K8: 100000 | L8: 0 | M8: =IF(K8="","",J8*K8*(1-IFERROR(L8,0))) -> 100000 | N8: =IF(M8="","",IF(F8="SI",M8*0.19,0)) -> 19000 | O8: =IF(K8="","",M8+N8) -> 119000 | P8: =IF(K8="","",SUMIF($B:$B,B8,$O:$O)) -> 357000 | Q8: =IF(H8="","",VLOOKUP(H8,'Base de datos'!E:M,9,FALSE)) -> 22500 | R8: =IF(Q8="","",SUMIF($B:$B,B8,$Q:$Q)) -> 45000
A9: =B9&"-"&C9 -> 5-1 | B9: 5 | C9: =IF(B9="","",COUNTIF($B$4:B9,B9)) -> 1 | D9: {=IF(B9="","",IFERROR( INDEX(R_COTIZACIONES!D:D,MATCH(B9,R_COTIZACIONES!A:A,0)), ""))} -> Condominio Lomas de San Joaquin | E9: {=IF(B9="","",IFERROR( INDEX(R_COTIZACIONES!C:C,MATCH(B9,R_COTIZACIONES!A:A,0)), ""))} -> 50.000.001-0 | F9: Si | G9: APACOM | H9: D10TKIT | I9: =IF(H9="","",VLOOKUP(H9,'Base de datos'!$E:$G,3,FALSE)) -> D10 Turbo (6 crem y 2 controles) | J9: 1 | K9: 1400000 | L9: 0 | M9: =IF(K9="","",J9*K9*(1-IFERROR(L9,0))) -> 1400000 | N9: =IF(M9="","",IF(F9="SI",M9*0.19,0)) -> 266000 | O9: =IF(K9="","",M9+N9) -> 1666000 | P9: =IF(K9="","",SUMIF($B:$B,B9,$O:$O)) -> 1666000 | Q9: =IF(H9="","",VLOOKUP(H9,'Base de datos'!E:M,9,FALSE)) -> 450483.6 | R9: =IF(Q9="","",SUMIF($B:$B,B9,$Q:$Q)) -> 450483.6
A10: =B10&"-"&C10 -> 6-1 | B10: 6 | C10: =IF(B10="","",COUNTIF($B$4:B10,B10)) -> 1 | D10: {=IF(B10="","",IFERROR( INDEX(R_COTIZACIONES!D:D,MATCH(B10,R_COTIZACIONES!A:A,0)), ""))} -> Comunidad Edificio Florencia | E10: {=IF(B10="","",IFERROR( INDEX(R_COTIZACIONES!C:C,MATCH(B10,R_COTIZACIONES!A:A,0)), ""))} -> 56047780-5 | F10: Si | G10: Particular | H10: S07 | I10: =IF(H10="","",VLOOKUP(H10,'Base de datos'!$E:$G,3,FALSE)) -> Mantención programada | J10: 1 | K10: 230000 | L10: 0 | M10: =IF(K10="","",J10*K10*(1-IFERROR(L10,0))) -> 230000 | N10: =IF(M10="","",IF(F10="SI",M10*0.19,0)) -> 43700 | O10: =IF(K10="","",M10+N10) -> 273700 | P10: =IF(K10="","",SUMIF($B:$B,B10,$O:$O)) -> 273700 | Q10: =IF(H10="","",VLOOKUP(H10,'Base de datos'!E:M,9,FALSE)) -> 100000 | R10: =IF(Q10="","",SUMIF($B:$B,B10,$Q:$Q)) -> 100000
A11: =B11&"-"&C11 -> 7-1 | B11: 7 | C11: =IF(B11="","",COUNTIF($B$4:B11,B11)) -> 1 | D11: {=IF(B11="","",IFERROR( INDEX(R_COTIZACIONES!D:D,MATCH(B11,R_COTIZACIONES!A:A,0)), ""))} -> Condominio Los Tamarindos I | E11: {=IF(B11="","",IFERROR( INDEX(R_COTIZACIONES!C:C,MATCH(B11,R_COTIZACIONES!A:A,0)), ""))} -> 53.322.860-7 | F11: no | G11: RW | H11: D10SKIT | I11: =IF(H11="","",VLOOKUP(H11,'Base de datos'!$E:$G,3,FALSE)) -> D10 Standard Kit 1(6 crem y 2 controles) | J11: 1 | K11: 1500000 | L11: 0 | M11: =IF(K11="","",J11*K11*(1-IFERROR(L11,0))) -> 1500000 | N11: =IF(M11="","",IF(F11="SI",M11*0.19,0)) -> 0 | O11: =IF(K11="","",M11+N11) -> 1500000 | P11: =IF(K11="","",SUMIF($B:$B,B11,$O:$O)) -> 1500000 | Q11: =IF(H11="","",VLOOKUP(H11,'Base de datos'!E:M,9,FALSE)) -> 420000 | R11: =IF(Q11="","",SUMIF($B:$B,B11,$Q:$Q)) -> 420000
A12: =B12&"-"&C12 -> 8-1 | B12: 8 | C12: =IF(B12="","",COUNTIF($B$4:B12,B12)) -> 1 | D12: {=IF(B12="","",IFERROR( INDEX(R_COTIZACIONES!D:D,MATCH(B12,R_COTIZACIONES!A:A,0)), ""))} -> Condominio Los Tamarindos I | E12: {=IF(B12="","",IFERROR( INDEX(R_COTIZACIONES!C:C,MATCH(B12,R_COTIZACIONES!A:A,0)), ""))} -> 53.322.860-7 | F12: no | G12: RW | H12: WP17 | I12: =IF(H12="","",VLOOKUP(H12,'Base de datos'!$E:$G,3,FALSE)) -> Controlador Wifi WP17 | J12: 1 | K12: 220000 | L12: 0 | M12: =IF(K12="","",J12*K12*(1-IFERROR(L12,0))) -> 220000 | N12: =IF(M12="","",IF(F12="SI",M12*0.19,0)) -> 0 | O12: =IF(K12="","",M12+N12) -> 220000 | P12: =IF(K12="","",SUMIF($B:$B,B12,$O:$O)) -> 220000 | Q12: =IF(H12="","",VLOOKUP(H12,'Base de datos'!E:M,9,FALSE)) -> 161840 | R12: =IF(Q12="","",SUMIF($B:$B,B12,$Q:$Q)) -> 161840
A13: =B13&"-"&C13 -> 9-1 | B13: 9 | C13: =IF(B13="","",COUNTIF($B$4:B13,B13)) -> 1 | D13: {=IF(B13="","",IFERROR( INDEX(R_COTIZACIONES!D:D,MATCH(B13,R_COTIZACIONES!A:A,0)), ""))} -> Condominio Jardin Central | E13: {=IF(B13="","",IFERROR( INDEX(R_COTIZACIONES!C:C,MATCH(B13,R_COTIZACIONES!A:A,0)), ""))} -> 53.332.075-9 | F13: no | G13: Particular | H13: S07 | I13: =IF(H13="","",VLOOKUP(H13,'Base de datos'!$E:$G,3,FALSE)) -> Mantención programada | J13: 1 | K13: 170000 | L13: 0 | M13: =IF(K13="","",J13*K13*(1-IFERROR(L13,0))) -> 170000 | N13: =IF(M13="","",IF(F13="SI",M13*0.19,0)) -> 0 | O13: =IF(K13="","",M13+N13) -> 170000 | P13: =IF(K13="","",SUMIF($B:$B,B13,$O:$O)) -> 170000 | Q13: =IF(H13="","",VLOOKUP(H13,'Base de datos'!E:M,9,FALSE)) -> 100000 | R13: =IF(Q13="","",SUMIF($B:$B,B13,$Q:$Q)) -> 100000
A14: =B14&"-"&C14 -> 10-1 | B14: 10 | C14: =IF(B14="","",COUNTIF($B$4:B14,B14)) -> 1 | D14: {=IF(B14="","",IFERROR( INDEX(R_COTIZACIONES!D:D,MATCH(B14,R_COTIZACIONES!A:A,0)), ""))} -> Edificio Puerta Centro | E14: {=IF(B14="","",IFERROR( INDEX(R_COTIZACIONES!C:C,MATCH(B14,R_COTIZACIONES!A:A,0)), ""))} -> 50.000.000-0 | F14: no | G14: Particular | H14: S07 | I14: =IF(H14="","",VLOOKUP(H14,'Base de datos'!$E:$G,3,FALSE)) -> Mantención programada | J14: 1 | K14: 170000 | L14: 0 | M14: =IF(K14="","",J14*K14*(1-IFERROR(L14,0))) -> 170000 | N14: =IF(M14="","",IF(F14="SI",M14*0.19,0)) -> 0 | O14: =IF(K14="","",M14+N14) -> 170000 | P14: =IF(K14="","",SUMIF($B:$B,B14,$O:$O)) -> 170000 | Q14: =IF(H14="","",VLOOKUP(H14,'Base de datos'!E:M,9,FALSE)) -> 100000 | R14: =IF(Q14="","",SUMIF($B:$B,B14,$Q:$Q)) -> 100000
A15: =B15&"-"&C15 -> 11-1 | B15: 11 | C15: =IF(B15="","",COUNTIF($B$4:B15,B15)) -> 1 | D15: {=IF(B15="","",IFERROR( INDEX(R_COTIZACIONES!D:D,MATCH(B15,R_COTIZACIONES!A:A,0)), ""))} -> Condominio Neo Spazio | E15: {=IF(B15="","",IFERROR( INDEX(R_COTIZACIONES!C:C,MATCH(B15,R_COTIZACIONES!A:A,0)), ""))} -> 65.095.336-2 | F15: Si | G15: Otro | H15: S07 | I15: =IF(H15="","",VLOOKUP(H15,'Base de datos'!$E:$G,3,FALSE)) -> Mantención programada | J15: 1 | K15: 1250000 | L15: 0 | M15: =IF(K15="","",J15*K15*(1-IFERROR(L15,0))) -> 1250000 | N15: =IF(M15="","",IF(F15="SI",M15*0.19,0)) -> 237500 | O15: =IF(K15="","",M15+N15) -> 1487500 | P15: =IF(K15="","",SUMIF($B:$B,B15,$O:$O)) -> 1487500 | Q15: =IF(H15="","",VLOOKUP(H15,'Base de datos'!E:M,9,FALSE)) -> 100000 | R15: =IF(Q15="","",SUMIF($B:$B,B15,$Q:$Q)) -> 100000
A16: =B16&"-"&C16 -> 12-1 | B16: 12 | C16: =IF(B16="","",COUNTIF($B$4:B16,B16)) -> 1 | D16: {=IF(B16="","",IFERROR( INDEX(R_COTIZACIONES!D:D,MATCH(B16,R_COTIZACIONES!A:A,0)), ""))} -> Condominio Mirador El Milagro | E16: {=IF(B16="","",IFERROR( INDEX(R_COTIZACIONES!C:C,MATCH(B16,R_COTIZACIONES!A:A,0)), ""))} -> 65216508-7 | F16: Si | G16: RW | H16: D10SKIT | I16: =IF(H16="","",VLOOKUP(H16,'Base de datos'!$E:$G,3,FALSE)) -> D10 Standard Kit 1(6 crem y 2 controles) | J16: 1 | K16: 1435990 | L16: 0 | M16: =IF(K16="","",J16*K16*(1-IFERROR(L16,0))) -> 1435990 | N16: =IF(M16="","",IF(F16="SI",M16*0.19,0)) -> 272838.1 | O16: =IF(K16="","",M16+N16) -> 1708828.1 | P16: =IF(K16="","",SUMIF($B:$B,B16,$O:$O)) -> 1708828.1 | Q16: =IF(H16="","",VLOOKUP(H16,'Base de datos'!E:M,9,FALSE)) -> 420000 | R16: =IF(Q16="","",SUMIF($B:$B,B16,$Q:$Q)) -> 420000
A17: =B17&"-"&C17 -> 13-1 | B17: 13 | C17: =IF(B17="","",COUNTIF($B$4:B17,B17)) -> 1 | D17: {=IF(B17="","",IFERROR( INDEX(R_COTIZACIONES!D:D,MATCH(B17,R_COTIZACIONES!A:A,0)), ""))} -> Condominio Colinas del Milagro | E17: {=IF(B17="","",IFERROR( INDEX(R_COTIZACIONES!C:C,MATCH(B17,R_COTIZACIONES!A:A,0)), ""))} -> 53333086-k | F17: Si | G17: RW | H17: D10SKIT | I17: =IF(H17="","",VLOOKUP(H17,'Base de datos'!$E:$G,3,FALSE)) -> D10 Standard Kit 1(6 crem y 2 controles) | J17: 1 | K17: 1340000 | L17: 0 | M17: =IF(K17="","",J17*K17*(1-IFERROR(L17,0))) -> 1340000 | N17: =IF(M17="","",IF(F17="SI",M17*0.19,0)) -> 254600 | O17: =IF(K17="","",M17+N17) -> 1594600 | P17: =IF(K17="","",SUMIF($B:$B,B17,$O:$O)) -> 1594600 | Q17: =IF(H17="","",VLOOKUP(H17,'Base de datos'!E:M,9,FALSE)) -> 420000 | R17: =IF(Q17="","",SUMIF($B:$B,B17,$Q:$Q)) -> 420000
... A37: =B37&"-"&C37 -> 30-1 | B37: 30 | C37: =IF(B37="","",COUNTIF($B$4:B37,B37)) -> 1 | D37: {=IF(B37="","",IFERROR( INDEX(R_COTIZACIONES!D:D,MATCH(B37,R_COTIZACIONES!A:A,0)), ""))} -> Condominio Paseo Peñuelas | E37: {=IF(B37="","",IFERROR( INDEX(R_COTIZACIONES!C:C,MATCH(B37,R_COTIZACIONES!A:A,0)), ""))} -> 53320939-4 | F37: no | G37: Particular | H37: S07 | I37: =IF(H37="","",VLOOKUP(H37,'Base de datos'!$E:$G,3,FALSE)) -> Mantención programada | J37: 1 | K37: 200000 | L37: 0 | M37: =IF(K37="","",J37*K37*(1-IFERROR(L37,0))) -> 200000 | N37: =IF(M37="","",IF(F37="SI",M37*0.19,0)) -> 0 | O37: =IF(K37="","",M37+N37) -> 200000 | P37: =IF(K37="","",SUMIF($B:$B,B37,$O:$O)) -> 200000 | Q37: =IF(H37="","",VLOOKUP(H37,'Base de datos'!E:M,9,FALSE)) -> 100000 | R37: =IF(Q37="","",SUMIF($B:$B,B37,$Q:$Q)) -> 100000
A38: =B38&"-"&C38 -> 31-1 | B38: 31 | C38: =IF(B38="","",COUNTIF($B$4:B38,B38)) -> 1 | D38: {=IF(B38="","",IFERROR( INDEX(R_COTIZACIONES!D:D,MATCH(B38,R_COTIZACIONES!A:A,0)), ""))} -> Condominio Mirador El Milagro | E38: {=IF(B38="","",IFERROR( INDEX(R_COTIZACIONES!C:C,MATCH(B38,R_COTIZACIONES!A:A,0)), ""))} -> 65216508-7 | F38: Si | G38: Particular | H38: S07 | I38: =IF(H38="","",VLOOKUP(H38,'Base de datos'!$E:$G,3,FALSE)) -> Mantención programada | J38: 1 | K38: =IF(H38="","",VLOOKUP(H38,'Base de datos'!E:N,10,FALSE)) -> 200000 | L38: 0 | M38: =IF(K38="","",J38*K38*(1-IFERROR(L38,0))) -> 200000 | N38: =IF(M38="","",IF(F38="SI",M38*0.19,0)) -> 38000 | O38: =IF(K38="","",M38+N38) -> 238000 | P38: =IF(K38="","",SUMIF($B:$B,B38,$O:$O)) -> 238000 | Q38: =IF(H38="","",VLOOKUP(H38,'Base de datos'!E:M,9,FALSE)) -> 100000 | R38: =IF(Q38="","",SUMIF($B:$B,B38,$Q:$Q)) -> 100000
A39: =B39&"-"&C39 -> 32-1 | B39: 32 | C39: =IF(B39="","",COUNTIF($B$4:B39,B39)) -> 1 | D39: {=IF(B39="","",IFERROR( INDEX(R_COTIZACIONES!D:D,MATCH(B39,R_COTIZACIONES!A:A,0)), ""))} -> Condominio Mirador El Milagro | E39: {=IF(B39="","",IFERROR( INDEX(R_COTIZACIONES!C:C,MATCH(B39,R_COTIZACIONES!A:A,0)), ""))} -> 65216508-7 | F39: no | G39: RW | H39: NOVA2 | I39: =IF(H39="","",VLOOKUP(H39,'Base de datos'!$E:$G,3,FALSE)) -> Control NOVA 2CH | J39: 9 | K39: 17000 | L39: 0 | M39: =IF(K39="","",J39*K39*(1-IFERROR(L39,0))) -> 153000 | N39: =IF(M39="","",IF(F39="SI",M39*0.19,0)) -> 0 | O39: =IF(K39="","",M39+N39) -> 153000 | P39: =IF(K39="","",SUMIF($B:$B,B39,$O:$O)) -> 153000 | Q39: =IF(H39="","",VLOOKUP(H39,'Base de datos'!E:M,9,FALSE)) -> 8021.7 | R39: =IF(Q39="","",SUMIF($B:$B,B39,$Q:$Q)) -> 8021.7
A40: =B40&"-"&C40 -> 33-1 | B40: 33 | C40: =IF(B40="","",COUNTIF($B$4:B40,B40)) -> 1 | D40: {=IF(B40="","",IFERROR( INDEX(R_COTIZACIONES!D:D,MATCH(B40,R_COTIZACIONES!A:A,0)), ""))} -> Condominio Colinas del Milagro | E40: {=IF(B40="","",IFERROR( INDEX(R_COTIZACIONES!C:C,MATCH(B40,R_COTIZACIONES!A:A,0)), ""))} -> 53333086-k | F40: Si | G40: Particular | H40: S07 | I40: =IF(H40="","",VLOOKUP(H40,'Base de datos'!$E:$G,3,FALSE)) -> Mantención programada | J40: 1 | K40: =IF(H40="","",VLOOKUP(H40,'Base de datos'!E:N,10,FALSE)) -> 200000 | L40: 0 | M40: =IF(K40="","",J40*K40*(1-IFERROR(L40,0))) -> 200000 | N40: =IF(M40="","",IF(F40="SI",M40*0.19,0)) -> 38000 | O40: =IF(K40="","",M40+N40) -> 238000 | P40: =IF(K40="","",SUMIF($B:$B,B40,$O:$O)) -> 238000 | Q40: =IF(H40="","",VLOOKUP(H40,'Base de datos'!E:M,9,FALSE)) -> 100000 | R40: =IF(Q40="","",SUMIF($B:$B,B40,$Q:$Q)) -> 100000
A41: =B41&"-"&C41 -> 34-1 | B41: 34 | C41: =IF(B41="","",COUNTIF($B$4:B41,B41)) -> 1 | D41: {=IF(B41="","",IFERROR( INDEX(R_COTIZACIONES!D:D,MATCH(B41,R_COTIZACIONES!A:A,0)), ""))} -> Condominio Vicenza II | E41: {=IF(B41="","",IFERROR( INDEX(R_COTIZACIONES!C:C,MATCH(B41,R_COTIZACIONES!A:A,0)), ""))} -> 65198585-4 | F41: Si | G41: Particular | H41: S07 | I41: =IF(H41="","",VLOOKUP(H41,'Base de datos'!$E:$G,3,FALSE)) -> Mantención programada | J41: 1 | K41: =IF(H41="","",VLOOKUP(H41,'Base de datos'!E:N,10,FALSE)) -> 200000 | L41: 0 | M41: =IF(K41="","",J41*K41*(1-IFERROR(L41,0))) -> 200000 | N41: =IF(M41="","",IF(F41="SI",M41*0.19,0)) -> 38000 | O41: =IF(K41="","",M41+N41) -> 238000 | P41: =IF(K41="","",SUMIF($B:$B,B41,$O:$O)) -> 238000 | Q41: =IF(H41="","",VLOOKUP(H41,'Base de datos'!E:M,9,FALSE)) -> 100000 | R41: =IF(Q41="","",SUMIF($B:$B,B41,$Q:$Q)) -> 100000
A42: =B42&"-"&C42 -> 35-1 | B42: 35 | C42: =IF(B42="","",COUNTIF($B$4:B42,B42)) -> 1 | D42: {=IF(B42="","",IFERROR( INDEX(R_COTIZACIONES!D:D,MATCH(B42,R_COTIZACIONES!A:A,0)), ""))} -> Condominio Vicenza II | E42: {=IF(B42="","",IFERROR( INDEX(R_COTIZACIONES!C:C,MATCH(B42,R_COTIZACIONES!A:A,0)), ""))} -> 65198585-4 | F42: Si | G42: Smartsecure | H42: ASI1201E-D | I42: =IF(H42="","",VLOOKUP(H42,'Base de datos'!$E:$G,3,FALSE)) -> Control Acceso ASI1201E-D | J42: 1 | K42: 100000 | L42: 0 | M42: =IF(K42="","",J42*K42*(1-IFERROR(L42,0))) -> 100000 | N42: =IF(M42="","",IF(F42="SI",M42*0.19,0)) -> 19000 | O42: =IF(K42="","",M42+N42) -> 119000 | P42: =IF(K42="","",SUMIF($B:$B,B42,$O:$O)) -> 238000 | Q42: =IF(H42="","",VLOOKUP(H42,'Base de datos'!E:M,9,FALSE)) -> 73047 | R42: =IF(Q42="","",SUMIF($B:$B,B42,$Q:$Q)) -> 83047
A43: =B43&"-"&C43 -> 35-2 | B43: 35 | C43: =IF(B43="","",COUNTIF($B$4:B43,B43)) -> 2 | D43: {=IF(B43="","",IFERROR( INDEX(R_COTIZACIONES!D:D,MATCH(B43,R_COTIZACIONES!A:A,0)), ""))} -> Condominio Vicenza II | E43: {=IF(B43="","",IFERROR( INDEX(R_COTIZACIONES!C:C,MATCH(B43,R_COTIZACIONES!A:A,0)), ""))} -> 65198585-4 | F43: Si | G43: Particular | H43: S10 | I43: =IF(H43="","",VLOOKUP(H43,'Base de datos'!$E:$G,3,FALSE)) -> Servicio de instalación digitador de acceso | J43: 1 | K43: 100000 | L43: 0 | M43: =IF(K43="","",J43*K43*(1-IFERROR(L43,0))) -> 100000 | N43: =IF(M43="","",IF(F43="SI",M43*0.19,0)) -> 19000 | O43: =IF(K43="","",M43+N43) -> 119000 | P43: =IF(K43="","",SUMIF($B:$B,B43,$O:$O)) -> 238000 | Q43: =IF(H43="","",VLOOKUP(H43,'Base de datos'!E:M,9,FALSE)) -> 10000 | R43: =IF(Q43="","",SUMIF($B:$B,B43,$Q:$Q)) -> 83047
A44: =B44&"-"&C44 -> 36-1 | B44: 36 | C44: =IF(B44="","",COUNTIF($B$4:B44,B44)) -> 1 | D44: {=IF(B44="","",IFERROR( INDEX(R_COTIZACIONES!D:D,MATCH(B44,R_COTIZACIONES!A:A,0)), ""))} -> Portal del Valle II | E44: {=IF(B44="","",IFERROR( INDEX(R_COTIZACIONES!C:C,MATCH(B44,R_COTIZACIONES!A:A,0)), ""))} -> 53332414-2 | F44: Si | G44: Particular | H44: S11 | I44: =IF(H44="","",VLOOKUP(H44,'Base de datos'!$E:$G,3,FALSE)) -> Fabricación de perfil 100x100 c/ pintura y polines | J44: 1 | K44: 290000 | L44: 0 | M44: =IF(K44="","",J44*K44*(1-IFERROR(L44,0))) -> 290000 | N44: =IF(M44="","",IF(F44="SI",M44*0.19,0)) -> 55100 | O44: =IF(K44="","",M44+N44) -> 345100 | P44: =IF(K44="","",SUMIF($B:$B,B44,$O:$O)) -> 345100 | Q44: =IF(H44="","",VLOOKUP(H44,'Base de datos'!E:M,9,FALSE)) -> 151260.5 | R44: =IF(Q44="","",SUMIF($B:$B,B44,$Q:$Q)) -> 151260.5
A45: =B45&"-"&C45 -> 37-1 | B45: 37 | C45: =IF(B45="","",COUNTIF($B$4:B45,B45)) -> 1 | D45: {=IF(B45="","",IFERROR( INDEX(R_COTIZACIONES!D:D,MATCH(B45,R_COTIZACIONES!A:A,0)), ""))} -> Condominio Gabriela Mistral | E45: {=IF(B45="","",IFERROR( INDEX(R_COTIZACIONES!C:C,MATCH(B45,R_COTIZACIONES!A:A,0)), ""))} -> 90000000-1 | F45: no | G45: Otro | H45: ASSABLOY | I45: =IF(H45="","",VLOOKUP(H45,'Base de datos'!$E:$G,3,FALSE)) -> Cerradura Eléctrica Poli Estándar 3010 Color Gris | J45: 1 | K45: 250000 | L45: 0 | M45: =IF(K45="","",J45*K45*(1-IFERROR(L45,0))) -> 250000 | N45: =IF(M45="","",IF(F45="SI",M45*0.19,0)) -> 0 | O45: =IF(K45="","",M45+N45) -> 250000 | P45: =IF(K45="","",SUMIF($B:$B,B45,$O:$O)) -> 250000 | Q45: =IF(H45="","",VLOOKUP(H45,'Base de datos'!E:M,9,FALSE)) -> 45144 | R45: =IF(Q45="","",SUMIF($B:$B,B45,$Q:$Q)) -> 45144
A46: =B46&"-"&C46 -> 38-1 | B46: 38 | C46: =IF(B46="","",COUNTIF($B$4:B46,B46)) -> 1 | D46: {=IF(B46="","",IFERROR( INDEX(R_COTIZACIONES!D:D,MATCH(B46,R_COTIZACIONES!A:A,0)), ""))} -> Cond Aires de La Florida 4 | E46: {=IF(B46="","",IFERROR( INDEX(R_COTIZACIONES!C:C,MATCH(B46,R_COTIZACIONES!A:A,0)), ""))} -> 53332351-0 | F46: Si | G46: RW | H46: D10TKIT | I46: =IF(H46="","",VLOOKUP(H46,'Base de datos'!$E:$G,3,FALSE)) -> D10 Turbo (6 crem y 2 controles) | J46: 1 | K46: 1290000 | L46: 0 | M46: =IF(K46="","",J46*K46*(1-IFERROR(L46,0))) -> 1290000 | N46: =IF(M46="","",IF(F46="SI",M46*0.19,0)) -> 245100 | O46: =IF(K46="","",M46+N46) -> 1535100 | P46: =IF(K46="","",SUMIF($B:$B,B46,$O:$O)) -> 2225300 | Q46: =IF(H46="","",VLOOKUP(H46,'Base de datos'!E:M,9,FALSE)) -> 450483.6 | R46: =IF(Q46="","",SUMIF($B:$B,B46,$Q:$Q)) -> 710203.8
A47: =B47&"-"&C47 -> 38-2 | B47: 38 | C47: =IF(B47="","",COUNTIF($B$4:B47,B47)) -> 2 | D47: {=IF(B47="","",IFERROR( INDEX(R_COTIZACIONES!D:D,MATCH(B47,R_COTIZACIONES!A:A,0)), ""))} -> Cond Aires de La Florida 4 | E47: {=IF(B47="","",IFERROR( INDEX(R_COTIZACIONES!C:C,MATCH(B47,R_COTIZACIONES!A:A,0)), ""))} -> 53332351-0 | F47: Si | G47: RW | H47: PHSMRT | I47: =IF(H47="","",VLOOKUP(H47,'Base de datos'!$E:$G,3,FALSE)) -> Photon Smart (par) | J47: 1 | K47: 100000 | L47: 0 | M47: =IF(K47="","",J47*K47*(1-IFERROR(L47,0))) -> 100000 | N47: =IF(M47="","",IF(F47="SI",M47*0.19,0)) -> 19000 | O47: =IF(K47="","",M47+N47) -> 119000 | P47: =IF(K47="","",SUMIF($B:$B,B47,$O:$O)) -> 2225300 | Q47: =IF(H47="","",VLOOKUP(H47,'Base de datos'!E:M,9,FALSE)) -> 35692.8 | R47: =IF(Q47="","",SUMIF($B:$B,B47,$Q:$Q)) -> 710203.8
A48: =B48&"-"&C48 -> 38-3 | B48: 38 | C48: =IF(B48="","",COUNTIF($B$4:B48,B48)) -> 3 | D48: {=IF(B48="","",IFERROR( INDEX(R_COTIZACIONES!D:D,MATCH(B48,R_COTIZACIONES!A:A,0)), ""))} -> Cond Aires de La Florida 4 | E48: {=IF(B48="","",IFERROR( INDEX(R_COTIZACIONES!C:C,MATCH(B48,R_COTIZACIONES!A:A,0)), ""))} -> 53332351-0 | F48: Si | G48: PRODALAM | H48: KITG4060 | I48: =IF(H48="","",VLOOKUP(H48,'Base de datos'!$E:$G,3,FALSE)) -> Set de Guias 40x60 | J48: 1 | K48: 30000 | L48: 0 | M48: =IF(K48="","",J48*K48*(1-IFERROR(L48,0))) -> 30000 | N48: =IF(M48="","",IF(F48="SI",M48*0.19,0)) -> 5700 | O48: =IF(K48="","",M48+N48) -> 35700 | P48: =IF(K48="","",SUMIF($B:$B,B48,$O:$O)) -> 2225300 | Q48: =IF(H48="","",VLOOKUP(H48,'Base de datos'!E:M,9,FALSE)) -> 10019.4 | R48: =IF(Q48="","",SUMIF($B:$B,B48,$Q:$Q)) -> 710203.8
A49: =B49&"-"&C49 -> 38-4 | B49: 38 | C49: =IF(B49="","",COUNTIF($B$4:B49,B49)) -> 4 | D49: {=IF(B49="","",IFERROR( INDEX(R_COTIZACIONES!D:D,MATCH(B49,R_COTIZACIONES!A:A,0)), ""))} -> Cond Aires de La Florida 4 | E49: {=IF(B49="","",IFERROR( INDEX(R_COTIZACIONES!C:C,MATCH(B49,R_COTIZACIONES!A:A,0)), ""))} -> 53332351-0 | F49: Si | G49: RW | H49: BALNC1225 | I49: =IF(H49="","",VLOOKUP(H49,'Base de datos'!$E:$G,3,FALSE)) -> Baliza NICE 12-38V | J49: 1 | K49: 60000 | L49: 0 | M49: =IF(K49="","",J49*K49*(1-IFERROR(L49,0))) -> 60000 | N49: =IF(M49="","",IF(F49="SI",M49*0.19,0)) -> 11400 | O49: =IF(K49="","",M49+N49) -> 71400 | P49: =IF(K49="","",SUMIF($B:$B,B49,$O:$O)) -> 2225300 | Q49: =IF(H49="","",VLOOKUP(H49,'Base de datos'!E:M,9,FALSE)) -> 34008 | R49: =IF(Q49="","",SUMIF($B:$B,B49,$Q:$Q)) -> 710203.8
A50: =B50&"-"&C50 -> 38-5 | B50: 38 | C50: =IF(B50="","",COUNTIF($B$4:B50,B50)) -> 5 | D50: {=IF(B50="","",IFERROR( INDEX(R_COTIZACIONES!D:D,MATCH(B50,R_COTIZACIONES!A:A,0)), ""))} -> Cond Aires de La Florida 4 | E50: {=IF(B50="","",IFERROR( INDEX(R_COTIZACIONES!C:C,MATCH(B50,R_COTIZACIONES!A:A,0)), ""))} -> 53332351-0 | F50: Si | G50: Particular | H50: S02 | I50: =IF(H50="","",VLOOKUP(H50,'Base de datos'!$E:$G,3,FALSE)) -> Instalación de motor (Kit) | J50: 1 | K50: 390000 | L50: 0 | M50: =IF(K50="","",J50*K50*(1-IFERROR(L50,0))) -> 390000 | N50: =IF(M50="","",IF(F50="SI",M50*0.19,0)) -> 74100 | O50: =IF(K50="","",M50+N50) -> 464100 | P50: =IF(K50="","",SUMIF($B:$B,B50,$O:$O)) -> 2225300 | Q50: =IF(H50="","",VLOOKUP(H50,'Base de datos'!E:M,9,FALSE)) -> 180000 | R50: =IF(Q50="","",SUMIF($B:$B,B50,$Q:$Q)) -> 710203.8
A51: =B51&"-"&C51 -> 39-1 | B51: 39 | C51: =IF(B51="","",COUNTIF($B$4:B51,B51)) -> 1 | D51: {=IF(B51="","",IFERROR( INDEX(R_COTIZACIONES!D:D,MATCH(B51,R_COTIZACIONES!A:A,0)), ""))} -> Comunidad Edificio Florencia | E51: {=IF(B51="","",IFERROR( INDEX(R_COTIZACIONES!C:C,MATCH(B51,R_COTIZACIONES!A:A,0)), ""))} -> 56047780-5 | F51: no | G51: Particular | H51: S01CIP | I51: =IF(H51="","",VLOOKUP(H51,'Base de datos'!$E:$G,3,FALSE)) -> Servicio de recuperación IP de cámara asociada a NVR | J51: 8 | K51: 48750 | L51: 0 | M51: =IF(K51="","",J51*K51*(1-IFERROR(L51,0))) -> 390000 | N51: =IF(M51="","",IF(F51="SI",M51*0.19,0)) -> 0 | O51: =IF(K51="","",M51+N51) -> 390000 | P51: =IF(K51="","",SUMIF($B:$B,B51,$O:$O)) -> 430000 | Q51: =IF(H51="","",VLOOKUP(H51,'Base de datos'!E:M,9,FALSE)) -> 0 | R51: =IF(Q51="","",SUMIF($B:$B,B51,$Q:$Q)) -> 0
A52: =B52&"-"&C52 -> 39-2 | B52: 39 | C52: =IF(B52="","",COUNTIF($B$4:B52,B52)) -> 2 | D52: {=IF(B52="","",IFERROR( INDEX(R_COTIZACIONES!D:D,MATCH(B52,R_COTIZACIONES!A:A,0)), ""))} -> Comunidad Edificio Florencia | E52: {=IF(B52="","",IFERROR( INDEX(R_COTIZACIONES!C:C,MATCH(B52,R_COTIZACIONES!A:A,0)), ""))} -> 56047780-5 | F52: no | G52: Particular | H52: S02GATOR | I52: =IF(H52="","",VLOOKUP(H52,'Base de datos'!$E:$G,3,FALSE)) -> Servicio de recuperación de dispositivo Protegus 2 | J52: 1 | K52: 40000 | L52: 0 | M52: =IF(K52="","",J52*K52*(1-IFERROR(L52,0))) -> 40000 | N52: =IF(M52="","",IF(F52="SI",M52*0.19,0)) -> 0 | O52: =IF(K52="","",M52+N52) -> 40000 | P52: =IF(K52="","",SUMIF($B:$B,B52,$O:$O)) -> 430000 | Q52: =IF(H52="","",VLOOKUP(H52,'Base de datos'!E:M,9,FALSE)) -> 0 | R52: =IF(Q52="","",SUMIF($B:$B,B52,$Q:$Q)) -> 0
A53: =B53&"-"&C53 -> 40-1 | B53: 40 | C53: =IF(B53="","",COUNTIF($B$4:B53,B53)) -> 1 | D53: {=IF(B53="","",IFERROR( INDEX(R_COTIZACIONES!D:D,MATCH(B53,R_COTIZACIONES!A:A,0)), ""))} -> Condominio Golf III | E53: {=IF(B53="","",IFERROR( INDEX(R_COTIZACIONES!C:C,MATCH(B53,R_COTIZACIONES!A:A,0)), ""))} -> 90000002-1 | F53: Si | G53: Particular | H53: PROYECTO | I53: =IF(H53="","",VLOOKUP(H53,'Base de datos'!$E:$G,3,FALSE)) -> Proyecto asociado a propuesta (revisar adjuntos) | J53: 1 | K53: 8215000 | L53: 0 | M53: =IF(K53="","",J53*K53*(1-IFERROR(L53,0))) -> 8215000 | N53: =IF(M53="","",IF(F53="SI",M53*0.19,0)) -> 1560850 | O53: =IF(K53="","",M53+N53) -> 9775850 | P53: =IF(K53="","",SUMIF($B:$B,B53,$O:$O)) -> 9775850 | Q53: =IF(H53="","",VLOOKUP(H53,'Base de datos'!E:M,9,FALSE)) -> 0 | R53: =IF(Q53="","",SUMIF($B:$B,B53,$Q:$Q)) -> 0
... A61: =B61&"-"&C61 -> 46-1 | B61: 46 | C61: =IF(B61="","",COUNTIF($B$4:B61,B61)) -> 1 | D61: {=IF(B61="","",IFERROR( INDEX(R_COTIZACIONES!D:D,MATCH(B61,R_COTIZACIONES!A:A,0)), ""))} -> Condominio Alto Bellavista | E61: {=IF(B61="","",IFERROR( INDEX(R_COTIZACIONES!C:C,MATCH(B61,R_COTIZACIONES!A:A,0)), ""))} -> 65242132-6 | F61: Si | G61: Particular | H61: S09F | I61: =IF(H61="","",VLOOKUP(H61,'Base de datos'!$E:$G,3,FALSE)) -> Servicio de recuperación estructural | J61: 1 | K61: 750000 | L61: 0 | M61: =IF(K61="","",J61*K61*(1-IFERROR(L61,0))) -> 750000 | N61: =IF(M61="","",IF(F61="SI",M61*0.19,0)) -> 142500 | O61: =IF(K61="","",M61+N61) -> 892500 | P61: =IF(K61="","",SUMIF($B:$B,B61,$O:$O)) -> 892500 | Q61: =IF(H61="","",VLOOKUP(H61,'Base de datos'!E:M,9,FALSE)) -> 0 | R61: =IF(Q61="","",SUMIF($B:$B,B61,$Q:$Q)) -> 0
A62: =B62&"-"&C62 -> 47-1 | B62: 47 | C62: =IF(B62="","",COUNTIF($B$4:B62,B62)) -> 1 | D62: {=IF(B62="","",IFERROR( INDEX(R_COTIZACIONES!D:D,MATCH(B62,R_COTIZACIONES!A:A,0)), ""))} -> Condominio Paseo Peñuelas | E62: {=IF(B62="","",IFERROR( INDEX(R_COTIZACIONES!C:C,MATCH(B62,R_COTIZACIONES!A:A,0)), ""))} -> 53320939-4 | F62: Si | G62: Smartsecure | H62: PROYECTO | I62: Servicio de renovación CCTV fase I | J62: 1 | K62: 3304000 | L62: 0 | M62: =IF(K62="","",J62*K62*(1-IFERROR(L62,0))) -> 3304000 | N62: =IF(M62="","",IF(F62="SI",M62*0.19,0)) -> 627760 | O62: =IF(K62="","",M62+N62) -> 3931760 | P62: =IF(K62="","",SUMIF($B:$B,B62,$O:$O)) -> 3931760 | Q62: =IF(H62="","",VLOOKUP(H62,'Base de datos'!E:M,9,FALSE)) -> 0 | R62: =IF(Q62="","",SUMIF($B:$B,B62,$Q:$Q)) -> 0
A63: =B63&"-"&C63 -> 48-1 | B63: 48 | C63: =IF(B63="","",COUNTIF($B$4:B63,B63)) -> 1 | D63: {=IF(B63="","",IFERROR( INDEX(R_COTIZACIONES!D:D,MATCH(B63,R_COTIZACIONES!A:A,0)), ""))} -> Condominio Paseo Peñuelas | E63: {=IF(B63="","",IFERROR( INDEX(R_COTIZACIONES!C:C,MATCH(B63,R_COTIZACIONES!A:A,0)), ""))} -> 53320939-4 | F63: Si | G63: Smartsecure | H63: PROYECTO | I63: Servicio de renovación CCTV fase II | J63: 1 | K63: 4825000 | L63: 0 | M63: =IF(K63="","",J63*K63*(1-IFERROR(L63,0))) -> 4825000 | N63: =IF(M63="","",IF(F63="SI",M63*0.19,0)) -> 916750 | O63: =IF(K63="","",M63+N63) -> 5741750 | P63: =IF(K63="","",SUMIF($B:$B,B63,$O:$O)) -> 5741750 | Q63: =IF(H63="","",VLOOKUP(H63,'Base de datos'!E:M,9,FALSE)) -> 0 | R63: =IF(Q63="","",SUMIF($B:$B,B63,$Q:$Q)) -> 0
A64: =B64&"-"&C64 -> 49-1 | B64: 49 | C64: =IF(B64="","",COUNTIF($B$4:B64,B64)) -> 1 | D64: {=IF(B64="","",IFERROR( INDEX(R_COTIZACIONES!D:D,MATCH(B64,R_COTIZACIONES!A:A,0)), ""))} -> Condominio Paseo Peñuelas | E64: {=IF(B64="","",IFERROR( INDEX(R_COTIZACIONES!C:C,MATCH(B64,R_COTIZACIONES!A:A,0)), ""))} -> 53320939-4 | F64: Si | G64: Smartsecure | H64: PROYECTO | I64: Servicio de renovación CCTV fase III | J64: 1 | K64: 10871000 | L64: 0 | M64: =IF(K64="","",J64*K64*(1-IFERROR(L64,0))) -> 10871000 | N64: =IF(M64="","",IF(F64="SI",M64*0.19,0)) -> 2065490 | O64: =IF(K64="","",M64+N64) -> 12936490 | P64: =IF(K64="","",SUMIF($B:$B,B64,$O:$O)) -> 12936490 | Q64: =IF(H64="","",VLOOKUP(H64,'Base de datos'!E:M,9,FALSE)) -> 0 | R64: =IF(Q64="","",SUMIF($B:$B,B64,$Q:$Q)) -> 0
A65: =B65&"-"&C65 -> 50-1 | B65: 50 | C65: =IF(B65="","",COUNTIF($B$4:B65,B65)) -> 1 | D65: {=IF(B65="","",IFERROR( INDEX(R_COTIZACIONES!D:D,MATCH(B65,R_COTIZACIONES!A:A,0)), ""))} -> Comunidad Edificio Florencia | E65: {=IF(B65="","",IFERROR( INDEX(R_COTIZACIONES!C:C,MATCH(B65,R_COTIZACIONES!A:A,0)), ""))} -> 56047780-5 | F65: no | G65: RW | H65: NOVA2 | I65: =IF(H65="","",VLOOKUP(H65,'Base de datos'!$E:$G,3,FALSE)) -> Control NOVA 2CH | J65: 10 | K65: 170000 | L65: 0 | M65: =IF(K65="","",J65*K65*(1-IFERROR(L65,0))) -> 1700000 | N65: =IF(M65="","",IF(F65="SI",M65*0.19,0)) -> 0 | O65: =IF(K65="","",M65+N65) -> 1700000 | P65: =IF(K65="","",SUMIF($B:$B,B65,$O:$O)) -> 1700000 | Q65: =IF(H65="","",VLOOKUP(H65,'Base de datos'!E:M,9,FALSE)) -> 8021.7 | R65: =IF(Q65="","",SUMIF($B:$B,B65,$Q:$Q)) -> 8021.7
A66: =B66&"-"&C66 -> 51-1 | B66: 51 | C66: =IF(B66="","",COUNTIF($B$4:B66,B66)) -> 1 | D66: {=IF(B66="","",IFERROR( INDEX(R_COTIZACIONES!D:D,MATCH(B66,R_COTIZACIONES!A:A,0)), ""))} -> Condominio Capri | E66: {=IF(B66="","",IFERROR( INDEX(R_COTIZACIONES!C:C,MATCH(B66,R_COTIZACIONES!A:A,0)), ""))} -> 65106948-3 | F66: no | G66: APACOM | H66: D10SKIT | I66: =IF(H66="","",VLOOKUP(H66,'Base de datos'!$E:$G,3,FALSE)) -> D10 Standard Kit 1(6 crem y 2 controles) | J66: 1 | K66: 1050000 | L66: 0 | M66: =IF(K66="","",J66*K66*(1-IFERROR(L66,0))) -> 1050000 | N66: =IF(M66="","",IF(F66="SI",M66*0.19,0)) -> 0 | O66: =IF(K66="","",M66+N66) -> 1050000 | P66: =IF(K66="","",SUMIF($B:$B,B66,$O:$O)) -> 1550000 | Q66: =IF(H66="","",VLOOKUP(H66,'Base de datos'!E:M,9,FALSE)) -> 420000 | R66: =IF(Q66="","",SUMIF($B:$B,B66,$Q:$Q)) -> 664983
A67: =B67&"-"&C67 -> 51-2 | B67: 51 | C67: =IF(B67="","",COUNTIF($B$4:B67,B67)) -> 2 | D67: {=IF(B67="","",IFERROR( INDEX(R_COTIZACIONES!D:D,MATCH(B67,R_COTIZACIONES!A:A,0)), ""))} -> Condominio Capri | E67: {=IF(B67="","",IFERROR( INDEX(R_COTIZACIONES!C:C,MATCH(B67,R_COTIZACIONES!A:A,0)), ""))} -> 65106948-3 | F67: no | G67: APACOM | H67: PHSMRT | I67: =IF(H67="","",VLOOKUP(H67,'Base de datos'!$E:$G,3,FALSE)) -> Photon Smart (par) | J67: 1 | K67: 95000 | L67: 0 | M67: =IF(K67="","",J67*K67*(1-IFERROR(L67,0))) -> 95000 | N67: =IF(M67="","",IF(F67="SI",M67*0.19,0)) -> 0 | O67: =IF(K67="","",M67+N67) -> 95000 | P67: =IF(K67="","",SUMIF($B:$B,B67,$O:$O)) -> 1550000 | Q67: =IF(H67="","",VLOOKUP(H67,'Base de datos'!E:M,9,FALSE)) -> 35692.8 | R67: =IF(Q67="","",SUMIF($B:$B,B67,$Q:$Q)) -> 664983
A68: =B68&"-"&C68 -> 51-3 | B68: 51 | C68: =IF(B68="","",COUNTIF($B$4:B68,B68)) -> 3 | D68: {=IF(B68="","",IFERROR( INDEX(R_COTIZACIONES!D:D,MATCH(B68,R_COTIZACIONES!A:A,0)), ""))} -> Condominio Capri | E68: {=IF(B68="","",IFERROR( INDEX(R_COTIZACIONES!C:C,MATCH(B68,R_COTIZACIONES!A:A,0)), ""))} -> 65106948-3 | F68: no | G68: PRODALAM | H68: KITG4060 | I68: =IF(H68="","",VLOOKUP(H68,'Base de datos'!$E:$G,3,FALSE)) -> Set de Guias 40x60 | J68: 1 | K68: 25000 | L68: 0 | M68: =IF(K68="","",J68*K68*(1-IFERROR(L68,0))) -> 25000 | N68: =IF(M68="","",IF(F68="SI",M68*0.19,0)) -> 0 | O68: =IF(K68="","",M68+N68) -> 25000 | P68: =IF(K68="","",SUMIF($B:$B,B68,$O:$O)) -> 1550000 | Q68: =IF(H68="","",VLOOKUP(H68,'Base de datos'!E:M,9,FALSE)) -> 10019.4 | R68: =IF(Q68="","",SUMIF($B:$B,B68,$Q:$Q)) -> 664983
A69: =B69&"-"&C69 -> 51-4 | B69: 51 | C69: =IF(B69="","",COUNTIF($B$4:B69,B69)) -> 4 | D69: {=IF(B69="","",IFERROR( INDEX(R_COTIZACIONES!D:D,MATCH(B69,R_COTIZACIONES!A:A,0)), ""))} -> Condominio Capri | E69: {=IF(B69="","",IFERROR( INDEX(R_COTIZACIONES!C:C,MATCH(B69,R_COTIZACIONES!A:A,0)), ""))} -> 65106948-3 | F69: no | G69: APACOM | H69: BALNC1224 | I69: =IF(H69="","",VLOOKUP(H69,'Base de datos'!$E:$G,3,FALSE)) -> Baliza NICE 12-38V | J69: 1 | K69: 80000 | L69: 0 | M69: =IF(K69="","",J69*K69*(1-IFERROR(L69,0))) -> 80000 | N69: =IF(M69="","",IF(F69="SI",M69*0.19,0)) -> 0 | O69: =IF(K69="","",M69+N69) -> 80000 | P69: =IF(K69="","",SUMIF($B:$B,B69,$O:$O)) -> 1550000 | Q69: =IF(H69="","",VLOOKUP(H69,'Base de datos'!E:M,9,FALSE)) -> 19270.8 | R69: =IF(Q69="","",SUMIF($B:$B,B69,$Q:$Q)) -> 664983
A70: =B70&"-"&C70 -> 51-5 | B70: 51 | C70: =IF(B70="","",COUNTIF($B$4:B70,B70)) -> 5 | D70: {=IF(B70="","",IFERROR( INDEX(R_COTIZACIONES!D:D,MATCH(B70,R_COTIZACIONES!A:A,0)), ""))} -> Condominio Capri | E70: {=IF(B70="","",IFERROR( INDEX(R_COTIZACIONES!C:C,MATCH(B70,R_COTIZACIONES!A:A,0)), ""))} -> 65106948-3 | F70: no | G70: Particular | H70: S02 | I70: =IF(H70="","",VLOOKUP(H70,'Base de datos'!$E:$G,3,FALSE)) -> Instalación de motor (Kit) | J70: 1 | K70: 300000 | L70: 0 | M70: =IF(K70="","",J70*K70*(1-IFERROR(L70,0))) -> 300000 | N70: =IF(M70="","",IF(F70="SI",M70*0.19,0)) -> 0 | O70: =IF(K70="","",M70+N70) -> 300000 | P70: =IF(K70="","",SUMIF($B:$B,B70,$O:$O)) -> 1550000 | Q70: =IF(H70="","",VLOOKUP(H70,'Base de datos'!E:M,9,FALSE)) -> 180000 | R70: =IF(Q70="","",SUMIF($B:$B,B70,$Q:$Q)) -> 664983
A71: =B71&"-"&C71 -> 52-1 | B71: 52 | C71: =IF(B71="","",COUNTIF($B$4:B71,B71)) -> 1 | D71: {=IF(B71="","",IFERROR( INDEX(R_COTIZACIONES!D:D,MATCH(B71,R_COTIZACIONES!A:A,0)), ""))} -> Espacio Norte La Serena | E71: {=IF(B71="","",IFERROR( INDEX(R_COTIZACIONES!C:C,MATCH(B71,R_COTIZACIONES!A:A,0)), ""))} -> 76785900-7 | F71: no | G71: APACOM | H71: D10TKIT | I71: =IF(H71="","",VLOOKUP(H71,'Base de datos'!$E:$G,3,FALSE)) -> D10 Turbo (6 crem y 2 controles) | J71: 1 | K71: 1200000 | L71: 0 | M71: =IF(K71="","",J71*K71*(1-IFERROR(L71,0))) -> 1200000 | N71: =IF(M71="","",IF(F71="SI",M71*0.19,0)) -> 0 | O71: =IF(K71="","",M71+N71) -> 1200000 | P71: =IF(K71="","",SUMIF($B:$B,B71,$O:$O)) -> 1710000 | Q71: =IF(H71="","",VLOOKUP(H71,'Base de datos'!E:M,9,FALSE)) -> 450483.6 | R71: =IF(Q71="","",SUMIF($B:$B,B71,$Q:$Q)) -> 731195.8
A72: =B72&"-"&C72 -> 52-2 | B72: 52 | C72: =IF(B72="","",COUNTIF($B$4:B72,B72)) -> 2 | D72: {=IF(B72="","",IFERROR( INDEX(R_COTIZACIONES!D:D,MATCH(B72,R_COTIZACIONES!A:A,0)), ""))} -> Espacio Norte La Serena | E72: {=IF(B72="","",IFERROR( INDEX(R_COTIZACIONES!C:C,MATCH(B72,R_COTIZACIONES!A:A,0)), ""))} -> 76785900-7 | F72: no | G72: APACOM | H72: PHSMRT | I72: =IF(H72="","",VLOOKUP(H72,'Base de datos'!$E:$G,3,FALSE)) -> Photon Smart (par) | J72: 1 | K72: 95000 | L72: 0 | M72: =IF(K72="","",J72*K72*(1-IFERROR(L72,0))) -> 95000 | N72: =IF(M72="","",IF(F72="SI",M72*0.19,0)) -> 0 | O72: =IF(K72="","",M72+N72) -> 95000 | P72: =IF(K72="","",SUMIF($B:$B,B72,$O:$O)) -> 1710000 | Q72: =IF(H72="","",VLOOKUP(H72,'Base de datos'!E:M,9,FALSE)) -> 35692.8 | R72: =IF(Q72="","",SUMIF($B:$B,B72,$Q:$Q)) -> 731195.8
A73: =B73&"-"&C73 -> 52-3 | B73: 52 | C73: =IF(B73="","",COUNTIF($B$4:B73,B73)) -> 3 | D73: {=IF(B73="","",IFERROR( INDEX(R_COTIZACIONES!D:D,MATCH(B73,R_COTIZACIONES!A:A,0)), ""))} -> Espacio Norte La Serena | E73: {=IF(B73="","",IFERROR( INDEX(R_COTIZACIONES!C:C,MATCH(B73,R_COTIZACIONES!A:A,0)), ""))} -> 76785900-7 | F73: no | G73: Particular | H73: SEMT | I73: =IF(H73="","",VLOOKUP(H73,'Base de datos'!$E:$G,3,FALSE)) -> Servicio de instalación de punto eléctrico x mt | J73: 2 | K73: =IF(H73="","",VLOOKUP(H73,'Base de datos'!E:N,10,FALSE)) -> 20000 | L73: 0 | M73: =IF(K73="","",J73*K73*(1-IFERROR(L73,0))) -> 40000 | N73: =IF(M73="","",IF(F73="SI",M73*0.19,0)) -> 0 | O73: =IF(K73="","",M73+N73) -> 40000 | P73: =IF(K73="","",SUMIF($B:$B,B73,$O:$O)) -> 1710000 | Q73: =IF(H73="","",VLOOKUP(H73,'Base de datos'!E:M,9,FALSE)) -> 0 | R73: =IF(Q73="","",SUMIF($B:$B,B73,$Q:$Q)) -> 731195.8
A74: =B74&"-"&C74 -> 52-4 | B74: 52 | C74: =IF(B74="","",COUNTIF($B$4:B74,B74)) -> 4 | D74: {=IF(B74="","",IFERROR( INDEX(R_COTIZACIONES!D:D,MATCH(B74,R_COTIZACIONES!A:A,0)), ""))} -> Espacio Norte La Serena | E74: {=IF(B74="","",IFERROR( INDEX(R_COTIZACIONES!C:C,MATCH(B74,R_COTIZACIONES!A:A,0)), ""))} -> 76785900-7 | F74: no | G74: Otro | H74: FERRV | I74: =IF(H74="","",VLOOKUP(H74,'Base de datos'!$E:$G,3,FALSE)) -> Ferreterías varias | J74: 1 | K74: 50000 | L74: 0 | M74: =IF(K74="","",J74*K74*(1-IFERROR(L74,0))) -> 50000 | N74: =IF(M74="","",IF(F74="SI",M74*0.19,0)) -> 0 | O74: =IF(K74="","",M74+N74) -> 50000 | P74: =IF(K74="","",SUMIF($B:$B,B74,$O:$O)) -> 1710000 | Q74: =IF(H74="","",VLOOKUP(H74,'Base de datos'!E:M,9,FALSE)) -> 55000 | R74: =IF(Q74="","",SUMIF($B:$B,B74,$Q:$Q)) -> 731195.8
A75: =B75&"-"&C75 -> 52-5 | B75: 52 | C75: =IF(B75="","",COUNTIF($B$4:B75,B75)) -> 5 | D75: {=IF(B75="","",IFERROR( INDEX(R_COTIZACIONES!D:D,MATCH(B75,R_COTIZACIONES!A:A,0)), ""))} -> Espacio Norte La Serena | E75: {=IF(B75="","",IFERROR( INDEX(R_COTIZACIONES!C:C,MATCH(B75,R_COTIZACIONES!A:A,0)), ""))} -> 76785900-7 | F75: no | G75: Particular | H75: S02 | I75: =IF(H75="","",VLOOKUP(H75,'Base de datos'!$E:$G,3,FALSE)) -> Instalación de motor (Kit) | J75: 1 | K75: 300000 | L75: 0 | M75: =IF(K75="","",J75*K75*(1-IFERROR(L75,0))) -> 300000 | N75: =IF(M75="","",IF(F75="SI",M75*0.19,0)) -> 0 | O75: =IF(K75="","",M75+N75) -> 300000 | P75: =IF(K75="","",SUMIF($B:$B,B75,$O:$O)) -> 1710000 | Q75: =IF(H75="","",VLOOKUP(H75,'Base de datos'!E:M,9,FALSE)) -> 180000 | R75: =IF(Q75="","",SUMIF($B:$B,B75,$Q:$Q)) -> 731195.8
A76: =B76&"-"&C76 -> 52-6 | B76: 52 | C76: =IF(B76="","",COUNTIF($B$4:B76,B76)) -> 6 | D76: {=IF(B76="","",IFERROR( INDEX(R_COTIZACIONES!D:D,MATCH(B76,R_COTIZACIONES!A:A,0)), ""))} -> Espacio Norte La Serena | E76: {=IF(B76="","",IFERROR( INDEX(R_COTIZACIONES!C:C,MATCH(B76,R_COTIZACIONES!A:A,0)), ""))} -> 76785900-7 | F76: no | G76: PRODALAM | H76: KITG4060 | I76: =IF(H76="","",VLOOKUP(H76,'Base de datos'!$E:$G,3,FALSE)) -> Set de Guias 40x60 | J76: 1 | K76: 25000 | L76: 0 | M76: =IF(K76="","",J76*K76*(1-IFERROR(L76,0))) -> 25000 | N76: =IF(M76="","",IF(F76="SI",M76*0.19,0)) -> 0 | O76: =IF(K76="","",M76+N76) -> 25000 | P76: =IF(K76="","",SUMIF($B:$B,B76,$O:$O)) -> 1710000 | Q76: =IF(H76="","",VLOOKUP(H76,'Base de datos'!E:M,9,FALSE)) -> 10019.4 | R76: =IF(Q76="","",SUMIF($B:$B,B76,$Q:$Q)) -> 731195.8
A77: =B77&"-"&C77 -> 53-1 | B77: 53 | C77: =IF(B77="","",COUNTIF($B$4:B77,B77)) -> 1 | D77: {=IF(B77="","",IFERROR( INDEX(R_COTIZACIONES!D:D,MATCH(B77,R_COTIZACIONES!A:A,0)), ""))} -> Espacio Norte La Serena | E77: {=IF(B77="","",IFERROR( INDEX(R_COTIZACIONES!C:C,MATCH(B77,R_COTIZACIONES!A:A,0)), ""))} -> 76785900-7 | F77: no | G77: APACOM | H77: D6KIT | I77: =IF(H77="","",VLOOKUP(H77,'Base de datos'!$E:$G,3,FALSE)) -> D6 (6 crem y 2 controles) | J77: 1 | K77: 850000 | L77: 0 | M77: =IF(K77="","",J77*K77*(1-IFERROR(L77,0))) -> 850000 | N77: =IF(M77="","",IF(F77="SI",M77*0.19,0)) -> 0 | O77: =IF(K77="","",M77+N77) -> 850000 | P77: =IF(K77="","",SUMIF($B:$B,B77,$O:$O)) -> 990000 | Q77: =IF(H77="","",VLOOKUP(H77,'Base de datos'!E:M,9,FALSE)) -> 311967 | R77: =IF(Q77="","",SUMIF($B:$B,B77,$Q:$Q)) -> 376986.4
A78: =B78&"-"&C78 -> 53-2 | B78: 53 | C78: =IF(B78="","",COUNTIF($B$4:B78,B78)) -> 2 | D78: {=IF(B78="","",IFERROR( INDEX(R_COTIZACIONES!D:D,MATCH(B78,R_COTIZACIONES!A:A,0)), ""))} -> Espacio Norte La Serena | E78: {=IF(B78="","",IFERROR( INDEX(R_COTIZACIONES!C:C,MATCH(B78,R_COTIZACIONES!A:A,0)), ""))} -> 76785900-7 | F78: no | G78: PRODALAM | H78: KITG4060 | I78: =IF(H78="","",VLOOKUP(H78,'Base de datos'!$E:$G,3,FALSE)) -> Set de Guias 40x60 | J78: 1 | K78: 50000 | L78: 0 | M78: =IF(K78="","",J78*K78*(1-IFERROR(L78,0))) -> 50000 | N78: =IF(M78="","",IF(F78="SI",M78*0.19,0)) -> 0 | O78: =IF(K78="","",M78+N78) -> 50000 | P78: =IF(K78="","",SUMIF($B:$B,B78,$O:$O)) -> 990000 | Q78: =IF(H78="","",VLOOKUP(H78,'Base de datos'!E:M,9,FALSE)) -> 10019.4 | R78: =IF(Q78="","",SUMIF($B:$B,B78,$Q:$Q)) -> 376986.4
A79: =B79&"-"&C79 -> 53-3 | B79: 53 | C79: =IF(B79="","",COUNTIF($B$4:B79,B79)) -> 3 | D79: {=IF(B79="","",IFERROR( INDEX(R_COTIZACIONES!D:D,MATCH(B79,R_COTIZACIONES!A:A,0)), ""))} -> Espacio Norte La Serena | E79: {=IF(B79="","",IFERROR( INDEX(R_COTIZACIONES!C:C,MATCH(B79,R_COTIZACIONES!A:A,0)), ""))} -> 76785900-7 | F79: no | G79: Particular | H79: SEMT | I79: =IF(H79="","",VLOOKUP(H79,'Base de datos'!$E:$G,3,FALSE)) -> Servicio de instalación de punto eléctrico x mt | J79: 2 | K79: =IF(H79="","",VLOOKUP(H79,'Base de datos'!E:N,10,FALSE)) -> 20000 | L79: 0 | M79: =IF(K79="","",J79*K79*(1-IFERROR(L79,0))) -> 40000 | N79: =IF(M79="","",IF(F79="SI",M79*0.19,0)) -> 0 | O79: =IF(K79="","",M79+N79) -> 40000 | P79: =IF(K79="","",SUMIF($B:$B,B79,$O:$O)) -> 990000 | Q79: =IF(H79="","",VLOOKUP(H79,'Base de datos'!E:M,9,FALSE)) -> 0 | R79: =IF(Q79="","",SUMIF($B:$B,B79,$Q:$Q)) -> 376986.4
A80: =B80&"-"&C80 -> 53-4 | B80: 53 | C80: =IF(B80="","",COUNTIF($B$4:B80,B80)) -> 4 | D80: {=IF(B80="","",IFERROR( INDEX(R_COTIZACIONES!D:D,MATCH(B80,R_COTIZACIONES!A:A,0)), ""))} -> Espacio Norte La Serena | E80: {=IF(B80="","",IFERROR( INDEX(R_COTIZACIONES!C:C,MATCH(B80,R_COTIZACIONES!A:A,0)), ""))} -> 76785900-7 | F80: no | G80: Otro | H80: FERRV | I80: =IF(H80="","",VLOOKUP(H80,'Base de datos'!$E:$G,3,FALSE)) -> Ferreterías varias | J80: 1 | K80: 50000 | L80: 0 | M80: =IF(K80="","",J80*K80*(1-IFERROR(L80,0))) -> 50000 | N80: =IF(M80="","",IF(F80="SI",M80*0.19,0)) -> 0 | O80: =IF(K80="","",M80+N80) -> 50000 | P80: =IF(K80="","",SUMIF($B:$B,B80,$O:$O)) -> 990000 | Q80: =IF(H80="","",VLOOKUP(H80,'Base de datos'!E:M,9,FALSE)) -> 55000 | R80: =IF(Q80="","",SUMIF($B:$B,B80,$Q:$Q)) -> 376986.4
A81: =B81&"-"&C81 -> 54-1 | B81: 54 | C81: =IF(B81="","",COUNTIF($B$4:B81,B81)) -> 1 | D81: {=IF(B81="","",IFERROR( INDEX(R_COTIZACIONES!D:D,MATCH(B81,R_COTIZACIONES!A:A,0)), ""))} -> Condominio Parque Libertad | E81: {=IF(B81="","",IFERROR( INDEX(R_COTIZACIONES!C:C,MATCH(B81,R_COTIZACIONES!A:A,0)), ""))} -> 53318313-1 | F81: no | G81: RW | H81: WP17 | I81: =IF(H81="","",VLOOKUP(H81,'Base de datos'!$E:$G,3,FALSE)) -> Controlador Wifi WP17 | J81: 1 | K81: 260000 | L81: 0 | M81: =IF(K81="","",J81*K81*(1-IFERROR(L81,0))) -> 260000 | N81: =IF(M81="","",IF(F81="SI",M81*0.19,0)) -> 0 | O81: =IF(K81="","",M81+N81) -> 260000 | P81: =IF(K81="","",SUMIF($B:$B,B81,$O:$O)) -> 260000 | Q81: =IF(H81="","",VLOOKUP(H81,'Base de datos'!E:M,9,FALSE)) -> 161840 | R81: =IF(Q81="","",SUMIF($B:$B,B81,$Q:$Q)) -> 161840
A82: =B82&"-"&C82 -> 55-1 | B82: 55 | C82: =IF(B82="","",COUNTIF($B$4:B82,B82)) -> 1 | D82: {=IF(B82="","",IFERROR( INDEX(R_COTIZACIONES!D:D,MATCH(B82,R_COTIZACIONES!A:A,0)), ""))} -> Cond Marina Horizonte | E82: {=IF(B82="","",IFERROR( INDEX(R_COTIZACIONES!C:C,MATCH(B82,R_COTIZACIONES!A:A,0)), ""))} -> 65094027-K | F82: no | G82: Smartsecure | H82: CM180H | I82: =IF(H82="","",VLOOKUP(H82,'Base de datos'!$E:$G,3,FALSE)) -> ZK Teco CM-180H Retenedor electromagnético para puertas batientes | J82: 2 | K82: 60000 | L82: 0 | M82: =IF(K82="","",J82*K82*(1-IFERROR(L82,0))) -> 120000 | N82: =IF(M82="","",IF(F82="SI",M82*0.19,0)) -> 0 | O82: =IF(K82="","",M82+N82) -> 120000 | P82: =IF(K82="","",SUMIF($B:$B,B82,$O:$O)) -> 310400 | Q82: =IF(H82="","",VLOOKUP(H82,'Base de datos'!E:M,9,FALSE)) -> 39041.2 | R82: =IF(Q82="","",SUMIF($B:$B,B82,$Q:$Q)) -> 79541.2
A83: =B83&"-"&C83 -> 55-2 | B83: 55 | C83: =IF(B83="","",COUNTIF($B$4:B83,B83)) -> 2 | D83: {=IF(B83="","",IFERROR( INDEX(R_COTIZACIONES!D:D,MATCH(B83,R_COTIZACIONES!A:A,0)), ""))} -> Cond Marina Horizonte | E83: {=IF(B83="","",IFERROR( INDEX(R_COTIZACIONES!C:C,MATCH(B83,R_COTIZACIONES!A:A,0)), ""))} -> 65094027-K | F83: Si | G83: Particular | H83: S05 | I83: =IF(H83="","",VLOOKUP(H83,'Base de datos'!$E:$G,3,FALSE)) -> Instalación Retenedor | J83: 2 | K83: 80000 | L83: 0 | M83: =IF(K83="","",J83*K83*(1-IFERROR(L83,0))) -> 160000 | N83: =IF(M83="","",IF(F83="SI",M83*0.19,0)) -> 30400 | O83: =IF(K83="","",M83+N83) -> 190400 | P83: =IF(K83="","",SUMIF($B:$B,B83,$O:$O)) -> 310400 | Q83: =IF(H83="","",VLOOKUP(H83,'Base de datos'!E:M,9,FALSE)) -> 40500 | R83: =IF(Q83="","",SUMIF($B:$B,B83,$Q:$Q)) -> 79541.2
A84: =B84&"-"&C84 -> 56-1 | B84: 56 | C84: =IF(B84="","",COUNTIF($B$4:B84,B84)) -> 1 | D84: {=IF(B84="","",IFERROR( INDEX(R_COTIZACIONES!D:D,MATCH(B84,R_COTIZACIONES!A:A,0)), ""))} -> Condominio Pacífico | E84: {=IF(B84="","",IFERROR( INDEX(R_COTIZACIONES!C:C,MATCH(B84,R_COTIZACIONES!A:A,0)), ""))} -> 76866075-2 | F84: Si | G84: Smartsecure | H84: CM180H | I84: =IF(H84="","",VLOOKUP(H84,'Base de datos'!$E:$G,3,FALSE)) -> ZK Teco CM-180H Retenedor electromagnético para puertas batientes | J84: 1 | K84: 60000 | L84: 0 | M84: =IF(K84="","",J84*K84*(1-IFERROR(L84,0))) -> 60000 | N84: =IF(M84="","",IF(F84="SI",M84*0.19,0)) -> 11400 | O84: =IF(K84="","",M84+N84) -> 71400 | P84: =IF(K84="","",SUMIF($B:$B,B84,$O:$O)) -> 90440 | Q84: =IF(H84="","",VLOOKUP(H84,'Base de datos'!E:M,9,FALSE)) -> 39041.2 | R84: =IF(Q84="","",SUMIF($B:$B,B84,$Q:$Q)) -> 55549.2
A85: =B85&"-"&C85 -> 56-2 | B85: 56 | C85: =IF(B85="","",COUNTIF($B$4:B85,B85)) -> 2 | D85: {=IF(B85="","",IFERROR( INDEX(R_COTIZACIONES!D:D,MATCH(B85,R_COTIZACIONES!A:A,0)), ""))} -> Condominio Pacífico | E85: {=IF(B85="","",IFERROR( INDEX(R_COTIZACIONES!C:C,MATCH(B85,R_COTIZACIONES!A:A,0)), ""))} -> 76866075-2 | F85: Si | G85: Smartsecure | H85: SOPRET01 | I85: =IF(H85="","",VLOOKUP(H85,'Base de datos'!$E:$G,3,FALSE)) -> Soporte retenedor tipo L | J85: 1 | K85: 16000 | L85: 0 | M85: =IF(K85="","",J85*K85*(1-IFERROR(L85,0))) -> 16000 | N85: =IF(M85="","",IF(F85="SI",M85*0.19,0)) -> 3040 | O85: =IF(K85="","",M85+N85) -> 19040 | P85: =IF(K85="","",SUMIF($B:$B,B85,$O:$O)) -> 90440 | Q85: =IF(H85="","",VLOOKUP(H85,'Base de datos'!E:M,9,FALSE)) -> 16508 | R85: =IF(Q85="","",SUMIF($B:$B,B85,$Q:$Q)) -> 55549.2
A86: =B86&"-"&C86 -> 57-1 | B86: 57 | C86: =IF(B86="","",COUNTIF($B$4:B86,B86)) -> 1 | D86: {=IF(B86="","",IFERROR( INDEX(R_COTIZACIONES!D:D,MATCH(B86,R_COTIZACIONES!A:A,0)), ""))} -> Condominio Vicenza II | E86: {=IF(B86="","",IFERROR( INDEX(R_COTIZACIONES!C:C,MATCH(B86,R_COTIZACIONES!A:A,0)), ""))} -> 65198585-4 | F86: Si | G86: Smartsecure | H86: CM180H | I86: =IF(H86="","",VLOOKUP(H86,'Base de datos'!$E:$G,3,FALSE)) -> ZK Teco CM-180H Retenedor electromagnético para puertas batientes | J86: 1 | K86: 70000 | L86: 0 | M86: =IF(K86="","",J86*K86*(1-IFERROR(L86,0))) -> 70000 | N86: =IF(M86="","",IF(F86="SI",M86*0.19,0)) -> 13300 | O86: =IF(K86="","",M86+N86) -> 83300 | P86: =IF(K86="","",SUMIF($B:$B,B86,$O:$O)) -> 130900 | Q86: =IF(H86="","",VLOOKUP(H86,'Base de datos'!E:M,9,FALSE)) -> 39041.2 | R86: =IF(Q86="","",SUMIF($B:$B,B86,$Q:$Q)) -> 79541.2
A87: =B87&"-"&C87 -> 57-2 | B87: 57 | C87: =IF(B87="","",COUNTIF($B$4:B87,B87)) -> 2 | D87: {=IF(B87="","",IFERROR( INDEX(R_COTIZACIONES!D:D,MATCH(B87,R_COTIZACIONES!A:A,0)), ""))} -> Condominio Vicenza II | E87: {=IF(B87="","",IFERROR( INDEX(R_COTIZACIONES!C:C,MATCH(B87,R_COTIZACIONES!A:A,0)), ""))} -> 65198585-4 | F87: Si | G87: Particular | H87: S05 | I87: =IF(H87="","",VLOOKUP(H87,'Base de datos'!$E:$G,3,FALSE)) -> Instalación Retenedor | J87: 1 | K87: 40000 | L87: 0 | M87: =IF(K87="","",J87*K87*(1-IFERROR(L87,0))) -> 40000 | N87: =IF(M87="","",IF(F87="SI",M87*0.19,0)) -> 7600 | O87: =IF(K87="","",M87+N87) -> 47600 | P87: =IF(K87="","",SUMIF($B:$B,B87,$O:$O)) -> 130900 | Q87: =IF(H87="","",VLOOKUP(H87,'Base de datos'!E:M,9,FALSE)) -> 40500 | R87: =IF(Q87="","",SUMIF($B:$B,B87,$Q:$Q)) -> 79541.2
A88: =B88&"-"&C88 -> 58-1 | B88: 58 | C88: =IF(B88="","",COUNTIF($B$4:B88,B88)) -> 1 | D88: {=IF(B88="","",IFERROR( INDEX(R_COTIZACIONES!D:D,MATCH(B88,R_COTIZACIONES!A:A,0)), ""))} -> Portal del Valle II | E88: {=IF(B88="","",IFERROR( INDEX(R_COTIZACIONES!C:C,MATCH(B88,R_COTIZACIONES!A:A,0)), ""))} -> 53332414-2 | F88: Si | G88: Particular | H88: S09 | I88: =IF(H88="","",VLOOKUP(H88,'Base de datos'!$E:$G,3,FALSE)) -> Servicio de recuperación post colisión Motor Centurion | J88: 1 | K88: 200000 | L88: 0 | M88: =IF(K88="","",J88*K88*(1-IFERROR(L88,0))) -> 200000 | N88: =IF(M88="","",IF(F88="SI",M88*0.19,0)) -> 38000 | O88: =IF(K88="","",M88+N88) -> 238000 | P88: =IF(K88="","",SUMIF($B:$B,B88,$O:$O)) -> 238000 | Q88: =IF(H88="","",VLOOKUP(H88,'Base de datos'!E:M,9,FALSE)) -> 100000 | R88: =IF(Q88="","",SUMIF($B:$B,B88,$Q:$Q)) -> 100000
A89: =B89&"-"&C89 -> 59-1 | B89: 59 | C89: =IF(B89="","",COUNTIF($B$4:B89,B89)) -> 1 | D89: {=IF(B89="","",IFERROR( INDEX(R_COTIZACIONES!D:D,MATCH(B89,R_COTIZACIONES!A:A,0)), ""))} -> Condominio Vicenza II | E89: {=IF(B89="","",IFERROR( INDEX(R_COTIZACIONES!C:C,MATCH(B89,R_COTIZACIONES!A:A,0)), ""))} -> 65198585-4 | F89: Si | G89: Particular | H89: S01CIP | I89: =IF(H89="","",VLOOKUP(H89,'Base de datos'!$E:$G,3,FALSE)) -> Servicio de recuperación IP de cámara asociada a NVR | J89: 1 | K89: 250000 | L89: 0 | M89: =IF(K89="","",J89*K89*(1-IFERROR(L89,0))) -> 250000 | N89: =IF(M89="","",IF(F89="SI",M89*0.19,0)) -> 47500 | O89: =IF(K89="","",M89+N89) -> 297500
A90: =B90&"-"&C90 -> 60-1 | B90: 60 | C90: =IF(B90="","",COUNTIF($B$4:B90,B90)) -> 1 | D90: {=IF(B90="","",IFERROR( INDEX(R_COTIZACIONES!D:D,MATCH(B90,R_COTIZACIONES!A:A,0)), ""))} -> Condominio Vicenza II | E90: {=IF(B90="","",IFERROR( INDEX(R_COTIZACIONES!C:C,MATCH(B90,R_COTIZACIONES!A:A,0)), ""))} -> 65198585-4 | F90: Si | G90: Smartsecure | H90: CM180H | I90: =IF(H90="","",VLOOKUP(H90,'Base de datos'!$E:$G,3,FALSE)) -> ZK Teco CM-180H Retenedor electromagnético para puertas batientes | J90: 1 | K90: 70000 | L90: 0 | M90: =IF(K90="","",J90*K90*(1-IFERROR(L90,0))) -> 70000 | N90: =IF(M90="","",IF(F90="SI",M90*0.19,0)) -> 13300 | O90: =IF(K90="","",M90+N90) -> 83300 | P90: =IF(K90="","",SUMIF($B:$B,B90,$O:$O)) -> 386750
A91: =B91&"-"&C91 -> 60-2 | B91: 60 | C91: =IF(B91="","",COUNTIF($B$4:B91,B91)) -> 2 | D91: {=IF(B91="","",IFERROR( INDEX(R_COTIZACIONES!D:D,MATCH(B91,R_COTIZACIONES!A:A,0)), ""))} -> Condominio Vicenza II | E91: {=IF(B91="","",IFERROR( INDEX(R_COTIZACIONES!C:C,MATCH(B91,R_COTIZACIONES!A:A,0)), ""))} -> 65198585-4 | F91: Si | G91: Smartsecure | H91: ASI1201E | I91: =IF(H91="","",VLOOKUP(H91,'Base de datos'!$E:$G,3,FALSE)) -> Control Acceso DHI-ASI1201E | J91: 1 | K91: 110000 | L91: 0 | M91: =IF(K91="","",J91*K91*(1-IFERROR(L91,0))) -> 110000 | N91: =IF(M91="","",IF(F91="SI",M91*0.19,0)) -> 20900 | O91: =IF(K91="","",M91+N91) -> 130900 | P91: =IF(K91="","",SUMIF($B:$B,B91,$O:$O)) -> 386750
A92: =B92&"-"&C92 -> 60-3 | B92: 60 | C92: =IF(B92="","",COUNTIF($B$4:B92,B92)) -> 3 | D92: {=IF(B92="","",IFERROR( INDEX(R_COTIZACIONES!D:D,MATCH(B92,R_COTIZACIONES!A:A,0)), ""))} -> Condominio Vicenza II | E92: {=IF(B92="","",IFERROR( INDEX(R_COTIZACIONES!C:C,MATCH(B92,R_COTIZACIONES!A:A,0)), ""))} -> 65198585-4 | F92: Si | G92: Particular | H92: S05 | I92: =IF(H92="","",VLOOKUP(H92,'Base de datos'!$E:$G,3,FALSE)) -> Instalación Retenedor | J92: 1 | K92: 45000 | L92: 0 | M92: =IF(K92="","",J92*K92*(1-IFERROR(L92,0))) -> 45000 | N92: =IF(M92="","",IF(F92="SI",M92*0.19,0)) -> 8550 | O92: =IF(K92="","",M92+N92) -> 53550 | P92: =IF(K92="","",SUMIF($B:$B,B92,$O:$O)) -> 386750
A93: =B93&"-"&C93 -> 60-4 | B93: 60 | C93: =IF(B93="","",COUNTIF($B$4:B93,B93)) -> 4 | D93: {=IF(B93="","",IFERROR( INDEX(R_COTIZACIONES!D:D,MATCH(B93,R_COTIZACIONES!A:A,0)), ""))} -> Condominio Vicenza II | E93: {=IF(B93="","",IFERROR( INDEX(R_COTIZACIONES!C:C,MATCH(B93,R_COTIZACIONES!A:A,0)), ""))} -> 65198585-4 | F93: Si | G93: Particular | H93: S10 | I93: =IF(H93="","",VLOOKUP(H93,'Base de datos'!$E:$G,3,FALSE)) -> Servicio de instalación digitador de acceso | J93: 1 | K93: 100000 | L93: 0 | M93: =IF(K93="","",J93*K93*(1-IFERROR(L93,0))) -> 100000 | N93: =IF(M93="","",IF(F93="SI",M93*0.19,0)) -> 19000 | O93: =IF(K93="","",M93+N93) -> 119000 | P93: =IF(K93="","",SUMIF($B:$B,B93,$O:$O)) -> 386750 | Q93: =IF(H93="","",VLOOKUP(H93,'Base de datos'!E:M,9,FALSE)) -> 10000 | R93: =IF(Q93="","",SUMIF($B:$B,B93,$Q:$Q)) -> 10000
A94: =B94&"-"&C94 -> 61-1 | B94: 61 | C94: =IF(B94="","",COUNTIF($B$4:B94,B94)) -> 1 | D94: {=IF(B94="","",IFERROR( INDEX(R_COTIZACIONES!D:D,MATCH(B94,R_COTIZACIONES!A:A,0)), ""))} -> Condominio Vicenza II | E94: {=IF(B94="","",IFERROR( INDEX(R_COTIZACIONES!C:C,MATCH(B94,R_COTIZACIONES!A:A,0)), ""))} -> 65198585-4 | F94: no | G94: Smartsecure | H94: CM180H | I94: =IF(H94="","",VLOOKUP(H94,'Base de datos'!$E:$G,3,FALSE)) -> ZK Teco CM-180H Retenedor electromagnético para puertas batientes | J94: 1 | K94: 70000 | L94: 0 | M94: =IF(K94="","",J94*K94*(1-IFERROR(L94,0))) -> 70000 | N94: =IF(M94="","",IF(F94="SI",M94*0.19,0)) -> 0 | O94: =IF(K94="","",M94+N94) -> 70000 | P94: =IF(K94="","",SUMIF($B:$B,B94,$O:$O)) -> 325000 | Q94: =IF(H94="","",VLOOKUP(H94,'Base de datos'!E:M,9,FALSE)) -> 39041.2 | R94: =IF(Q94="","",SUMIF($B:$B,B94,$Q:$Q)) -> 175594.7
A95: =B95&"-"&C95 -> 61-2 | B95: 61 | C95: =IF(B95="","",COUNTIF($B$4:B95,B95)) -> 2 | D95: {=IF(B95="","",IFERROR( INDEX(R_COTIZACIONES!D:D,MATCH(B95,R_COTIZACIONES!A:A,0)), ""))} -> Condominio Vicenza II | E95: {=IF(B95="","",IFERROR( INDEX(R_COTIZACIONES!C:C,MATCH(B95,R_COTIZACIONES!A:A,0)), ""))} -> 65198585-4 | F95: no | G95: Smartsecure | H95: ASI1201E | I95: =IF(H95="","",VLOOKUP(H95,'Base de datos'!$E:$G,3,FALSE)) -> Control Acceso DHI-ASI1201E | J95: 1 | K95: 110000 | L95: 0 | M95: =IF(K95="","",J95*K95*(1-IFERROR(L95,0))) -> 110000 | N95: =IF(M95="","",IF(F95="SI",M95*0.19,0)) -> 0 | O95: =IF(K95="","",M95+N95) -> 110000 | P95: =IF(K95="","",SUMIF($B:$B,B95,$O:$O)) -> 325000 | Q95: =IF(H95="","",VLOOKUP(H95,'Base de datos'!E:M,9,FALSE)) -> 86053.5 | R95: =IF(Q95="","",SUMIF($B:$B,B95,$Q:$Q)) -> 175594.7
A96: =B96&"-"&C96 -> 61-3 | B96: 61 | C96: =IF(B96="","",COUNTIF($B$4:B96,B96)) -> 3 | D96: {=IF(B96="","",IFERROR( INDEX(R_COTIZACIONES!D:D,MATCH(B96,R_COTIZACIONES!A:A,0)), ""))} -> Condominio Vicenza II | E96: {=IF(B96="","",IFERROR( INDEX(R_COTIZACIONES!C:C,MATCH(B96,R_COTIZACIONES!A:A,0)), ""))} -> 65198585-4 | F96: no | G96: Particular | H96: S05 | I96: =IF(H96="","",VLOOKUP(H96,'Base de datos'!$E:$G,3,FALSE)) -> Instalación Retenedor | J96: 1 | K96: 45000 | L96: 0 | M96: =IF(K96="","",J96*K96*(1-IFERROR(L96,0))) -> 45000 | N96: =IF(M96="","",IF(F96="SI",M96*0.19,0)) -> 0 | O96: =IF(K96="","",M96+N96) -> 45000 | P96: =IF(K96="","",SUMIF($B:$B,B96,$O:$O)) -> 325000 | Q96: =IF(H96="","",VLOOKUP(H96,'Base de datos'!E:M,9,FALSE)) -> 40500 | R96: =IF(Q96="","",SUMIF($B:$B,B96,$Q:$Q)) -> 175594.7
A97: =B97&"-"&C97 -> 61-4 | B97: 61 | C97: =IF(B97="","",COUNTIF($B$4:B97,B97)) -> 4 | D97: {=IF(B97="","",IFERROR( INDEX(R_COTIZACIONES!D:D,MATCH(B97,R_COTIZACIONES!A:A,0)), ""))} -> Condominio Vicenza II | E97: {=IF(B97="","",IFERROR( INDEX(R_COTIZACIONES!C:C,MATCH(B97,R_COTIZACIONES!A:A,0)), ""))} -> 65198585-4 | F97: no | G97: Particular | H97: S10 | I97: =IF(H97="","",VLOOKUP(H97,'Base de datos'!$E:$G,3,FALSE)) -> Servicio de instalación digitador de acceso | J97: 1 | K97: 100000 | L97: 0 | M97: =IF(K97="","",J97*K97*(1-IFERROR(L97,0))) -> 100000 | N97: =IF(M97="","",IF(F97="SI",M97*0.19,0)) -> 0 | O97: =IF(K97="","",M97+N97) -> 100000 | P97: =IF(K97="","",SUMIF($B:$B,B97,$O:$O)) -> 325000 | Q97: =IF(H97="","",VLOOKUP(H97,'Base de datos'!E:M,9,FALSE)) -> 10000 | R97: =IF(Q97="","",SUMIF($B:$B,B97,$Q:$Q)) -> 175594.7
A98: =B98&"-"&C98 -> 62-1 | B98: 62 | C98: =IF(B98="","",COUNTIF($B$4:B98,B98)) -> 1 | D98: {=IF(B98="","",IFERROR( INDEX(R_COTIZACIONES!D:D,MATCH(B98,R_COTIZACIONES!A:A,0)), ""))} -> Distrito Verde I | E98: {=IF(B98="","",IFERROR( INDEX(R_COTIZACIONES!C:C,MATCH(B98,R_COTIZACIONES!A:A,0)), ""))} -> 65.229.898-2 | F98: Si | G98: Particular | H98: S07 | I98: =IF(H98="","",VLOOKUP(H98,'Base de datos'!$E:$G,3,FALSE)) -> Mantención programada | J98: 1 | K98: 200000 | L98: 0 | M98: =IF(K98="","",J98*K98*(1-IFERROR(L98,0))) -> 200000 | N98: =IF(M98="","",IF(F98="SI",M98*0.19,0)) -> 38000 | O98: =IF(K98="","",M98+N98) -> 238000 | P98: =IF(K98="","",SUMIF($B:$B,B98,$O:$O)) -> 238000 | Q98: =IF(H98="","",VLOOKUP(H98,'Base de datos'!E:M,9,FALSE)) -> 100000 | R98: =IF(Q98="","",SUMIF($B:$B,B98,$Q:$Q)) -> 100000
A99: =B99&"-"&C99 -> 63-1 | B99: 63 | C99: =IF(B99="","",COUNTIF($B$4:B99,B99)) -> 1 | D99: {=IF(B99="","",IFERROR( INDEX(R_COTIZACIONES!D:D,MATCH(B99,R_COTIZACIONES!A:A,0)), ""))} -> Condominio Palermo | E99: {=IF(B99="","",IFERROR( INDEX(R_COTIZACIONES!C:C,MATCH(B99,R_COTIZACIONES!A:A,0)), ""))} -> 53.312.705-3 | F99: Si | G99: RW | H99: D10SKIT | I99: =IF(H99="","",VLOOKUP(H99,'Base de datos'!$E:$G,3,FALSE)) -> D10 Standard Kit 1(6 crem y 2 controles) | J99: 1 | K99: 1050000 | L99: 0.05 | M99: =IF(K99="","",J99*K99*(1-IFERROR(L99,0))) -> 997500 | N99: =IF(M99="","",IF(F99="SI",M99*0.19,0)) -> 189525 | O99: =IF(K99="","",M99+N99) -> 1187025 | P99: =IF(K99="","",SUMIF($B:$B,B99,$O:$O)) -> 1854020 | Q99: =IF(H99="","",VLOOKUP(H99,'Base de datos'!E:M,9,FALSE)) -> 420000 | R99: =IF(Q99="","",SUMIF($B:$B,B99,$Q:$Q)) -> 668433.1
A100: =B100&"-"&C100 -> 63-2 | B100: 63 | C100: =IF(B100="","",COUNTIF($B$4:B100,B100)) -> 2 | D100: {=IF(B100="","",IFERROR( INDEX(R_COTIZACIONES!D:D,MATCH(B100,R_COTIZACIONES!A:A,0)), ""))} -> Condominio Palermo | E100: {=IF(B100="","",IFERROR( INDEX(R_COTIZACIONES!C:C,MATCH(B100,R_COTIZACIONES!A:A,0)), ""))} -> 53.312.705-3 | F100: Si | G100: RW | H100: PHSMRT | I100: =IF(H100="","",VLOOKUP(H100,'Base de datos'!$E:$G,3,FALSE)) -> Photon Smart (par) | J100: 1 | K100: 100000 | L100: 0.05 | M100: =IF(K100="","",J100*K100*(1-IFERROR(L100,0))) -> 95000 | N100: =IF(M100="","",IF(F100="SI",M100*0.19,0)) -> 18050 | O100: =IF(K100="","",M100+N100) -> 113050 | P100: =IF(K100="","",SUMIF($B:$B,B100,$O:$O)) -> 1854020 | Q100: =IF(H100="","",VLOOKUP(H100,'Base de datos'!E:M,9,FALSE)) -> 35692.8 | R100: =IF(Q100="","",SUMIF($B:$B,B100,$Q:$Q)) -> 668433.1
A101: =B101&"-"&C101 -> 63-3 | B101: 63 | C101: =IF(B101="","",COUNTIF($B$4:B101,B101)) -> 3 | D101: {=IF(B101="","",IFERROR( INDEX(R_COTIZACIONES!D:D,MATCH(B101,R_COTIZACIONES!A:A,0)), ""))} -> Condominio Palermo | E101: {=IF(B101="","",IFERROR( INDEX(R_COTIZACIONES!C:C,MATCH(B101,R_COTIZACIONES!A:A,0)), ""))} -> 53.312.705-3 | F101: Si | G101: PRODALAM | H101: R100 | I101: =IF(H101="","",VLOOKUP(H101,'Base de datos'!$E:$G,3,FALSE)) -> Ruedas c/ Pasador 100 mm | J101: 2 | K101: 30000 | L101: 0.05 | M101: =IF(K101="","",J101*K101*(1-IFERROR(L101,0))) -> 57000 | N101: =IF(M101="","",IF(F101="SI",M101*0.19,0)) -> 10830 | O101: =IF(K101="","",M101+N101) -> 67830 | P101: =IF(K101="","",SUMIF($B:$B,B101,$O:$O)) -> 1854020 | Q101: =IF(H101="","",VLOOKUP(H101,'Base de datos'!E:M,9,FALSE)) -> 13469.5 | R101: =IF(Q101="","",SUMIF($B:$B,B101,$Q:$Q)) -> 668433.1
A102: =B102&"-"&C102 -> 63-4 | B102: 63 | C102: =IF(B102="","",COUNTIF($B$4:B102,B102)) -> 4 | D102: {=IF(B102="","",IFERROR( INDEX(R_COTIZACIONES!D:D,MATCH(B102,R_COTIZACIONES!A:A,0)), ""))} -> Condominio Palermo | E102: {=IF(B102="","",IFERROR( INDEX(R_COTIZACIONES!C:C,MATCH(B102,R_COTIZACIONES!A:A,0)), ""))} -> 53.312.705-3 | F102: Si | G102: APACOM | H102: BALNC1224 | I102: =IF(H102="","",VLOOKUP(H102,'Base de datos'!$E:$G,3,FALSE)) -> Baliza NICE 12-38V | J102: 1 | K102: 50000 | L102: 0.05 | M102: =IF(K102="","",J102*K102*(1-IFERROR(L102,0))) -> 47500 | N102: =IF(M102="","",IF(F102="SI",M102*0.19,0)) -> 9025 | O102: =IF(K102="","",M102+N102) -> 56525 | P102: =IF(K102="","",SUMIF($B:$B,B102,$O:$O)) -> 1854020 | Q102: =IF(H102="","",VLOOKUP(H102,'Base de datos'!E:M,9,FALSE)) -> 19270.8 | R102: =IF(Q102="","",SUMIF($B:$B,B102,$Q:$Q)) -> 668433.1
A103: =B103&"-"&C103 -> 63-5 | B103: 63 | C103: =IF(B103="","",COUNTIF($B$4:B103,B103)) -> 5 | D103: {=IF(B103="","",IFERROR( INDEX(R_COTIZACIONES!D:D,MATCH(B103,R_COTIZACIONES!A:A,0)), ""))} -> Condominio Palermo | E103: {=IF(B103="","",IFERROR( INDEX(R_COTIZACIONES!C:C,MATCH(B103,R_COTIZACIONES!A:A,0)), ""))} -> 53.312.705-3 | F103: Si | G103: Particular | H103: S02 | I103: =IF(H103="","",VLOOKUP(H103,'Base de datos'!$E:$G,3,FALSE)) -> Instalación de motor (Kit) | J103: 1 | K103: 380000 | L103: 0.05 | M103: =IF(K103="","",J103*K103*(1-IFERROR(L103,0))) -> 361000 | N103: =IF(M103="","",IF(F103="SI",M103*0.19,0)) -> 68590 | O103: =IF(K103="","",M103+N103) -> 429590 | P103: =IF(K103="","",SUMIF($B:$B,B103,$O:$O)) -> 1854020 | Q103: =IF(H103="","",VLOOKUP(H103,'Base de datos'!E:M,9,FALSE)) -> 180000 | R103: =IF(Q103="","",SUMIF($B:$B,B103,$Q:$Q)) -> 668433.1
A104: =B104&"-"&C104 -> 64-1 | B104: 64 | C104: =IF(B104="","",COUNTIF($B$4:B104,B104)) -> 1 | D104: {=IF(B104="","",IFERROR( INDEX(R_COTIZACIONES!D:D,MATCH(B104,R_COTIZACIONES!A:A,0)), ""))} -> Condominio Palermo | E104: {=IF(B104="","",IFERROR( INDEX(R_COTIZACIONES!C:C,MATCH(B104,R_COTIZACIONES!A:A,0)), ""))} -> 53.312.705-3 | F104: Si | G104: RW | H104: D10TKIT | I104: =IF(H104="","",VLOOKUP(H104,'Base de datos'!$E:$G,3,FALSE)) -> D10 Turbo (6 crem y 2 controles) | J104: 1 | K104: 1150000 | L104: 0.05 | M104: =IF(K104="","",J104*K104*(1-IFERROR(L104,0))) -> 1092500 | N104: =IF(M104="","",IF(F104="SI",M104*0.19,0)) -> 207575 | O104: =IF(K104="","",M104+N104) -> 1300075 | P104: =IF(K104="","",SUMIF($B:$B,B104,$O:$O)) -> 1967070 | Q104: =IF(H104="","",VLOOKUP(H104,'Base de datos'!E:M,9,FALSE)) -> 450483.6 | R104: =IF(Q104="","",SUMIF($B:$B,B104,$Q:$Q)) -> 713653.9
... A110: =B110&"-"&C110 -> 65-2 | B110: 65 | C110: =IF(B110="","",COUNTIF($B$4:B110,B110)) -> 2 | D110: {=IF(B110="","",IFERROR( INDEX(R_COTIZACIONES!D:D,MATCH(B110,R_COTIZACIONES!A:A,0)), ""))} -> Condominio Neo Spazio | E110: {=IF(B110="","",IFERROR( INDEX(R_COTIZACIONES!C:C,MATCH(B110,R_COTIZACIONES!A:A,0)), ""))} -> 65.095.336-2 | F110: Si | G110: Particular | H110: S09F | I110: =IF(H110="","",VLOOKUP(H110,'Base de datos'!$E:$G,3,FALSE)) -> Servicio de recuperación estructural | J110: 1 | K110: 300000 | L110: 0 | M110: =IF(K110="","",J110*K110*(1-IFERROR(L110,0))) -> 300000 | N110: =IF(M110="","",IF(F110="SI",M110*0.19,0)) -> 57000 | O110: =IF(K110="","",M110+N110) -> 357000 | P110: =IF(K110="","",SUMIF($B:$B,B110,$O:$O)) -> 428400 | Q110: =IF(H110="","",VLOOKUP(H110,'Base de datos'!E:M,9,FALSE)) -> 0 | R110: =IF(Q110="","",SUMIF($B:$B,B110,$Q:$Q)) -> 4633.8
A111: =B111&"-"&C111 -> 66-1 | B111: 66 | C111: =IF(B111="","",COUNTIF($B$4:B111,B111)) -> 1 | D111: {=IF(B111="","",IFERROR( INDEX(R_COTIZACIONES!D:D,MATCH(B111,R_COTIZACIONES!A:A,0)), ""))} -> Comunidad Edificio Florencia | E111: {=IF(B111="","",IFERROR( INDEX(R_COTIZACIONES!C:C,MATCH(B111,R_COTIZACIONES!A:A,0)), ""))} -> 56047780-5 | F111: no | G111: RW | H111: NOVA2 | I111: =IF(H111="","",VLOOKUP(H111,'Base de datos'!$E:$G,3,FALSE)) -> Control NOVA 2CH | J111: 10 | K111: 17000 | L111: 0 | M111: =IF(K111="","",J111*K111*(1-IFERROR(L111,0))) -> 170000 | N111: =IF(M111="","",IF(F111="SI",M111*0.19,0)) -> 0 | O111: =IF(K111="","",M111+N111) -> 170000 | Q111: =IF(H111="","",VLOOKUP(H111,'Base de datos'!E:M,9,FALSE)) -> 8021.7 | R111: =IF(Q111="","",SUMIF($B:$B,B111,$Q:$Q)) -> 8021.7
A112: =B112&"-"&C112 -> 67-1 | B112: 67 | C112: =IF(B112="","",COUNTIF($B$4:B112,B112)) -> 1 | D112: {=IF(B112="","",IFERROR( INDEX(R_COTIZACIONES!D:D,MATCH(B112,R_COTIZACIONES!A:A,0)), ""))} -> Espacio Urbano | E112: {=IF(B112="","",IFERROR( INDEX(R_COTIZACIONES!C:C,MATCH(B112,R_COTIZACIONES!A:A,0)), ""))} -> 65.049.582-9 | F112: Si | G112: APACOM | H112: D6KIT | I112: =IF(H112="","",VLOOKUP(H112,'Base de datos'!$E:$G,3,FALSE)) -> D6 (6 crem y 2 controles) | J112: 1 | K112: 750000 | L112: 0.1 | M112: =IF(K112="","",J112*K112*(1-IFERROR(L112,0))) -> 675000 | N112: =IF(M112="","",IF(F112="SI",M112*0.19,0)) -> 128250 | O112: =IF(K112="","",M112+N112) -> 803250 | Q112: =IF(H112="","",VLOOKUP(H112,'Base de datos'!E:M,9,FALSE)) -> 311967 | R112: =IF(Q112="","",SUMIF($B:$B,B112,$Q:$Q)) -> 527659.8
A113: =B113&"-"&C113 -> 67-2 | B113: 67 | C113: =IF(B113="","",COUNTIF($B$4:B113,B113)) -> 2 | D113: {=IF(B113="","",IFERROR( INDEX(R_COTIZACIONES!D:D,MATCH(B113,R_COTIZACIONES!A:A,0)), ""))} -> Espacio Urbano | E113: {=IF(B113="","",IFERROR( INDEX(R_COTIZACIONES!C:C,MATCH(B113,R_COTIZACIONES!A:A,0)), ""))} -> 65.049.582-9 | F113: Si | G113: APACOM | H113: PHSMRT | I113: =IF(H113="","",VLOOKUP(H113,'Base de datos'!$E:$G,3,FALSE)) -> Photon Smart (par) | J113: 1 | K113: 100000 | L113: 0.1 | M113: =IF(K113="","",J113*K113*(1-IFERROR(L113,0))) -> 90000 | N113: =IF(M113="","",IF(F113="SI",M113*0.19,0)) -> 17100 | O113: =IF(K113="","",M113+N113) -> 107100 | Q113: =IF(H113="","",VLOOKUP(H113,'Base de datos'!E:M,9,FALSE)) -> 35692.8 | R113: =IF(Q113="","",SUMIF($B:$B,B113,$Q:$Q)) -> 527659.8
A114: =B114&"-"&C114 -> 67-3 | B114: 67 | C114: =IF(B114="","",COUNTIF($B$4:B114,B114)) -> 3 | D114: {=IF(B114="","",IFERROR( INDEX(R_COTIZACIONES!D:D,MATCH(B114,R_COTIZACIONES!A:A,0)), ""))} -> Espacio Urbano | E114: {=IF(B114="","",IFERROR( INDEX(R_COTIZACIONES!C:C,MATCH(B114,R_COTIZACIONES!A:A,0)), ""))} -> 65.049.582-9 | F114: Si | G114: Particular | H114: S02 | I114: =IF(H114="","",VLOOKUP(H114,'Base de datos'!$E:$G,3,FALSE)) -> Instalación de motor (Kit) | J114: 1 | K114: 300000 | L114: 0.05 | M114: =IF(K114="","",J114*K114*(1-IFERROR(L114,0))) -> 285000 | N114: =IF(M114="","",IF(F114="SI",M114*0.19,0)) -> 54150 | O114: =IF(K114="","",M114+N114) -> 339150 | Q114: =IF(H114="","",VLOOKUP(H114,'Base de datos'!E:M,9,FALSE)) -> 180000 | R114: =IF(Q114="","",SUMIF($B:$B,B114,$Q:$Q)) -> 527659.8
A115: =B115&"-"&C115 -> 68-1 | B115: 68 | C115: =IF(B115="","",COUNTIF($B$4:B115,B115)) -> 1 | D115: {=IF(B115="","",IFERROR( INDEX(R_COTIZACIONES!D:D,MATCH(B115,R_COTIZACIONES!A:A,0)), ""))} -> Paseo San Carlos VII | E115: {=IF(B115="","",IFERROR( INDEX(R_COTIZACIONES!C:C,MATCH(B115,R_COTIZACIONES!A:A,0)), ""))} -> 76866075-1 | F115: Si | G115: PRODALAM | H115: R100 | I115: =IF(H115="","",VLOOKUP(H115,'Base de datos'!$E:$G,3,FALSE)) -> Ruedas c/ Pasador 100 mm | J115: 2 | K115: 25000 | L115: 0 | M115: =IF(K115="","",J115*K115*(1-IFERROR(L115,0))) -> 50000 | N115: =IF(M115="","",IF(F115="SI",M115*0.19,0)) -> 9500 | O115: =IF(K115="","",M115+N115) -> 59500 | Q115: =IF(H115="","",VLOOKUP(H115,'Base de datos'!E:M,9,FALSE)) -> 13469.5 | R115: =IF(Q115="","",SUMIF($B:$B,B115,$Q:$Q)) -> 35969.5
A116: =B116&"-"&C116 -> 68-2 | B116: 68 | C116: =IF(B116="","",COUNTIF($B$4:B116,B116)) -> 2 | D116: {=IF(B116="","",IFERROR( INDEX(R_COTIZACIONES!D:D,MATCH(B116,R_COTIZACIONES!A:A,0)), ""))} -> Paseo San Carlos VII | E116: {=IF(B116="","",IFERROR( INDEX(R_COTIZACIONES!C:C,MATCH(B116,R_COTIZACIONES!A:A,0)), ""))} -> 76866075-1 | F116: Si | G116: Particular | H116: S03 | I116: =IF(H116="","",VLOOKUP(H116,'Base de datos'!$E:$G,3,FALSE)) -> Instalación de ruedas (Unidad) | J116: 2 | K116: 40000 | L116: 0 | M116: =IF(K116="","",J116*K116*(1-IFERROR(L116,0))) -> 80000 | N116: =IF(M116="","",IF(F116="SI",M116*0.19,0)) -> 15200 | O116: =IF(K116="","",M116+N116) -> 95200 | Q116: =IF(H116="","",VLOOKUP(H116,'Base de datos'!E:M,9,FALSE)) -> 22500 | R116: =IF(Q116="","",SUMIF($B:$B,B116,$Q:$Q)) -> 35969.5
A117: =B117&"-"&C117 -> 69-1 | B117: 69 | C117: =IF(B117="","",COUNTIF($B$4:B117,B117)) -> 1 | D117: {=IF(B117="","",IFERROR( INDEX(R_COTIZACIONES!D:D,MATCH(B117,R_COTIZACIONES!A:A,0)), ""))} -> Condominio Ossandon | E117: {=IF(B117="","",IFERROR( INDEX(R_COTIZACIONES!C:C,MATCH(B117,R_COTIZACIONES!A:A,0)), ""))} -> 65.066.845-6 | F117: no | G117: RW | H117: WP17 | I117: =IF(H117="","",VLOOKUP(H117,'Base de datos'!$E:$G,3,FALSE)) -> Controlador Wifi WP17 | J117: 1 | K117: 220000 | L117: 0 | M117: =IF(K117="","",J117*K117*(1-IFERROR(L117,0))) -> 220000 | N117: =IF(M117="","",IF(F117="SI",M117*0.19,0)) -> 0 | O117: =IF(K117="","",M117+N117) -> 220000 | Q117: =IF(H117="","",VLOOKUP(H117,'Base de datos'!E:M,9,FALSE)) -> 161840 | R117: =IF(Q117="","",SUMIF($B:$B,B117,$Q:$Q)) -> 161840
A118: =B118&"-"&C118 -> 70-1 | B118: 70 | C118: =IF(B118="","",COUNTIF($B$4:B118,B118)) -> 1 | D118: {=IF(B118="","",IFERROR( INDEX(R_COTIZACIONES!D:D,MATCH(B118,R_COTIZACIONES!A:A,0)), ""))} -> Condominio Ossandon | E118: {=IF(B118="","",IFERROR( INDEX(R_COTIZACIONES!C:C,MATCH(B118,R_COTIZACIONES!A:A,0)), ""))} -> 65.066.845-6 | F118: Si | G118: Particular | H118: S07 | I118: =IF(H118="","",VLOOKUP(H118,'Base de datos'!$E:$G,3,FALSE)) -> Mantención programada | J118: 2 | K118: 150000 | L118: 0 | M118: =IF(K118="","",J118*K118*(1-IFERROR(L118,0))) -> 300000 | N118: =IF(M118="","",IF(F118="SI",M118*0.19,0)) -> 57000 | O118: =IF(K118="","",M118+N118) -> 357000 | Q118: =IF(H118="","",VLOOKUP(H118,'Base de datos'!E:M,9,FALSE)) -> 100000 | R118: =IF(Q118="","",SUMIF($B:$B,B118,$Q:$Q)) -> 100000
A119: =B119&"-"&C119 -> 71-1 | B119: 71 | C119: =IF(B119="","",COUNTIF($B$4:B119,B119)) -> 1 | D119: {=IF(B119="","",IFERROR( INDEX(R_COTIZACIONES!D:D,MATCH(B119,R_COTIZACIONES!A:A,0)), ""))} -> Condominio Bahia Horizonte | E119: {=IF(B119="","",IFERROR( INDEX(R_COTIZACIONES!C:C,MATCH(B119,R_COTIZACIONES!A:A,0)), ""))} -> 65.110.744-K | F119: Si | G119: APACOM | H119: D6KIT 3 | I119: =IF(H119="","",VLOOKUP(H119,'Base de datos'!$E:$G,3,FALSE)) -> D6 (6 crem, 2 controles 1 par de Photosmart Fotoceldas Inalámbricas) | J119: 1 | K119: 850000 | L119: 0.1 | M119: =IF(K119="","",J119*K119*(1-IFERROR(L119,0))) -> 765000 | N119: =IF(M119="","",IF(F119="SI",M119*0.19,0)) -> 145350 | O119: =IF(K119="","",M119+N119) -> 910350 | Q119: =IF(H119="","",VLOOKUP(H119,'Base de datos'!E:M,9,FALSE)) -> 346968 | R119: =IF(Q119="","",SUMIF($B:$B,B119,$Q:$Q)) -> 688808
A120: =B120&"-"&C120 -> 71-2 | B120: 71 | C120: =IF(B120="","",COUNTIF($B$4:B120,B120)) -> 2 | D120: {=IF(B120="","",IFERROR( INDEX(R_COTIZACIONES!D:D,MATCH(B120,R_COTIZACIONES!A:A,0)), ""))} -> Condominio Bahia Horizonte | E120: {=IF(B120="","",IFERROR( INDEX(R_COTIZACIONES!C:C,MATCH(B120,R_COTIZACIONES!A:A,0)), ""))} -> 65.110.744-K | F120: Si | G120: Particular | H120: S02 | I120: =IF(H120="","",VLOOKUP(H120,'Base de datos'!$E:$G,3,FALSE)) -> Instalación de motor (Kit) | J120: 1 | K120: 300000 | L120: 0.05 | M120: =IF(K120="","",J120*K120*(1-IFERROR(L120,0))) -> 285000 | N120: =IF(M120="","",IF(F120="SI",M120*0.19,0)) -> 54150 | O120: =IF(K120="","",M120+N120) -> 339150 | Q120: =IF(H120="","",VLOOKUP(H120,'Base de datos'!E:M,9,FALSE)) -> 180000 | R120: =IF(Q120="","",SUMIF($B:$B,B120,$Q:$Q)) -> 688808
A121: =B121&"-"&C121 -> 71-3 | B121: 71 | C121: =IF(B121="","",COUNTIF($B$4:B121,B121)) -> 3 | D121: {=IF(B121="","",IFERROR( INDEX(R_COTIZACIONES!D:D,MATCH(B121,R_COTIZACIONES!A:A,0)), ""))} -> Condominio Bahia Horizonte | E121: {=IF(B121="","",IFERROR( INDEX(R_COTIZACIONES!C:C,MATCH(B121,R_COTIZACIONES!A:A,0)), ""))} -> 65.110.744-K | F121: Si | G121: RW | H121: WP17 | I121: =IF(H121="","",VLOOKUP(H121,'Base de datos'!$E:$G,3,FALSE)) -> Controlador Wifi WP17 | J121: 1 | K121: 220000 | L121: 0.05 | M121: =IF(K121="","",J121*K121*(1-IFERROR(L121,0))) -> 209000 | N121: =IF(M121="","",IF(F121="SI",M121*0.19,0)) -> 39710 | O121: =IF(K121="","",M121+N121) -> 248710 | Q121: =IF(H121="","",VLOOKUP(H121,'Base de datos'!E:M,9,FALSE)) -> 161840 | R121: =IF(Q121="","",SUMIF($B:$B,B121,$Q:$Q)) -> 688808
A122: =B122&"-"&C122 -> 72-1 | B122: 72 | C122: =IF(B122="","",COUNTIF($B$4:B122,B122)) -> 1 | D122: {=IF(B122="","",IFERROR( INDEX(R_COTIZACIONES!D:D,MATCH(B122,R_COTIZACIONES!A:A,0)), ""))} -> Condominio Bahia Horizonte | E122: {=IF(B122="","",IFERROR( INDEX(R_COTIZACIONES!C:C,MATCH(B122,R_COTIZACIONES!A:A,0)), ""))} -> 65.110.744-K | F122: Si | G122: APACOM | H122: D10TKIT 2 | I122: =IF(H122="","",VLOOKUP(H122,'Base de datos'!$E:$G,3,FALSE)) -> D10 (6 crem, 2 controles 1 par de Photosmart Fotoceldas Inalámbricas) | J122: 1 | K122: 1250000 | L122: 0.05 | M122: =IF(K122="","",J122*K122*(1-IFERROR(L122,0))) -> 1187500 | N122: =IF(M122="","",IF(F122="SI",M122*0.19,0)) -> 225625 | O122: =IF(K122="","",M122+N122) -> 1413125 | Q122: =IF(H122="","",VLOOKUP(H122,'Base de datos'!E:M,9,FALSE)) -> 406788.5 | R122: =IF(Q122="","",SUMIF($B:$B,B122,$Q:$Q)) -> 748628.5
... A125: =B125&"-"&C125 -> 73-1 | B125: 73 | C125: =IF(B125="","",COUNTIF($B$4:B125,B125)) -> 1 | D125: {=IF(B125="","",IFERROR( INDEX(R_COTIZACIONES!D:D,MATCH(B125,R_COTIZACIONES!A:A,0)), ""))} -> Condominio Ossandon | E125: {=IF(B125="","",IFERROR( INDEX(R_COTIZACIONES!C:C,MATCH(B125,R_COTIZACIONES!A:A,0)), ""))} -> 65.066.845-6 | F125: no | G125: RW | H125: D10S | I125: =IF(H125="","",VLOOKUP(H125,'Base de datos'!$E:$G,3,FALSE)) -> D10 Standard | J125: 1 | K125: 1000000 | L125: 0 | M125: =IF(K125="","",J125*K125*(1-IFERROR(L125,0))) -> 1000000 | N125: =IF(M125="","",IF(F125="SI",M125*0.19,0)) -> 0 | O125: =IF(K125="","",M125+N125) -> 1000000 | Q125: =IF(H125="","",VLOOKUP(H125,'Base de datos'!E:M,9,FALSE)) -> 383410.8 | R125: =IF(Q125="","",SUMIF($B:$B,B125,$Q:$Q)) -> 705250.8
A126: =B126&"-"&C126 -> 73-2 | B126: 73 | C126: 2 | D126: {=IF(B126="","",IFERROR( INDEX(R_COTIZACIONES!D:D,MATCH(B126,R_COTIZACIONES!A:A,0)), ""))} -> Condominio Ossandon | E126: {=IF(B126="","",IFERROR( INDEX(R_COTIZACIONES!C:C,MATCH(B126,R_COTIZACIONES!A:A,0)), ""))} -> 65.066.845-6 | F126: no | G126: RW | H126: WP17 | I126: =IF(H126="","",VLOOKUP(H126,'Base de datos'!$E:$G,3,FALSE)) -> Controlador Wifi WP17 | J126: 1 | K126: 200000 | L126: 0 | M126: =IF(K126="","",J126*K126*(1-IFERROR(L126,0))) -> 200000 | N126: =IF(M126="","",IF(F126="SI",M126*0.19,0)) -> 0 | O126: =IF(K126="","",M126+N126) -> 200000 | Q126: =IF(H126="","",VLOOKUP(H126,'Base de datos'!E:M,9,FALSE)) -> 161840 | R126: =IF(Q126="","",SUMIF($B:$B,B126,$Q:$Q)) -> 705250.8
A127: =B127&"-"&C127 -> 73-3 | B127: 73 | C127: =IF(B127="","",COUNTIF($B$4:B127,B127)) -> 3 | D127: {=IF(B127="","",IFERROR( INDEX(R_COTIZACIONES!D:D,MATCH(B127,R_COTIZACIONES!A:A,0)), ""))} -> Condominio Ossandon | E127: {=IF(B127="","",IFERROR( INDEX(R_COTIZACIONES!C:C,MATCH(B127,R_COTIZACIONES!A:A,0)), ""))} -> 65.066.845-6 | F127: Si | G127: Particular | H127: S01 | I127: =IF(H127="","",VLOOKUP(H127,'Base de datos'!$E:$G,3,FALSE)) -> Instalación de motor (Solo) | J127: 1 | K127: 100000 | L127: 0 | M127: =IF(K127="","",J127*K127*(1-IFERROR(L127,0))) -> 100000 | N127: =IF(M127="","",IF(F127="SI",M127*0.19,0)) -> 19000 | O127: =IF(K127="","",M127+N127) -> 119000 | Q127: =IF(H127="","",VLOOKUP(H127,'Base de datos'!E:M,9,FALSE)) -> 60000 | R127: =IF(Q127="","",SUMIF($B:$B,B127,$Q:$Q)) -> 705250.8
A128: =B128&"-"&C128 -> 73-4 | B128: 73 | C128: =IF(B128="","",COUNTIF($B$4:B128,B128)) -> 4 | D128: {=IF(B128="","",IFERROR( INDEX(R_COTIZACIONES!D:D,MATCH(B128,R_COTIZACIONES!A:A,0)), ""))} -> Condominio Ossandon | E128: {=IF(B128="","",IFERROR( INDEX(R_COTIZACIONES!C:C,MATCH(B128,R_COTIZACIONES!A:A,0)), ""))} -> 65.066.845-6 | F128: Si | G128: Particular | H128: S07 | I128: =IF(H128="","",VLOOKUP(H128,'Base de datos'!$E:$G,3,FALSE)) -> Mantención programada | J128: 1 | K128: 150000 | L128: 0 | M128: =IF(K128="","",J128*K128*(1-IFERROR(L128,0))) -> 150000 | N128: =IF(M128="","",IF(F128="SI",M128*0.19,0)) -> 28500 | O128: =IF(K128="","",M128+N128) -> 178500 | Q128: =IF(H128="","",VLOOKUP(H128,'Base de datos'!E:M,9,FALSE)) -> 100000 | R128: =IF(Q128="","",SUMIF($B:$B,B128,$Q:$Q)) -> 705250.8
A129: =B129&"-"&C129 -> 74-1 | B129: 74 | C129: =IF(B129="","",COUNTIF($B$4:B129,B129)) -> 1 | D129: {=IF(B129="","",IFERROR( INDEX(R_COTIZACIONES!D:D,MATCH(B129,R_COTIZACIONES!A:A,0)), ""))} -> Condominio Jardines del Pacífico | E129: {=IF(B129="","",IFERROR( INDEX(R_COTIZACIONES!C:C,MATCH(B129,R_COTIZACIONES!A:A,0)), ""))} -> 53.330.222-K | F129: no | G129: Particular | H129: S13 | I129: =IF(H129="","",VLOOKUP(H129,'Base de datos'!$E:$G,3,FALSE)) -> Servicio de mantenimiento CCTV central. | J129: 1 | K129: 200000 | M129: =IF(K129="","",J129*K129*(1-IFERROR(L129,0))) -> 200000 | N129: =IF(M129="","",IF(F129="SI",M129*0.19,0)) -> 0 | O129: =IF(K129="","",M129+N129) -> 200000 | Q129: =IF(H129="","",VLOOKUP(H129,'Base de datos'!E:M,9,FALSE)) -> 252100.84 | R129: =IF(Q129="","",SUMIF($B:$B,B129,$Q:$Q)) -> 252100.84
A130: =B130&"-"&C130 -> 75-1 | B130: 75 | C130: =IF(B130="","",COUNTIF($B$4:B130,B130)) -> 1 | D130: {=IF(B130="","",IFERROR( INDEX(R_COTIZACIONES!D:D,MATCH(B130,R_COTIZACIONES!A:A,0)), ""))} -> Condominio Ossandon | E130: {=IF(B130="","",IFERROR( INDEX(R_COTIZACIONES!C:C,MATCH(B130,R_COTIZACIONES!A:A,0)), ""))} -> 65.066.845-6 | F130: no | G130: Otro | H130: RC20 | I130: =IF(H130="","",VLOOKUP(H130,'Base de datos'!$E:$G,3,FALSE)) -> Archer C20 | J130: 1 | K130: 30000 | L130: 0 | M130: =IF(K130="","",J130*K130*(1-IFERROR(L130,0))) -> 30000 | N130: =IF(M130="","",IF(F130="SI",M130*0.19,0)) -> 0 | O130: =IF(K130="","",M130+N130) -> 30000 | Q130: =IF(H130="","",VLOOKUP(H130,'Base de datos'!E:M,9,FALSE)) -> 15220.8 | R130: =IF(Q130="","",SUMIF($B:$B,B130,$Q:$Q)) -> 15220.8
A131: =B131&"-"&C131 -> 75-2 | B131: 75 | C131: =IF(B131="","",COUNTIF($B$4:B131,B131)) -> 2 | D131: {=IF(B131="","",IFERROR( INDEX(R_COTIZACIONES!D:D,MATCH(B131,R_COTIZACIONES!A:A,0)), ""))} -> Condominio Ossandon | E131: {=IF(B131="","",IFERROR( INDEX(R_COTIZACIONES!C:C,MATCH(B131,R_COTIZACIONES!A:A,0)), ""))} -> 65.066.845-6 | F131: Si | G131: Particular | H131: SEMT | I131: =IF(H131="","",VLOOKUP(H131,'Base de datos'!$E:$G,3,FALSE)) -> Servicio de instalación de punto eléctrico x mt | J131: 1 | K131: 60000 | L131: 0 | M131: =IF(K131="","",J131*K131*(1-IFERROR(L131,0))) -> 60000 | O131: =IF(K131="","",M131+N131) -> 60000 | Q131: =IF(H131="","",VLOOKUP(H131,'Base de datos'!E:M,9,FALSE)) -> 0 | R131: =IF(Q131="","",SUMIF($B:$B,B131,$Q:$Q)) -> 15220.8
A132: =B132&"-"&C132 -> 76-1 | B132: 76 | C132: =IF(B132="","",COUNTIF($B$4:B132,B132)) -> 1 | D132: {=IF(B132="","",IFERROR( INDEX(R_COTIZACIONES!D:D,MATCH(B132,R_COTIZACIONES!A:A,0)), ""))} -> Condominio Bahia Horizonte | E132: {=IF(B132="","",IFERROR( INDEX(R_COTIZACIONES!C:C,MATCH(B132,R_COTIZACIONES!A:A,0)), ""))} -> 65.110.744-K | F132: Si | G132: Particular | H132: S14 | I132: =IF(H132="","",VLOOKUP(H132,'Base de datos'!$E:$G,3,FALSE)) -> Servicio de mantenimiento y renovacion/acondicionamiento de central CCTV Fase I | J132: 1 | K132: 680000 | L132: 0 | M132: =IF(K132="","",J132*K132*(1-IFERROR(L132,0))) -> 680000 | O132: =IF(K132="","",M132+N132) -> 680000 | Q132: =IF(H132="","",VLOOKUP(H132,'Base de datos'!E:M,9,FALSE)) -> 857142.86 | R132: =IF(Q132="","",SUMIF($B:$B,B132,$Q:$Q)) -> 857142.86
A133: =B133&"-"&C133 -> 77-1 | B133: 77 | C133: =IF(B133="","",COUNTIF($B$4:B133,B133)) -> 1 | D133: {=IF(B133="","",IFERROR( INDEX(R_COTIZACIONES!D:D,MATCH(B133,R_COTIZACIONES!A:A,0)), ""))} -> Condominio Bahia Horizonte | E133: {=IF(B133="","",IFERROR( INDEX(R_COTIZACIONES!C:C,MATCH(B133,R_COTIZACIONES!A:A,0)), ""))} -> 65.110.744-K | F133: Si | G133: Particular | H133: S15 | I133: =IF(H133="","",VLOOKUP(H133,'Base de datos'!$E:$G,3,FALSE)) -> Servicio de implementación de infraestructura base y plataforma CCTV IP Fase II | J133: 1 | K133: 3334000 | L133: 0 | M133: =IF(K133="","",J133*K133*(1-IFERROR(L133,0))) -> 3334000 | O133: =IF(K133="","",M133+N133) -> 3334000 | Q133: =IF(H133="","",VLOOKUP(H133,'Base de datos'!E:M,9,FALSE)) -> 4202521 | R133: =IF(Q133="","",SUMIF($B:$B,B133,$Q:$Q)) -> 4202521
A134: =B134&"-"&C134 -> 78-1 | B134: 78 | C134: =IF(B134="","",COUNTIF($B$4:B134,B134)) -> 1 | D134: {=IF(B134="","",IFERROR( INDEX(R_COTIZACIONES!D:D,MATCH(B134,R_COTIZACIONES!A:A,0)), ""))} -> Condominio Bahia Horizonte | E134: {=IF(B134="","",IFERROR( INDEX(R_COTIZACIONES!C:C,MATCH(B134,R_COTIZACIONES!A:A,0)), ""))} -> 65.110.744-K | F134: Si | G134: Particular | H134: S16 | I134: =IF(H134="","",VLOOKUP(H134,'Base de datos'!$E:$G,3,FALSE)) -> Servicio de instalación CCTV IP en acccesos peatonales a las torres y piscina Fase III | J134: 1 | K134: 1590000 | L134: 0 | M134: =IF(K134="","",J134*K134*(1-IFERROR(L134,0))) -> 1590000 | O134: =IF(K134="","",M134+N134) -> 1590000 | Q134: =IF(H134="","",VLOOKUP(H134,'Base de datos'!E:M,9,FALSE)) -> 2004201.7 | R134: =IF(Q134="","",SUMIF($B:$B,B134,$Q:$Q)) -> 2004201.7
...

Sheet Consolidado de Venta
B2: Periodo: | C2: 2024 | D2: 1
B3: =VLOOKUP(C2,RegiPeri,2,FALSE) -> #REF! | C3: =VLOOKUP(C2,RegiPeri,3,FALSE) -> #REF!
B5: Ventas generales | C5: Cantidad Doc. | D5: Neto | E5: IVA | F5: Total
B6: Total Ventas | C6: =COUNTIFS(RegiCotiFech,">="&B3,RegiCotiFech,"<="&C3,RegiCotiVent,"SI") -> 0 | D6: =SUMIFS(RegiCotiNeto,RegiCotiFech,">="&B3,RegiCotiFech,"<="&C3) -> #N/A | E6: =SUMIFS(RegiCotiIVA,RegiCotiFech,">="&B3,RegiCotiFech,"<="&C3) -> #N/A | F6: =SUMIFS(RegiCotiTota,RegiCotiFech,">="&B3,RegiCotiFech,"<="&C3) -> #N/A
B7: Total Motores Vendidos | C7: =SUMIFS(RegiDetaCant,RegiDetaFech,">="&B3,RegiDetaFech,"<="&C3,RegiDetaPlan,"Motor") -> #N/A | D7: =SUMIFS(RegiDetaSub,RegiDetaFech,">="&B3,RegiDetaFech,"<="&C3,RegiDetaPlan,"Motor") -> #N/A | E7: =SUMIFS(RegiDetaIVA,RegiDetaFech,">="&B3,RegiDetaFech,"<="&C3,RegiDetaPlan,"Motor") -> #N/A | F7: =SUMIFS(RegiDetaTota,RegiDetaFech,">="&B3,RegiDetaFech,"<="&C3,RegiDetaPlan,"Motor") -> #N/A
B8: Total Productos y servicios | C8: =SUMIFS(RegiDetaCant,RegiDetaFech,">="&B3,RegiDetaFech,"<="&C3) -> #N/A
B11: Total Facturas | C11: =COUNTIFS(RegiCotiFech,">="&B3,RegiCotiFech,"<="&C3,RegiCotiVent,"SI",RegiCotiDocu,"Factura") -> 0 | D11: =SUMIFS(RegiCotiNeto,RegiCotiFech,">="&B3,RegiCotiFech,"<="&C3,RegiCotiDocu,"Factura") -> #N/A | E11: =SUMIFS(RegiCotiIVA,RegiCotiFech,">="&B3,RegiCotiFech,"<="&C3,RegiCotiDocu,"Factura") -> #N/A | F11: =SUMIFS(RegiCotiTota,RegiCotiFech,">="&B3,RegiCotiFech,"<="&C3,RegiCotiDocu,"Factura") -> #N/A
B12: Total Sin Documento | C12: =COUNTIFS(RegiCotiFech,">="&B3,RegiCotiFech,"<="&C3,RegiCotiVent,"SI",RegiCotiDocu,"SD") -> 0 | D12: =SUMIFS(RegiCotiNeto,RegiCotiFech,">="&B3,RegiCotiFech,"<="&C3,RegiCotiDocu,"SD") -> #N/A | E12: =SUMIFS(RegiCotiIVA,RegiCotiFech,">="&B3,RegiCotiFech,"<="&C3,RegiCotiDocu,"SD") -> #N/A | F12: =SUMIFS(RegiCotiTota,RegiCotiFech,">="&B3,RegiCotiFech,"<="&C3,RegiCotiDocu,"SD") -> #N/A

Sheet Hoja 5
B5: Característica | C5: D10 SMART | D5: D6 SMART
B6: Capacidad de Carga | C6: Hasta 1000 kg | D6: Hasta 600 kg
B7: Velocidad Máxima | C7: Hasta 26 m/min | D7: Hasta 36 m/min
B8: Ciclos Diarios | C8: 750 operaciones | D8: 150 operaciones
B9: Fuerza de Empuje (Nominal) | C9: 30 kgf | D9: 17 kgf
B10: Longitud Máxima de Puerta | C10: 50 m | D10: 100 m
A14: Cot 71
A15: Total | B15: Inicial | C15: Saldo (30 días)
A17: 1500000 | B17: 750000 | C17: 750000
A19: Cot 72 | B19: Inicial | C19: Saldo (30 días) | D19: Saldo (60 días)
A20: Total
A21: 2000000 | B21: 666666 | C21: 666666 | D21: 666666

Sheet csv
A1: codigo | B1: nombre | C1: descripcion | D1: precio | E1: unidad | F1: categoria | G1: proveedor | H1: tipo
A2: N32 | B2: NVR | C2: NVR4232-4KS3 | D2: 304518.4 | E2: un | F2: producto | G2: Smartsecure | H2: producto
A3: N32-E | B3: NVR | C3: NVR4232-4KS3 | D3: 291200 | E3: un | F3: producto | G3: Smartsecure | H3: producto
A4: H4TB | B4: HDD 4 TB | C4: ST4000VX015 | D4: 216153.6 | E4: un | F4: producto | G4: Smartsecure | H4: producto
A5: H6TB | B5: HDD 6 TB | C5: WD60EFFX | D5: 351984 | E5: un | F5: producto | G5: Smartsecure | H5: producto
A6: UPS15 | B6: UPS 1500 VA | C6: DH-PFM350-900-A | D6: 134780.8 | E6: un | F6: producto | G6: Smartsecure | H6: producto
A7: UPS15 | B7: UPS 1500 VA | C7: MR-UF1500 | D7: 187185.6 | E7: un | F7: producto | G7: Smartsecure | H7: producto
A8: SW24 | B8: Switch 24 | C8: DH-CS4228-24GT-240 | D8: 559280 | E8: un | F8: producto | G8: Smartsecure | H8: producto
A9: SW24 | B9: Switch 24 | C9: DH-CS4228-24GT-240 | D9: 384337.6 | E9: un | F9: producto | G9: Smartsecure | H9: producto
A10: SW8 | B10: Switch 8 | C10: DH-PFS3010-8ET-65 | D10: 101764.8 | E10: un | F10: producto | G10: Smartsecure | H10: producto
A11: SW8 | B11: Switch 8 | C11: POE208-100MB | D11: 58240 | E11: un | F11: producto | G11: Smartsecure | H11: producto
A12: SW4 | B12: Switch 4 | C12: DH-PFS3006-4ET-36 | D12: 56126.4 | E12: un | F12: producto | G12: Smartsecure | H12: producto
A13: SW4 | B13: Switch 4 | C13: POE204-100MB | D13: 37760 | E13: un | F13: producto | G13: Smartsecure | H13: producto
... A21: 2249S | B21: Cámara Bullet | C21: DH-IPC-HFW2249S-S-IL | D21: 93227.4 | E21: un | F21: producto | G21: Smartsecure | H21: producto
A22: 304020 | B22: Gabinete exteriores | C22: Gabinete Mural-304020 | D22: 60784 | E22: un | F22: producto | G22: Smartsecure | H22: producto
A23: 604550 | B23: Rack Gabinete interior | C23: Gabinete Rack 6U Dahua 600x450x501 | D23: 150512 | E23: un | F23: producto | G23: Smartsecure | H23: producto
A24: 534020 | B24: Rack Gabinete interior | C24: Gabinete Rack 4U Dahua 530X400X200 | D24: 97492.8 | E24: un | F24: producto | G24: Smartsecure | H24: producto
A25: 534060 | B25: Rack Gabinete interior | C25: Gabinete Rack 12U Dahua 530x400x600 | D25: 163440 | E25: un | F25: producto | G25: Smartsecure | H25: producto
A26: PATCH24 | B26: Patch panel | C26: Patch panel 24 puertos Cat 6 | D26: 24800 | E26: un | F26: producto | G26: Smartsecure | H26: producto
A27: PATCH24 | B27: Patch panel | C27: Patch panel 24 puertos Cat 6 | D27: 58072 | E27: un | F27: producto | G27: Smartsecure | H27: producto
A28: PATCH972 | B28: Patch cord | C28: DH-PFM972-6U-2-S | D28: 3689.6 | E28: un | F28: producto | G28: Smartsecure | H28: producto
A29: CAT6305 | B29: Caja de cable Cat 6 305 | C29: DH-PFM923I-6UN-C | D29: 216929.6 | E29: un | F29: producto | G29: Smartsecure | H29: producto
A30: CAT6100 | B30: Caja de cable Cat 6 100 | C30: DH-PFM920I-6UN-C-100 | D30: 76518.4 | E30: un | F30: producto | G30: Smartsecure | H30: producto
A31: CAN10050 | B31: Canaletas troncal 100x50 | C31: CANAL100X50 | D31: 12744 | E31: un | F31: producto | G31: Smartsecure | H31: producto
A32: CAE100100 | B32: Caja estanca 100x100 | C32: Cono 10010070 | D32: 3920 | E32: un | F32: producto | G32: Smartsecure | H32: producto
A33: D10S | B33: Motor Corredera | C33: D10 Standard | D33: 1022428.8 | E33: un | F33: producto | G33: APACOM | H33: producto
A34: D10S | B34: Motor Corredera | C34: D10 Standard | D34: 1024332.8 | E34: un | F34: producto | G34: APACOM | H34: producto
A35: D10SKIT | B35: Motor Corredera | C35: D10 Standard Kit 1(6 crem y 2 controles) | D35: 1120000 | E35: kit | F35: producto | G35: APACOM | H35: producto
A36: D10SKIT | B36: Motor Corredera | C36: D10 Standard Kit 1(6 crem y 2 controles) | D36: 1102281.6 | E36: kit | F36: producto | G36: APACOM | H36: producto
A37: D10T | B37: Motor Corredera | C37: D10 Turbo | D37: 1129004.8 | E37: un | F37: producto | G37: APACOM | H37: producto
... A100: PROYECTO | B100: PROYECTO | C100: Proyecto asociado a propuesta (revisar adjuntos) | D100: 9775850 | E100: un | F100: proyecto | G100: Particular | H100: servicio
